Workbook

Sheet FB Laser
AA1: Notes
Y2: Outsource | Z2: 0
Y3: Programming Fee | Z3: 60
Y4: Welding (in-house) | Z4: =IF(Welding!G10="Flat",Welding!E10+Welding!D6,IF(Welding!G10="Flat&Tube",(Welding!E10+Welding!D6)/2,0)) -> 0
Y5: Hardware | Z5: 0
Y6: QC | Z6: 0
Y7: Material Source | Z7: JWMCD | AB7: User Defined
Y8: Pallet Cost | Z8: =IF(AA8="Default",(ROUNDUP((AC34/1500),0)*30),IF(AA8="User Defined",AB8,"Need Input")) -> 0 | AA8: Default | AB8: 0
A9: dwg# | B9: Qty | C9: Length (in) | D9: Width (in) | E9: Laser Time Lot (min) | F9: Notes? | G9: Laser Cost (Each) | H9: Forming Cost (Each) | I9: Hardware Install (Each) | J9: Machining (Each) | K9: Finishing (Each) | L9: Labor (Each) | M9: sqft (Each) | N9: Material ID | O9: % Material Used | P9: Material Cost (LOT) | Q9: Material PRICE (EACH) | R9: Adjustment | S9: Total Cost (Each) | T9: Total Price (Each) | U9: Cost Lot | V9: Price Lot | W9: Price/Lbs | Y9: Delivery Cost | Z9: =IF(AA9="Delivery",ROUNDUP((AC34/8000),0)*100,IF(AA9="Will-Call",0,"Need Input")) -> 0 | AA9: Delivery
G10: =IFERROR(((E10/60)*$Z$10)/B10,"") | H10: =IF(Forming!G10>0,Forming!G10,0) -> 0 | I10: =IF('Hardware Install'!E10>0,'Hardware Install'!E10,0) -> 0 | J10: =IFERROR(VLOOKUP('FB Laser'!A10,Machining!A10:G100,7,FALSE),"") | K10: =IFERROR(IF(Finishing!G10>0,VLOOKUP('FB Laser'!A10,Finishing!A10:G100,7,FALSE),""),"") | L10: =IFERROR(SUM((H10*$Z$12),G10,I10,J10,K10,'FB Data'!AM9),"") -> 0 | M10: =IFERROR((C10*D10)*0.00694,"") -> 0 | O10: =IFERROR((B10*M10)/(VLOOKUP(N10,$Y$15:$AB$33,2,FALSE)),"") | P10: =IFERROR(VLOOKUP(N10,$Y$15:$AB$33,4,FALSE)*(O10/(VLOOKUP(N10,$Y$15:$AB$33,3,FALSE))),"") | Q10: =IFERROR((P10*$Z$11)/B10,"") | S10: =IFERROR(L10+Q10+($Z$8/$B$100)+($Z$9/$B$100)+($Z$3/$B$100)+($Z$2/$B$100)+($Z$4/$B$100)+($Z$5/$B$100)+($Z$6/$B$100),"") | T10: =IFERROR(ROUND(S10*'Quote Info'!$O$4+R10,2),"") | U10: =IFERROR(S10*B10,"") | V10: =IFERROR(T10*B10,"") | W10: =IFERROR(S10/((VLOOKUP(N10,'FB Data'!$A$2:$E$150,3,FALSE))*'FB Laser'!M10),"") | Y10: Laser/Hr (Cost) | Z10: 112.24 | AA10: =Z10*'Quote Info'!O4 -> 152.6464
G11: =IFERROR(((E11/60)*$Z$10)/B11,"") | H11: =IF(Forming!G11>0,Forming!G11,0) -> 0 | I11: =IF('Hardware Install'!E11>0,'Hardware Install'!E11,0) -> 0 | J11: =IFERROR(VLOOKUP('FB Laser'!A11,Machining!A11:G101,7,FALSE),"") | K11: =IFERROR(IF(Finishing!G11>0,VLOOKUP('FB Laser'!A11,Finishing!A11:G101,7,FALSE),""),"") | L11: =IFERROR(SUM((H11*$Z$12),G11,I11,J11,K11,'FB Data'!AM10),"") -> 0 | M11: =IFERROR((C11*D11)*0.00694,"") -> 0 | O11: =IFERROR((B11*M11)/(VLOOKUP(N11,$Y$15:$AB$33,2,FALSE)),"") | P11: =IFERROR(VLOOKUP(N11,$Y$15:$AB$33,4,FALSE)*(O11/(VLOOKUP(N11,$Y$15:$AB$33,3,FALSE))),"") | Q11: =IFERROR((P11*$Z$11)/B11,"") | S11: =IFERROR(L11+Q11+($Z$8/$B$100)+($Z$9/$B$100)+($Z$3/$B$100)+($Z$2/$B$100)+($Z$4/$B$100)+($Z$5/$B$100)+($Z$6/$B$100),"") | T11: =IFERROR(ROUND(S11*'Quote Info'!$O$4+R11,2),"") | U11: =IFERROR(S11*B11,"") | V11: =IFERROR(T11*B11,"") | W11: =IFERROR(S11/((VLOOKUP(N11,'FB Data'!$A$2:$E$150,3,FALSE))*'FB Laser'!M11),"") | Y11: Material Mark-Up | Z11: 1
G12: =IFERROR(((E12/60)*$Z$10)/B12,"") | H12: =IF(Forming!G12>0,Forming!G12,0) -> 0 | I12: =IF('Hardware Install'!E12>0,'Hardware Install'!E12,0) -> 0 | J12: =IFERROR(VLOOKUP('FB Laser'!A12,Machining!A12:G102,7,FALSE),"") | K12: =IFERROR(IF(Finishing!G12>0,VLOOKUP('FB Laser'!A12,Finishing!A12:G102,7,FALSE),""),"") | L12: =IFERROR(SUM((H12*$Z$12),G12,I12,J12,K12,'FB Data'!AM11),"") -> 0 | M12: =IFERROR((C12*D12)*0.00694,"") -> 0 | O12: =IFERROR((B12*M12)/(VLOOKUP(N12,$Y$15:$AB$33,2,FALSE)),"") | P12: =IFERROR(VLOOKUP(N12,$Y$15:$AB$33,4,FALSE)*(O12/(VLOOKUP(N12,$Y$15:$AB$33,3,FALSE))),"") | Q12: =IFERROR((P12*$Z$11)/B12,"") | S12: =IFERROR(L12+Q12+($Z$8/$B$100)+($Z$9/$B$100)+($Z$3/$B$100)+($Z$2/$B$100)+($Z$4/$B$100)+($Z$5/$B$100)+($Z$6/$B$100),"") | T12: =IFERROR(ROUND(S12*'Quote Info'!$O$4+R12,2),"") | U12: =IFERROR(S12*B12,"") | V12: =IFERROR(T12*B12,"") | W12: =IFERROR(S12/((VLOOKUP(N12,'FB Data'!$A$2:$E$150,3,FALSE))*'FB Laser'!M12),"") | Y12: Forming Mark-Up | Z12: 1
G13: =IFERROR(((E13/60)*$Z$10)/B13,"") | H13: =IF(Forming!G13>0,Forming!G13,0) -> 0 | I13: =IF('Hardware Install'!E13>0,'Hardware Install'!E13,0) -> 0 | J13: =IFERROR(VLOOKUP('FB Laser'!A13,Machining!A13:G103,7,FALSE),"") | K13: =IFERROR(IF(Finishing!G13>0,VLOOKUP('FB Laser'!A13,Finishing!A13:G103,7,FALSE),""),"") | L13: =IFERROR(SUM((H13*$Z$12),G13,I13,J13,K13,'FB Data'!AM12),"") -> 0 | M13: =IFERROR((C13*D13)*0.00694,"") -> 0 | O13: =IFERROR((B13*M13)/(VLOOKUP(N13,$Y$15:$AB$33,2,FALSE)),"") | P13: =IFERROR(VLOOKUP(N13,$Y$15:$AB$33,4,FALSE)*(O13/(VLOOKUP(N13,$Y$15:$AB$33,3,FALSE))),"") | Q13: =IFERROR((P13*$Z$11)/B13,"") | S13: =IFERROR(L13+Q13+($Z$8/$B$100)+($Z$9/$B$100)+($Z$3/$B$100)+($Z$2/$B$100)+($Z$4/$B$100)+($Z$5/$B$100)+($Z$6/$B$100),"") | T13: =IFERROR(ROUND(S13*'Quote Info'!$O$4+R13,2),"") | U13: =IFERROR(S13*B13,"") | V13: =IFERROR(T13*B13,"") | W13: =IFERROR(S13/((VLOOKUP(N13,'FB Data'!$A$2:$E$150,3,FALSE))*'FB Laser'!M13),"")
G14: =IFERROR(((E14/60)*$Z$10)/B14,"") | H14: =IF(Forming!G14>0,Forming!G14,0) -> 0 | I14: =IF('Hardware Install'!E14>0,'Hardware Install'!E14,0) -> 0 | J14: =IFERROR(VLOOKUP('FB Laser'!A14,Machining!A14:G104,7,FALSE),"") | K14: =IFERROR(IF(Finishing!G14>0,VLOOKUP('FB Laser'!A14,Finishing!A14:G104,7,FALSE),""),"") | L14: =IFERROR(SUM((H14*$Z$12),G14,I14,J14,K14,'FB Data'!AM13),"") -> 0 | M14: =IFERROR((C14*D14)*0.00694,"") -> 0 | O14: =IFERROR((B14*M14)/(VLOOKUP(N14,$Y$15:$AB$33,2,FALSE)),"") | P14: =IFERROR(VLOOKUP(N14,$Y$15:$AB$33,4,FALSE)*(O14/(VLOOKUP(N14,$Y$15:$AB$33,3,FALSE))),"") | Q14: =IFERROR((P14*$Z$11)/B14,"") | S14: =IFERROR(L14+Q14+($Z$8/$B$100)+($Z$9/$B$100)+($Z$3/$B$100)+($Z$2/$B$100)+($Z$4/$B$100)+($Z$5/$B$100)+($Z$6/$B$100),"") | T14: =IFERROR(ROUND(S14*'Quote Info'!$O$4+R14,2),"") | U14: =IFERROR(S14*B14,"") | V14: =IFERROR(T14*B14,"") | W14: =IFERROR(S14/((VLOOKUP(N14,'FB Data'!$A$2:$E$150,3,FALSE))*'FB Laser'!M14),"") | Y14: Material ID | Z14: Total Sqft | AA14: Yield % | AB14: Total Cost | AC14: Total Weight (lbs)
G15: =IFERROR(((E15/60)*$Z$10)/B15,"") | H15: =IF(Forming!G15>0,Forming!G15,0) -> 0 | I15: =IF('Hardware Install'!E15>0,'Hardware Install'!E15,0) -> 0 | J15: =IFERROR(VLOOKUP('FB Laser'!A15,Machining!A15:G105,7,FALSE),"") | K15: =IFERROR(IF(Finishing!G15>0,VLOOKUP('FB Laser'!A15,Finishing!A15:G105,7,FALSE),""),"") | L15: =IFERROR(SUM((H15*$Z$12),G15,I15,J15,K15,'FB Data'!AM14),"") -> 0 | M15: =IFERROR((C15*D15)*0.00694,"") -> 0 | O15: =IFERROR((B15*M15)/(VLOOKUP(N15,$Y$15:$AB$33,2,FALSE)),"") | P15: =IFERROR(VLOOKUP(N15,$Y$15:$AB$33,4,FALSE)*(O15/(VLOOKUP(N15,$Y$15:$AB$33,3,FALSE))),"") | Q15: =IFERROR((P15*$Z$11)/B15,"") | S15: =IFERROR(L15+Q15+($Z$8/$B$100)+($Z$9/$B$100)+($Z$3/$B$100)+($Z$2/$B$100)+($Z$4/$B$100)+($Z$5/$B$100)+($Z$6/$B$100),"") | T15: =IFERROR(ROUND(S15*'Quote Info'!$O$4+R15,2),"") | U15: =IFERROR(S15*B15,"") | V15: =IFERROR(T15*B15,"") | W15: =IFERROR(S15/((VLOOKUP(N15,'FB Data'!$A$2:$E$150,3,FALSE))*'FB Laser'!M15),"") | Y15: {=IFERROR(INDEX($Y$39:$Y$65, MATCH(0,IF(ISBLANK($Y$39:$Y$65),1,COUNTIF($Y$14:Y14, $Y$39:$Y$65)), 0)),"")} | Z15: =SUMIF($Y$39:$Y$65,Y15,$AC$39:$AC$65) -> 0 | AA15: =IFERROR(SUMIF($N$10:$N$99,Y15,$O$10:$O$99),"") -> 0 | AB15: =IFERROR(SUMIF($Y$39:$Y$65,Y15,$AD$39:$AD$65),"") -> 0 | AC15: =IFERROR(Z15*AA15*VLOOKUP(Y15,'FB Data'!$A$2:$E$150,3,FALSE),"")
G16: =IFERROR(((E16/60)*$Z$10)/B16,"") | H16: =IF(Forming!G16>0,Forming!G16,0) -> 0 | I16: =IF('Hardware Install'!E16>0,'Hardware Install'!E16,0) -> 0 | J16: =IFERROR(VLOOKUP('FB Laser'!A16,Machining!A16:G106,7,FALSE),"") | K16: =IFERROR(IF(Finishing!G16>0,VLOOKUP('FB Laser'!A16,Finishing!A16:G106,7,FALSE),""),"") | L16: =IFERROR(SUM((H16*$Z$12),G16,I16,J16,K16,'FB Data'!AM15),"") -> 0 | M16: =IFERROR((C16*D16)*0.00694,"") -> 0 | O16: =IFERROR((B16*M16)/(VLOOKUP(N16,$Y$15:$AB$33,2,FALSE)),"") | P16: =IFERROR(VLOOKUP(N16,$Y$15:$AB$33,4,FALSE)*(O16/(VLOOKUP(N16,$Y$15:$AB$33,3,FALSE))),"") | Q16: =IFERROR((P16*$Z$11)/B16,"") | S16: =IFERROR(L16+Q16+($Z$8/$B$100)+($Z$9/$B$100)+($Z$3/$B$100)+($Z$2/$B$100)+($Z$4/$B$100)+($Z$5/$B$100)+($Z$6/$B$100),"") | T16: =IFERROR(ROUND(S16*'Quote Info'!$O$4+R16,2),"") | U16: =IFERROR(S16*B16,"") | V16: =IFERROR(T16*B16,"") | W16: =IFERROR(S16/((VLOOKUP(N16,'FB Data'!$A$2:$E$150,3,FALSE))*'FB Laser'!M16),"") | Y16: {=IFERROR(INDEX($Y$39:$Y$65, MATCH(0,IF(ISBLANK($Y$39:$Y$65),1,COUNTIF($Y$14:Y15, $Y$39:$Y$65)), 0)),"")} | Z16: =SUMIF($Y$39:$Y$65,Y16,$AC$39:$AC$65) -> 0 | AA16: =IFERROR(SUMIF($N$10:$N$99,Y16,$O$10:$O$99),"") -> 0 | AB16: =IFERROR(SUMIF($Y$39:$Y$65,Y16,$AD$39:$AD$65),"") -> 0 | AC16: =IFERROR(Z16*AA16*VLOOKUP(Y16,'FB Data'!$A$2:$E$150,3,FALSE),"")
G17: =IFERROR(((E17/60)*$Z$10)/B17,"") | H17: =IF(Forming!G17>0,Forming!G17,0) -> 0 | I17: =IF('Hardware Install'!E17>0,'Hardware Install'!E17,0) -> 0 | J17: =IFERROR(VLOOKUP('FB Laser'!A17,Machining!A17:G107,7,FALSE),"") | K17: =IFERROR(IF(Finishing!G17>0,VLOOKUP('FB Laser'!A17,Finishing!A17:G107,7,FALSE),""),"") | L17: =IFERROR(SUM((H17*$Z$12),G17,I17,J17,K17,'FB Data'!AM16),"") -> 0 | M17: =IFERROR((C17*D17)*0.00694,"") -> 0 | O17: =IFERROR((B17*M17)/(VLOOKUP(N17,$Y$15:$AB$33,2,FALSE)),"") | P17: =IFERROR(VLOOKUP(N17,$Y$15:$AB$33,4,FALSE)*(O17/(VLOOKUP(N17,$Y$15:$AB$33,3,FALSE))),"") | Q17: =IFERROR((P17*$Z$11)/B17,"") | S17: =IFERROR(L17+Q17+($Z$8/$B$100)+($Z$9/$B$100)+($Z$3/$B$100)+($Z$2/$B$100)+($Z$4/$B$100)+($Z$5/$B$100)+($Z$6/$B$100),"") | T17: =IFERROR(ROUND(S17*'Quote Info'!$O$4+R17,2),"") | U17: =IFERROR(S17*B17,"") | V17: =IFERROR(T17*B17,"") | W17: =IFERROR(S17/((VLOOKUP(N17,'FB Data'!$A$2:$E$150,3,FALSE))*'FB Laser'!M17),"") | Y17: {=IFERROR(INDEX($Y$39:$Y$65, MATCH(0,IF(ISBLANK($Y$39:$Y$65),1,COUNTIF($Y$14:Y16, $Y$39:$Y$65)), 0)),"")} | Z17: =SUMIF($Y$39:$Y$65,Y17,$AC$39:$AC$65) -> 0 | AA17: =IFERROR(SUMIF($N$10:$N$99,Y17,$O$10:$O$99),"") -> 0 | AB17: =IFERROR(SUMIF($Y$39:$Y$65,Y17,$AD$39:$AD$65),"") -> 0 | AC17: =IFERROR(Z17*AA17*VLOOKUP(Y17,'FB Data'!$A$2:$E$150,3,FALSE),"")
G18: =IFERROR(((E18/60)*$Z$10)/B18,"") | H18: =IF(Forming!G18>0,Forming!G18,0) -> 0 | I18: =IF('Hardware Install'!E18>0,'Hardware Install'!E18,0) -> 0 | J18: =IFERROR(VLOOKUP('FB Laser'!A18,Machining!A18:G108,7,FALSE),"") | K18: =IFERROR(IF(Finishing!G18>0,VLOOKUP('FB Laser'!A18,Finishing!A18:G108,7,FALSE),""),"") | L18: =IFERROR(SUM((H18*$Z$12),G18,I18,J18,K18,'FB Data'!AM17),"") -> 0 | M18: =IFERROR((C18*D18)*0.00694,"") -> 0 | O18: =IFERROR((B18*M18)/(VLOOKUP(N18,$Y$15:$AB$33,2,FALSE)),"") | P18: =IFERROR(VLOOKUP(N18,$Y$15:$AB$33,4,FALSE)*(O18/(VLOOKUP(N18,$Y$15:$AB$33,3,FALSE))),"") | Q18: =IFERROR((P18*$Z$11)/B18,"") | S18: =IFERROR(L18+Q18+($Z$8/$B$100)+($Z$9/$B$100)+($Z$3/$B$100)+($Z$2/$B$100)+($Z$4/$B$100)+($Z$5/$B$100)+($Z$6/$B$100),"") | T18: =IFERROR(ROUND(S18*'Quote Info'!$O$4+R18,2),"") | U18: =IFERROR(S18*B18,"") | V18: =IFERROR(T18*B18,"") | W18: =IFERROR(S18/((VLOOKUP(N18,'FB Data'!$A$2:$E$150,3,FALSE))*'FB Laser'!M18),"") | Y18: {=IFERROR(INDEX($Y$39:$Y$65, MATCH(0,IF(ISBLANK($Y$39:$Y$65),1,COUNTIF($Y$14:Y17, $Y$39:$Y$65)), 0)),"")} | Z18: =SUMIF($Y$39:$Y$65,Y18,$AC$39:$AC$65) -> 0 | AA18: =IFERROR(SUMIF($N$10:$N$99,Y18,$O$10:$O$99),"") -> 0 | AB18: =IFERROR(SUMIF($Y$39:$Y$65,Y18,$AD$39:$AD$65),"") -> 0 | AC18: =IFERROR(Z18*AA18*VLOOKUP(Y18,'FB Data'!$A$2:$E$150,3,FALSE),"")
G19: =IFERROR(((E19/60)*$Z$10)/B19,"") | H19: =IF(Forming!G19>0,Forming!G19,0) -> 0 | I19: =IF('Hardware Install'!E19>0,'Hardware Install'!E19,0) -> 0 | J19: =IFERROR(VLOOKUP('FB Laser'!A19,Machining!A19:G109,7,FALSE),"") | K19: =IFERROR(IF(Finishing!G19>0,VLOOKUP('FB Laser'!A19,Finishing!A19:G109,7,FALSE),""),"") | L19: =IFERROR(SUM((H19*$Z$12),G19,I19,J19,K19,'FB Data'!AM18),"") -> 0 | M19: =IFERROR((C19*D19)*0.00694,"") -> 0 | O19: =IFERROR((B19*M19)/(VLOOKUP(N19,$Y$15:$AB$33,2,FALSE)),"") | P19: =IFERROR(VLOOKUP(N19,$Y$15:$AB$33,4,FALSE)*(O19/(VLOOKUP(N19,$Y$15:$AB$33,3,FALSE))),"") | Q19: =IFERROR((P19*$Z$11)/B19,"") | S19: =IFERROR(L19+Q19+($Z$8/$B$100)+($Z$9/$B$100)+($Z$3/$B$100)+($Z$2/$B$100)+($Z$4/$B$100)+($Z$5/$B$100)+($Z$6/$B$100),"") | T19: =IFERROR(ROUND(S19*'Quote Info'!$O$4+R19,2),"") | U19: =IFERROR(S19*B19,"") | V19: =IFERROR(T19*B19,"") | W19: =IFERROR(S19/((VLOOKUP(N19,'FB Data'!$A$2:$E$150,3,FALSE))*'FB Laser'!M19),"") | Y19: {=IFERROR(INDEX($Y$39:$Y$65, MATCH(0,IF(ISBLANK($Y$39:$Y$65),1,COUNTIF($Y$14:Y18, $Y$39:$Y$65)), 0)),"")} | Z19: =SUMIF($Y$39:$Y$65,Y19,$AC$39:$AC$65) -> 0 | AA19: =IFERROR(SUMIF($N$10:$N$99,Y19,$O$10:$O$99),"") -> 0 | AB19: =IFERROR(SUMIF($Y$39:$Y$65,Y19,$AD$39:$AD$65),"") -> 0 | AC19: =IFERROR(Z19*AA19*VLOOKUP(Y19,'FB Data'!$A$2:$E$150,3,FALSE),"")
G20: =IFERROR(((E20/60)*$Z$10)/B20,"") | H20: =IF(Forming!G20>0,Forming!G20,0) -> 0 | I20: =IF('Hardware Install'!E20>0,'Hardware Install'!E20,0) -> 0 | J20: =IFERROR(VLOOKUP('FB Laser'!A20,Machining!A20:G110,7,FALSE),"") | K20: =IFERROR(IF(Finishing!G20>0,VLOOKUP('FB Laser'!A20,Finishing!A20:G110,7,FALSE),""),"") | L20: =IFERROR(SUM((H20*$Z$12),G20,I20,J20,K20,'FB Data'!AM19),"") -> 0 | M20: =IFERROR((C20*D20)*0.00694,"") -> 0 | O20: =IFERROR((B20*M20)/(VLOOKUP(N20,$Y$15:$AB$33,2,FALSE)),"") | P20: =IFERROR(VLOOKUP(N20,$Y$15:$AB$33,4,FALSE)*(O20/(VLOOKUP(N20,$Y$15:$AB$33,3,FALSE))),"") | Q20: =IFERROR((P20*$Z$11)/B20,"") | S20: =IFERROR(L20+Q20+($Z$8/$B$100)+($Z$9/$B$100)+($Z$3/$B$100)+($Z$2/$B$100)+($Z$4/$B$100)+($Z$5/$B$100)+($Z$6/$B$100),"") | T20: =IFERROR(ROUND(S20*'Quote Info'!$O$4+R20,2),"") | U20: =IFERROR(S20*B20,"") | V20: =IFERROR(T20*B20,"") | W20: =IFERROR(S20/((VLOOKUP(N20,'FB Data'!$A$2:$E$150,3,FALSE))*'FB Laser'!M20),"") | Y20: {=IFERROR(INDEX($Y$39:$Y$65, MATCH(0,IF(ISBLANK($Y$39:$Y$65),1,COUNTIF($Y$14:Y19, $Y$39:$Y$65)), 0)),"")} | Z20: =SUMIF($Y$39:$Y$65,Y20,$AC$39:$AC$65) -> 0 | AA20: =IFERROR(SUMIF($N$10:$N$99,Y20,$O$10:$O$99),"") -> 0 | AB20: =IFERROR(SUMIF($Y$39:$Y$65,Y20,$AD$39:$AD$65),"") -> 0 | AC20: =IFERROR(Z20*AA20*VLOOKUP(Y20,'FB Data'!$A$2:$E$150,3,FALSE),"")
G21: =IFERROR(((E21/60)*$Z$10)/B21,"") | H21: =IF(Forming!G21>0,Forming!G21,0) -> 0 | I21: =IF('Hardware Install'!E21>0,'Hardware Install'!E21,0) -> 0 | J21: =IFERROR(VLOOKUP('FB Laser'!A21,Machining!A21:G111,7,FALSE),"") | K21: =IFERROR(IF(Finishing!G21>0,VLOOKUP('FB Laser'!A21,Finishing!A21:G111,7,FALSE),""),"") | L21: =IFERROR(SUM((H21*$Z$12),G21,I21,J21,K21,'FB Data'!AM20),"") -> 0 | M21: =IFERROR((C21*D21)*0.00694,"") -> 0 | O21: =IFERROR((B21*M21)/(VLOOKUP(N21,$Y$15:$AB$33,2,FALSE)),"") | P21: =IFERROR(VLOOKUP(N21,$Y$15:$AB$33,4,FALSE)*(O21/(VLOOKUP(N21,$Y$15:$AB$33,3,FALSE))),"") | Q21: =IFERROR((P21*$Z$11)/B21,"") | S21: =IFERROR(L21+Q21+($Z$8/$B$100)+($Z$9/$B$100)+($Z$3/$B$100)+($Z$2/$B$100)+($Z$4/$B$100)+($Z$5/$B$100)+($Z$6/$B$100),"") | T21: =IFERROR(ROUND(S21*'Quote Info'!$O$4+R21,2),"") | U21: =IFERROR(S21*B21,"") | V21: =IFERROR(T21*B21,"") | W21: =IFERROR(S21/((VLOOKUP(N21,'FB Data'!$A$2:$E$150,3,FALSE))*'FB Laser'!M21),"") | Y21: {=IFERROR(INDEX($Y$39:$Y$65, MATCH(0,IF(ISBLANK($Y$39:$Y$65),1,COUNTIF($Y$14:Y20, $Y$39:$Y$65)), 0)),"")} | Z21: =SUMIF($Y$39:$Y$65,Y21,$AC$39:$AC$65) -> 0 | AA21: =IFERROR(SUMIF($N$10:$N$99,Y21,$O$10:$O$99),"") -> 0 | AB21: =IFERROR(SUMIF($Y$39:$Y$65,Y21,$AD$39:$AD$65),"") -> 0 | AC21: =IFERROR(Z21*AA21*VLOOKUP(Y21,'FB Data'!$A$2:$E$150,3,FALSE),"")
G22: =IFERROR(((E22/60)*$Z$10)/B22,"") | H22: =IF(Forming!G22>0,Forming!G22,0) -> 0 | I22: =IF('Hardware Install'!E22>0,'Hardware Install'!E22,0) -> 0 | J22: =IFERROR(VLOOKUP('FB Laser'!A22,Machining!A22:G112,7,FALSE),"") | K22: =IFERROR(IF(Finishing!G22>0,VLOOKUP('FB Laser'!A22,Finishing!A22:G112,7,FALSE),""),"") | L22: =IFERROR(SUM((H22*$Z$12),G22,I22,J22,K22,'FB Data'!AM21),"") -> 0 | M22: =IFERROR((C22*D22)*0.00694,"") -> 0 | O22: =IFERROR((B22*M22)/(VLOOKUP(N22,$Y$15:$AB$33,2,FALSE)),"") | P22: =IFERROR(VLOOKUP(N22,$Y$15:$AB$33,4,FALSE)*(O22/(VLOOKUP(N22,$Y$15:$AB$33,3,FALSE))),"") | Q22: =IFERROR((P22*$Z$11)/B22,"") | S22: =IFERROR(L22+Q22+($Z$8/$B$100)+($Z$9/$B$100)+($Z$3/$B$100)+($Z$2/$B$100)+($Z$4/$B$100)+($Z$5/$B$100)+($Z$6/$B$100),"") | T22: =IFERROR(ROUND(S22*'Quote Info'!$O$4+R22,2),"") | U22: =IFERROR(S22*B22,"") | V22: =IFERROR(T22*B22,"") | W22: =IFERROR(S22/((VLOOKUP(N22,'FB Data'!$A$2:$E$150,3,FALSE))*'FB Laser'!M22),"") | Y22: {=IFERROR(INDEX($Y$39:$Y$65, MATCH(0,IF(ISBLANK($Y$39:$Y$65),1,COUNTIF($Y$14:Y21, $Y$39:$Y$65)), 0)),"")} | Z22: =SUMIF($Y$39:$Y$65,Y22,$AC$39:$AC$65) -> 0 | AA22: =IFERROR(SUMIF($N$10:$N$99,Y22,$O$10:$O$99),"") -> 0 | AB22: =IFERROR(SUMIF($Y$39:$Y$65,Y22,$AD$39:$AD$65),"") -> 0 | AC22: =IFERROR(Z22*AA22*VLOOKUP(Y22,'FB Data'!$A$2:$E$150,3,FALSE),"")
G23: =IFERROR(((E23/60)*$Z$10)/B23,"") | H23: =IF(Forming!G23>0,Forming!G23,0) -> 0 | I23: =IF('Hardware Install'!E23>0,'Hardware Install'!E23,0) -> 0 | J23: =IFERROR(VLOOKUP('FB Laser'!A23,Machining!A23:G113,7,FALSE),"") | K23: =IFERROR(IF(Finishing!G23>0,VLOOKUP('FB Laser'!A23,Finishing!A23:G113,7,FALSE),""),"") | L23: =IFERROR(SUM((H23*$Z$12),G23,I23,J23,K23,'FB Data'!AM22),"") -> 0 | M23: =IFERROR((C23*D23)*0.00694,"") -> 0 | O23: =IFERROR((B23*M23)/(VLOOKUP(N23,$Y$15:$AB$33,2,FALSE)),"") | P23: =IFERROR(VLOOKUP(N23,$Y$15:$AB$33,4,FALSE)*(O23/(VLOOKUP(N23,$Y$15:$AB$33,3,FALSE))),"") | Q23: =IFERROR((P23*$Z$11)/B23,"") | S23: =IFERROR(L23+Q23+($Z$8/$B$100)+($Z$9/$B$100)+($Z$3/$B$100)+($Z$2/$B$100)+($Z$4/$B$100)+($Z$5/$B$100)+($Z$6/$B$100),"") | T23: =IFERROR(ROUND(S23*'Quote Info'!$O$4+R23,2),"") | U23: =IFERROR(S23*B23,"") | V23: =IFERROR(T23*B23,"") | W23: =IFERROR(S23/((VLOOKUP(N23,'FB Data'!$A$2:$E$150,3,FALSE))*'FB Laser'!M23),"") | Y23: {=IFERROR(INDEX($Y$39:$Y$65, MATCH(0,IF(ISBLANK($Y$39:$Y$65),1,COUNTIF($Y$14:Y22, $Y$39:$Y$65)), 0)),"")} | Z23: =SUMIF($Y$39:$Y$65,Y23,$AC$39:$AC$65) -> 0 | AA23: =IFERROR(SUMIF($N$10:$N$99,Y23,$O$10:$O$99),"") -> 0 | AB23: =IFERROR(SUMIF($Y$39:$Y$65,Y23,$AD$39:$AD$65),"") -> 0 | AC23: =IFERROR(Z23*AA23*VLOOKUP(Y23,'FB Data'!$A$2:$E$150,3,FALSE),"")
G24: =IFERROR(((E24/60)*$Z$10)/B24,"") | H24: =IF(Forming!G24>0,Forming!G24,0) -> 0 | I24: =IF('Hardware Install'!E24>0,'Hardware Install'!E24,0) -> 0 | J24: =IFERROR(VLOOKUP('FB Laser'!A24,Machining!A24:G114,7,FALSE),"") | K24: =IFERROR(IF(Finishing!G24>0,VLOOKUP('FB Laser'!A24,Finishing!A24:G114,7,FALSE),""),"") | L24: =IFERROR(SUM((H24*$Z$12),G24,I24,J24,K24,'FB Data'!AM23),"") -> 0 | M24: =IFERROR((C24*D24)*0.00694,"") -> 0 | O24: =IFERROR((B24*M24)/(VLOOKUP(N24,$Y$15:$AB$33,2,FALSE)),"") | P24: =IFERROR(VLOOKUP(N24,$Y$15:$AB$33,4,FALSE)*(O24/(VLOOKUP(N24,$Y$15:$AB$33,3,FALSE))),"") | Q24: =IFERROR((P24*$Z$11)/B24,"") | S24: =IFERROR(L24+Q24+($Z$8/$B$100)+($Z$9/$B$100)+($Z$3/$B$100)+($Z$2/$B$100)+($Z$4/$B$100)+($Z$5/$B$100)+($Z$6/$B$100),"") | T24: =IFERROR(ROUND(S24*'Quote Info'!$O$4+R24,2),"") | U24: =IFERROR(S24*B24,"") | V24: =IFERROR(T24*B24,"") | W24: =IFERROR(S24/((VLOOKUP(N24,'FB Data'!$A$2:$E$150,3,FALSE))*'FB Laser'!M24),"") | Y24: {=IFERROR(INDEX($Y$39:$Y$65, MATCH(0,IF(ISBLANK($Y$39:$Y$65),1,COUNTIF($Y$14:Y23, $Y$39:$Y$65)), 0)),"")} | Z24: =SUMIF($Y$39:$Y$65,Y24,$AC$39:$AC$65) -> 0 | AA24: =IFERROR(SUMIF($N$10:$N$99,Y24,$O$10:$O$99),"") -> 0 | AB24: =IFERROR(SUMIF($Y$39:$Y$65,Y24,$AD$39:$AD$65),"") -> 0 | AC24: =IFERROR(Z24*AA24*VLOOKUP(Y24,'FB Data'!$A$2:$E$150,3,FALSE),"")
G25: =IFERROR(((E25/60)*$Z$10)/B25,"") | H25: =IF(Forming!G25>0,Forming!G25,0) -> 0 | I25: =IF('Hardware Install'!E25>0,'Hardware Install'!E25,0) -> 0 | J25: =IFERROR(VLOOKUP('FB Laser'!A25,Machining!A25:G115,7,FALSE),"") | K25: =IFERROR(IF(Finishing!G25>0,VLOOKUP('FB Laser'!A25,Finishing!A25:G115,7,FALSE),""),"") | L25: =IFERROR(SUM((H25*$Z$12),G25,I25,J25,K25,'FB Data'!AM24),"") -> 0 | M25: =IFERROR((C25*D25)*0.00694,"") -> 0 | O25: =IFERROR((B25*M25)/(VLOOKUP(N25,$Y$15:$AB$33,2,FALSE)),"") | P25: =IFERROR(VLOOKUP(N25,$Y$15:$AB$33,4,FALSE)*(O25/(VLOOKUP(N25,$Y$15:$AB$33,3,FALSE))),"") | Q25: =IFERROR((P25*$Z$11)/B25,"") | S25: =IFERROR(L25+Q25+($Z$8/$B$100)+($Z$9/$B$100)+($Z$3/$B$100)+($Z$2/$B$100)+($Z$4/$B$100)+($Z$5/$B$100)+($Z$6/$B$100),"") | T25: =IFERROR(ROUND(S25*'Quote Info'!$O$4+R25,2),"") | U25: =IFERROR(S25*B25,"") | V25: =IFERROR(T25*B25,"") | W25: =IFERROR(S25/((VLOOKUP(N25,'FB Data'!$A$2:$E$150,3,FALSE))*'FB Laser'!M25),"") | Y25: {=IFERROR(INDEX($Y$39:$Y$65, MATCH(0,IF(ISBLANK($Y$39:$Y$65),1,COUNTIF($Y$14:Y24, $Y$39:$Y$65)), 0)),"")} | Z25: =SUMIF($Y$39:$Y$65,Y25,$AC$39:$AC$65) -> 0 | AA25: =IFERROR(SUMIF($N$10:$N$99,Y25,$O$10:$O$99),"") -> 0 | AB25: =IFERROR(SUMIF($Y$39:$Y$65,Y25,$AD$39:$AD$65),"") -> 0 | AC25: =IFERROR(Z25*AA25*VLOOKUP(Y25,'FB Data'!$A$2:$E$150,3,FALSE),"")
G26: =IFERROR(((E26/60)*$Z$10)/B26,"") | H26: =IF(Forming!G26>0,Forming!G26,0) -> 0 | I26: =IF('Hardware Install'!E26>0,'Hardware Install'!E26,0) -> 0 | J26: =IFERROR(VLOOKUP('FB Laser'!A26,Machining!A26:G116,7,FALSE),"") | K26: =IFERROR(IF(Finishing!G26>0,VLOOKUP('FB Laser'!A26,Finishing!A26:G116,7,FALSE),""),"") | L26: =IFERROR(SUM((H26*$Z$12),G26,I26,J26,K26,'FB Data'!AM25),"") -> 0 | M26: =IFERROR((C26*D26)*0.00694,"") -> 0 | O26: =IFERROR((B26*M26)/(VLOOKUP(N26,$Y$15:$AB$33,2,FALSE)),"") | P26: =IFERROR(VLOOKUP(N26,$Y$15:$AB$33,4,FALSE)*(O26/(VLOOKUP(N26,$Y$15:$AB$33,3,FALSE))),"") | Q26: =IFERROR((P26*$Z$11)/B26,"") | S26: =IFERROR(L26+Q26+($Z$8/$B$100)+($Z$9/$B$100)+($Z$3/$B$100)+($Z$2/$B$100)+($Z$4/$B$100)+($Z$5/$B$100)+($Z$6/$B$100),"") | T26: =IFERROR(ROUND(S26*'Quote Info'!$O$4+R26,2),"") | U26: =IFERROR(S26*B26,"") | V26: =IFERROR(T26*B26,"") | W26: =IFERROR(S26/((VLOOKUP(N26,'FB Data'!$A$2:$E$150,3,FALSE))*'FB Laser'!M26),"") | Y26: {=IFERROR(INDEX($Y$39:$Y$65, MATCH(0,IF(ISBLANK($Y$39:$Y$65),1,COUNTIF($Y$14:Y25, $Y$39:$Y$65)), 0)),"")} | Z26: =SUMIF($Y$39:$Y$65,Y26,$AC$39:$AC$65) -> 0 | AA26: =IFERROR(SUMIF($N$10:$N$99,Y26,$O$10:$O$99),"") -> 0 | AB26: =IFERROR(SUMIF($Y$39:$Y$65,Y26,$AD$39:$AD$65),"") -> 0 | AC26: =IFERROR(Z26*AA26*VLOOKUP(Y26,'FB Data'!$A$2:$E$150,3,FALSE),"")
... G33: =IFERROR(((E33/60)*$Z$10)/B33,"") | H33: =IF(Forming!G33>0,Forming!G33,0) -> 0 | I33: =IF('Hardware Install'!E33>0,'Hardware Install'!E33,0) -> 0 | J33: =IFERROR(VLOOKUP('FB Laser'!A33,Machining!A33:G123,7,FALSE),"") | K33: =IFERROR(IF(Finishing!G33>0,VLOOKUP('FB Laser'!A33,Finishing!A33:G123,7,FALSE),""),"") | L33: =IFERROR(SUM((H33*$Z$12),G33,I33,J33,K33,'FB Data'!AM32),"") -> 0 | M33: =IFERROR((C33*D33)*0.00694,"") -> 0 | O33: =IFERROR((B33*M33)/(VLOOKUP(N33,$Y$15:$AB$33,2,FALSE)),"") | P33: =IFERROR(VLOOKUP(N33,$Y$15:$AB$33,4,FALSE)*(O33/(VLOOKUP(N33,$Y$15:$AB$33,3,FALSE))),"") | Q33: =IFERROR((P33*$Z$11)/B33,"") | S33: =IFERROR(L33+Q33+($Z$8/$B$100)+($Z$9/$B$100)+($Z$3/$B$100)+($Z$2/$B$100)+($Z$4/$B$100)+($Z$5/$B$100)+($Z$6/$B$100),"") | T33: =IFERROR(ROUND(S33*'Quote Info'!$O$4+R33,2),"") | U33: =IFERROR(S33*B33,"") | V33: =IFERROR(T33*B33,"") | W33: =IFERROR(S33/((VLOOKUP(N33,'FB Data'!$A$2:$E$150,3,FALSE))*'FB Laser'!M33),"") | Y33: {=IFERROR(INDEX($Y$39:$Y$65, MATCH(0,IF(ISBLANK($Y$39:$Y$65),1,COUNTIF($Y$14:Y32, $Y$39:$Y$65)), 0)),"")} | Z33: =SUMIF($Y$39:$Y$65,Y33,$AC$39:$AC$65) -> 0 | AA33: =IFERROR(SUMIF($N$10:$N$99,Y33,$O$10:$O$99),"") -> 0 | AB33: =IFERROR(SUMIF($Y$39:$Y$65,Y33,$AD$39:$AD$65),"") -> 0 | AC33: =IFERROR(Z33*AA33*VLOOKUP(Y33,'FB Data'!$A$2:$E$150,3,FALSE),"")
G34: =IFERROR(((E34/60)*$Z$10)/B34,"") | H34: =IF(Forming!G34>0,Forming!G34,0) -> 0 | I34: =IF('Hardware Install'!E34>0,'Hardware Install'!E34,0) -> 0 | J34: =IFERROR(VLOOKUP('FB Laser'!A34,Machining!A34:G124,7,FALSE),"") | K34: =IFERROR(IF(Finishing!G34>0,VLOOKUP('FB Laser'!A34,Finishing!A34:G124,7,FALSE),""),"") | L34: =IFERROR(SUM((H34*$Z$12),G34,I34,J34,K34,'FB Data'!AM33),"") -> 0 | M34: =IFERROR((C34*D34)*0.00694,"") -> 0 | O34: =IFERROR((B34*M34)/(VLOOKUP(N34,$Y$15:$AB$33,2,FALSE)),"") | P34: =IFERROR(VLOOKUP(N34,$Y$15:$AB$33,4,FALSE)*(O34/(VLOOKUP(N34,$Y$15:$AB$33,3,FALSE))),"") | Q34: =IFERROR((P34*$Z$11)/B34,"") | S34: =IFERROR(L34+Q34+($Z$8/$B$100)+($Z$9/$B$100)+($Z$3/$B$100)+($Z$2/$B$100)+($Z$4/$B$100)+($Z$5/$B$100)+($Z$6/$B$100),"") | T34: =IFERROR(ROUND(S34*'Quote Info'!$O$4+R34,2),"") | U34: =IFERROR(S34*B34,"") | V34: =IFERROR(T34*B34,"") | W34: =IFERROR(S34/((VLOOKUP(N34,'FB Data'!$A$2:$E$150,3,FALSE))*'FB Laser'!M34),"") | AC34: =SUMIF(AC15:AC25,"<>#N/A") -> 0
G35: =IFERROR(((E35/60)*$Z$10)/B35,"") | H35: =IF(Forming!G35>0,Forming!G35,0) -> 0 | I35: =IF('Hardware Install'!E35>0,'Hardware Install'!E35,0) -> 0 | J35: =IFERROR(VLOOKUP('FB Laser'!A35,Machining!A35:G125,7,FALSE),"") | K35: =IFERROR(IF(Finishing!G35>0,VLOOKUP('FB Laser'!A35,Finishing!A35:G125,7,FALSE),""),"") | L35: =IFERROR(SUM((H35*$Z$12),G35,I35,J35,K35,'FB Data'!AM34),"") -> 0 | M35: =IFERROR((C35*D35)*0.00694,"") -> 0 | O35: =IFERROR((B35*M35)/(VLOOKUP(N35,$Y$15:$AB$33,2,FALSE)),"") | P35: =IFERROR(VLOOKUP(N35,$Y$15:$AB$33,4,FALSE)*(O35/(VLOOKUP(N35,$Y$15:$AB$33,3,FALSE))),"") | Q35: =IFERROR((P35*$Z$11)/B35,"") | S35: =IFERROR(L35+Q35+($Z$8/$B$100)+($Z$9/$B$100)+($Z$3/$B$100)+($Z$2/$B$100)+($Z$4/$B$100)+($Z$5/$B$100)+($Z$6/$B$100),"") | T35: =IFERROR(ROUND(S35*'Quote Info'!$O$4+R35,2),"") | U35: =IFERROR(S35*B35,"") | V35: =IFERROR(T35*B35,"") | W35: =IFERROR(S35/((VLOOKUP(N35,'FB Data'!$A$2:$E$150,3,FALSE))*'FB Laser'!M35),"")
G36: =IFERROR(((E36/60)*$Z$10)/B36,"") | H36: =IF(Forming!G36>0,Forming!G36,0) -> 0 | I36: =IF('Hardware Install'!E36>0,'Hardware Install'!E36,0) -> 0 | J36: =IFERROR(VLOOKUP('FB Laser'!A36,Machining!A36:G126,7,FALSE),"") | K36: =IFERROR(IF(Finishing!G36>0,VLOOKUP('FB Laser'!A36,Finishing!A36:G126,7,FALSE),""),"") | L36: =IFERROR(SUM((H36*$Z$12),G36,I36,J36,K36,'FB Data'!AM35),"") -> 0 | M36: =IFERROR((C36*D36)*0.00694,"") -> 0 | O36: =IFERROR((B36*M36)/(VLOOKUP(N36,$Y$15:$AB$33,2,FALSE)),"") | P36: =IFERROR(VLOOKUP(N36,$Y$15:$AB$33,4,FALSE)*(O36/(VLOOKUP(N36,$Y$15:$AB$33,3,FALSE))),"") | Q36: =IFERROR((P36*$Z$11)/B36,"") | S36: =IFERROR(L36+Q36+($Z$8/$B$100)+($Z$9/$B$100)+($Z$3/$B$100)+($Z$2/$B$100)+($Z$4/$B$100)+($Z$5/$B$100)+($Z$6/$B$100),"") | T36: =IFERROR(ROUND(S36*'Quote Info'!$O$4+R36,2),"") | U36: =IFERROR(S36*B36,"") | V36: =IFERROR(T36*B36,"") | W36: =IFERROR(S36/((VLOOKUP(N36,'FB Data'!$A$2:$E$150,3,FALSE))*'FB Laser'!M36),"")
G37: =IFERROR(((E37/60)*$Z$10)/B37,"") | H37: =IF(Forming!G37>0,Forming!G37,0) -> 0 | I37: =IF('Hardware Install'!E37>0,'Hardware Install'!E37,0) -> 0 | J37: =IFERROR(VLOOKUP('FB Laser'!A37,Machining!A37:G127,7,FALSE),"") | K37: =IFERROR(IF(Finishing!G37>0,VLOOKUP('FB Laser'!A37,Finishing!A37:G127,7,FALSE),""),"") | L37: =IFERROR(SUM((H37*$Z$12),G37,I37,J37,K37,'FB Data'!AM36),"") -> 0 | M37: =IFERROR((C37*D37)*0.00694,"") -> 0 | O37: =IFERROR((B37*M37)/(VLOOKUP(N37,$Y$15:$AB$33,2,FALSE)),"") | P37: =IFERROR(VLOOKUP(N37,$Y$15:$AB$33,4,FALSE)*(O37/(VLOOKUP(N37,$Y$15:$AB$33,3,FALSE))),"") | Q37: =IFERROR((P37*$Z$11)/B37,"") | S37: =IFERROR(L37+Q37+($Z$8/$B$100)+($Z$9/$B$100)+($Z$3/$B$100)+($Z$2/$B$100)+($Z$4/$B$100)+($Z$5/$B$100)+($Z$6/$B$100),"") | T37: =IFERROR(ROUND(S37*'Quote Info'!$O$4+R37,2),"") | U37: =IFERROR(S37*B37,"") | V37: =IFERROR(T37*B37,"") | W37: =IFERROR(S37/((VLOOKUP(N37,'FB Data'!$A$2:$E$150,3,FALSE))*'FB Laser'!M37),"") | Y37: Material Required
G38: =IFERROR(((E38/60)*$Z$10)/B38,"") | H38: =IF(Forming!G38>0,Forming!G38,0) -> 0 | I38: =IF('Hardware Install'!E38>0,'Hardware Install'!E38,0) -> 0 | J38: =IFERROR(VLOOKUP('FB Laser'!A38,Machining!A38:G128,7,FALSE),"") | K38: =IFERROR(IF(Finishing!G38>0,VLOOKUP('FB Laser'!A38,Finishing!A38:G128,7,FALSE),""),"") | L38: =IFERROR(SUM((H38*$Z$12),G38,I38,J38,K38,'FB Data'!AM37),"") -> 0 | M38: =IFERROR((C38*D38)*0.00694,"") -> 0 | O38: =IFERROR((B38*M38)/(VLOOKUP(N38,$Y$15:$AB$33,2,FALSE)),"") | P38: =IFERROR(VLOOKUP(N38,$Y$15:$AB$33,4,FALSE)*(O38/(VLOOKUP(N38,$Y$15:$AB$33,3,FALSE))),"") | Q38: =IFERROR((P38*$Z$11)/B38,"") | S38: =IFERROR(L38+Q38+($Z$8/$B$100)+($Z$9/$B$100)+($Z$3/$B$100)+($Z$2/$B$100)+($Z$4/$B$100)+($Z$5/$B$100)+($Z$6/$B$100),"") | T38: =IFERROR(ROUND(S38*'Quote Info'!$O$4+R38,2),"") | U38: =IFERROR(S38*B38,"") | V38: =IFERROR(T38*B38,"") | W38: =IFERROR(S38/((VLOOKUP(N38,'FB Data'!$A$2:$E$150,3,FALSE))*'FB Laser'!M38),"") | Y38: Material ID | Z38: Qty | AA38: Width (in) | AB38: Length (in) | AC38: Total Sqft | AD38: Material Cost
G39: =IFERROR(((E39/60)*$Z$10)/B39,"") | H39: =IF(Forming!G39>0,Forming!G39,0) -> 0 | I39: =IF('Hardware Install'!E39>0,'Hardware Install'!E39,0) -> 0 | J39: =IFERROR(VLOOKUP('FB Laser'!A39,Machining!A39:G129,7,FALSE),"") | K39: =IFERROR(IF(Finishing!G39>0,VLOOKUP('FB Laser'!A39,Finishing!A39:G129,7,FALSE),""),"") | L39: =IFERROR(SUM((H39*$Z$12),G39,I39,J39,K39,'FB Data'!AM38),"") -> 0 | M39: =IFERROR((C39*D39)*0.00694,"") -> 0 | O39: =IFERROR((B39*M39)/(VLOOKUP(N39,$Y$15:$AB$33,2,FALSE)),"") | P39: =IFERROR(VLOOKUP(N39,$Y$15:$AB$33,4,FALSE)*(O39/(VLOOKUP(N39,$Y$15:$AB$33,3,FALSE))),"") | Q39: =IFERROR((P39*$Z$11)/B39,"") | S39: =IFERROR(L39+Q39+($Z$8/$B$100)+($Z$9/$B$100)+($Z$3/$B$100)+($Z$2/$B$100)+($Z$4/$B$100)+($Z$5/$B$100)+($Z$6/$B$100),"") | T39: =IFERROR(ROUND(S39*'Quote Info'!$O$4+R39,2),"") | U39: =IFERROR(S39*B39,"") | V39: =IFERROR(T39*B39,"") | W39: =IFERROR(S39/((VLOOKUP(N39,'FB Data'!$A$2:$E$150,3,FALSE))*'FB Laser'!M39),"") | AC39: =IFERROR((AA39/12)*(AB39/12)*Z39,"") -> 0 | AD39: =IFERROR(IF($Z$7="JWMCD",VLOOKUP(Y39,'FB Data'!$A$2:$E$151,3,FALSE)*VLOOKUP(Y39,'FB Data'!$A$2:$E$151,5,FALSE)*AC39,IF($Z$7="Customer Supplied",0,"Need Input")),"")
G40: =IFERROR(((E40/60)*$Z$10)/B40,"") | H40: =IF(Forming!G40>0,Forming!G40,0) -> 0 | I40: =IF('Hardware Install'!E40>0,'Hardware Install'!E40,0) -> 0 | J40: =IFERROR(VLOOKUP('FB Laser'!A40,Machining!A40:G130,7,FALSE),"") | K40: =IFERROR(IF(Finishing!G40>0,VLOOKUP('FB Laser'!A40,Finishing!A40:G130,7,FALSE),""),"") | L40: =IFERROR(SUM((H40*$Z$12),G40,I40,J40,K40,'FB Data'!AM39),"") -> 0 | M40: =IFERROR((C40*D40)*0.00694,"") -> 0 | O40: =IFERROR((B40*M40)/(VLOOKUP(N40,$Y$15:$AB$33,2,FALSE)),"") | P40: =IFERROR(VLOOKUP(N40,$Y$15:$AB$33,4,FALSE)*(O40/(VLOOKUP(N40,$Y$15:$AB$33,3,FALSE))),"") | Q40: =IFERROR((P40*$Z$11)/B40,"") | S40: =IFERROR(L40+Q40+($Z$8/$B$100)+($Z$9/$B$100)+($Z$3/$B$100)+($Z$2/$B$100)+($Z$4/$B$100)+($Z$5/$B$100)+($Z$6/$B$100),"") | T40: =IFERROR(ROUND(S40*'Quote Info'!$O$4+R40,2),"") | U40: =IFERROR(S40*B40,"") | V40: =IFERROR(T40*B40,"") | W40: =IFERROR(S40/((VLOOKUP(N40,'FB Data'!$A$2:$E$150,3,FALSE))*'FB Laser'!M40),"") | AC40: =IFERROR((AA40/12)*(AB40/12)*Z40,"") -> 0 | AD40: =IFERROR(IF($Z$7="JWMCD",VLOOKUP(Y40,'FB Data'!$A$2:$E$151,3,FALSE)*VLOOKUP(Y40,'FB Data'!$A$2:$E$151,5,FALSE)*AC40,IF($Z$7="Customer Supplied",0,"Need Input")),"")
G41: =IFERROR(((E41/60)*$Z$10)/B41,"") | H41: =IF(Forming!G41>0,Forming!G41,0) -> 0 | I41: =IF('Hardware Install'!E41>0,'Hardware Install'!E41,0) -> 0 | J41: =IFERROR(VLOOKUP('FB Laser'!A41,Machining!A41:G131,7,FALSE),"") | K41: =IFERROR(IF(Finishing!G41>0,VLOOKUP('FB Laser'!A41,Finishing!A41:G131,7,FALSE),""),"") | L41: =IFERROR(SUM((H41*$Z$12),G41,I41,J41,K41,'FB Data'!AM40),"") -> 0 | M41: =IFERROR((C41*D41)*0.00694,"") -> 0 | O41: =IFERROR((B41*M41)/(VLOOKUP(N41,$Y$15:$AB$33,2,FALSE)),"") | P41: =IFERROR(VLOOKUP(N41,$Y$15:$AB$33,4,FALSE)*(O41/(VLOOKUP(N41,$Y$15:$AB$33,3,FALSE))),"") | Q41: =IFERROR((P41*$Z$11)/B41,"") | S41: =IFERROR(L41+Q41+($Z$8/$B$100)+($Z$9/$B$100)+($Z$3/$B$100)+($Z$2/$B$100)+($Z$4/$B$100)+($Z$5/$B$100)+($Z$6/$B$100),"") | T41: =IFERROR(ROUND(S41*'Quote Info'!$O$4+R41,2),"") | U41: =IFERROR(S41*B41,"") | V41: =IFERROR(T41*B41,"") | W41: =IFERROR(S41/((VLOOKUP(N41,'FB Data'!$A$2:$E$150,3,FALSE))*'FB Laser'!M41),"") | AC41: =IFERROR((AA41/12)*(AB41/12)*Z41,"") -> 0 | AD41: =IFERROR(IF($Z$7="JWMCD",VLOOKUP(Y41,'FB Data'!$A$2:$E$151,3,FALSE)*VLOOKUP(Y41,'FB Data'!$A$2:$E$151,5,FALSE)*AC41,IF($Z$7="Customer Supplied",0,"Need Input")),"")
G42: =IFERROR(((E42/60)*$Z$10)/B42,"") | H42: =IF(Forming!G42>0,Forming!G42,0) -> 0 | I42: =IF('Hardware Install'!E42>0,'Hardware Install'!E42,0) -> 0 | J42: =IFERROR(VLOOKUP('FB Laser'!A42,Machining!A42:G132,7,FALSE),"") | K42: =IFERROR(IF(Finishing!G42>0,VLOOKUP('FB Laser'!A42,Finishing!A42:G132,7,FALSE),""),"") | L42: =IFERROR(SUM((H42*$Z$12),G42,I42,J42,K42,'FB Data'!AM41),"") -> 0 | M42: =IFERROR((C42*D42)*0.00694,"") -> 0 | O42: =IFERROR((B42*M42)/(VLOOKUP(N42,$Y$15:$AB$33,2,FALSE)),"") | P42: =IFERROR(VLOOKUP(N42,$Y$15:$AB$33,4,FALSE)*(O42/(VLOOKUP(N42,$Y$15:$AB$33,3,FALSE))),"") | Q42: =IFERROR((P42*$Z$11)/B42,"") | S42: =IFERROR(L42+Q42+($Z$8/$B$100)+($Z$9/$B$100)+($Z$3/$B$100)+($Z$2/$B$100)+($Z$4/$B$100)+($Z$5/$B$100)+($Z$6/$B$100),"") | T42: =IFERROR(ROUND(S42*'Quote Info'!$O$4+R42,2),"") | U42: =IFERROR(S42*B42,"") | V42: =IFERROR(T42*B42,"") | W42: =IFERROR(S42/((VLOOKUP(N42,'FB Data'!$A$2:$E$150,3,FALSE))*'FB Laser'!M42),"") | AC42: =IFERROR((AA42/12)*(AB42/12)*Z42,"") -> 0 | AD42: =IFERROR(IF($Z$7="JWMCD",VLOOKUP(Y42,'FB Data'!$A$2:$E$151,3,FALSE)*VLOOKUP(Y42,'FB Data'!$A$2:$E$151,5,FALSE)*AC42,IF($Z$7="Customer Supplied",0,"Need Input")),"")
G43: =IFERROR(((E43/60)*$Z$10)/B43,"") | H43: =IF(Forming!G43>0,Forming!G43,0) -> 0 | I43: =IF('Hardware Install'!E43>0,'Hardware Install'!E43,0) -> 0 | J43: =IFERROR(VLOOKUP('FB Laser'!A43,Machining!A43:G133,7,FALSE),"") | K43: =IFERROR(IF(Finishing!G43>0,VLOOKUP('FB Laser'!A43,Finishing!A43:G133,7,FALSE),""),"") | L43: =IFERROR(SUM((H43*$Z$12),G43,I43,J43,K43,'FB Data'!AM42),"") -> 0 | M43: =IFERROR((C43*D43)*0.00694,"") -> 0 | O43: =IFERROR((B43*M43)/(VLOOKUP(N43,$Y$15:$AB$33,2,FALSE)),"") | P43: =IFERROR(VLOOKUP(N43,$Y$15:$AB$33,4,FALSE)*(O43/(VLOOKUP(N43,$Y$15:$AB$33,3,FALSE))),"") | Q43: =IFERROR((P43*$Z$11)/B43,"") | S43: =IFERROR(L43+Q43+($Z$8/$B$100)+($Z$9/$B$100)+($Z$3/$B$100)+($Z$2/$B$100)+($Z$4/$B$100)+($Z$5/$B$100)+($Z$6/$B$100),"") | T43: =IFERROR(ROUND(S43*'Quote Info'!$O$4+R43,2),"") | U43: =IFERROR(S43*B43,"") | V43: =IFERROR(T43*B43,"") | W43: =IFERROR(S43/((VLOOKUP(N43,'FB Data'!$A$2:$E$150,3,FALSE))*'FB Laser'!M43),"") | AC43: =IFERROR((AA43/12)*(AB43/12)*Z43,"") -> 0 | AD43: =IFERROR(IF($Z$7="JWMCD",VLOOKUP(Y43,'FB Data'!$A$2:$E$151,3,FALSE)*VLOOKUP(Y43,'FB Data'!$A$2:$E$151,5,FALSE)*AC43,IF($Z$7="Customer Supplied",0,"Need Input")),"")
G44: =IFERROR(((E44/60)*$Z$10)/B44,"") | H44: =IF(Forming!G44>0,Forming!G44,0) -> 0 | I44: =IF('Hardware Install'!E44>0,'Hardware Install'!E44,0) -> 0 | J44: =IFERROR(VLOOKUP('FB Laser'!A44,Machining!A44:G134,7,FALSE),"") | K44: =IFERROR(IF(Finishing!G44>0,VLOOKUP('FB Laser'!A44,Finishing!A44:G134,7,FALSE),""),"") | L44: =IFERROR(SUM((H44*$Z$12),G44,I44,J44,K44,'FB Data'!AM43),"") -> 0 | M44: =IFERROR((C44*D44)*0.00694,"") -> 0 | O44: =IFERROR((B44*M44)/(VLOOKUP(N44,$Y$15:$AB$33,2,FALSE)),"") | P44: =IFERROR(VLOOKUP(N44,$Y$15:$AB$33,4,FALSE)*(O44/(VLOOKUP(N44,$Y$15:$AB$33,3,FALSE))),"") | Q44: =IFERROR((P44*$Z$11)/B44,"") | S44: =IFERROR(L44+Q44+($Z$8/$B$100)+($Z$9/$B$100)+($Z$3/$B$100)+($Z$2/$B$100)+($Z$4/$B$100)+($Z$5/$B$100)+($Z$6/$B$100),"") | T44: =IFERROR(ROUND(S44*'Quote Info'!$O$4+R44,2),"") | U44: =IFERROR(S44*B44,"") | V44: =IFERROR(T44*B44,"") | W44: =IFERROR(S44/((VLOOKUP(N44,'FB Data'!$A$2:$E$150,3,FALSE))*'FB Laser'!M44),"") | AC44: =IFERROR((AA44/12)*(AB44/12)*Z44,"") -> 0 | AD44: =IFERROR(IF($Z$7="JWMCD",VLOOKUP(Y44,'FB Data'!$A$2:$E$151,3,FALSE)*VLOOKUP(Y44,'FB Data'!$A$2:$E$151,5,FALSE)*AC44,IF($Z$7="Customer Supplied",0,"Need Input")),"")
G45: =IFERROR(((E45/60)*$Z$10)/B45,"") | H45: =IF(Forming!G45>0,Forming!G45,0) -> 0 | I45: =IF('Hardware Install'!E45>0,'Hardware Install'!E45,0) -> 0 | J45: =IFERROR(VLOOKUP('FB Laser'!A45,Machining!A45:G135,7,FALSE),"") | K45: =IFERROR(IF(Finishing!G45>0,VLOOKUP('FB Laser'!A45,Finishing!A45:G135,7,FALSE),""),"") | L45: =IFERROR(SUM((H45*$Z$12),G45,I45,J45,K45,'FB Data'!AM44),"") -> 0 | M45: =IFERROR((C45*D45)*0.00694,"") -> 0 | O45: =IFERROR((B45*M45)/(VLOOKUP(N45,$Y$15:$AB$33,2,FALSE)),"") | P45: =IFERROR(VLOOKUP(N45,$Y$15:$AB$33,4,FALSE)*(O45/(VLOOKUP(N45,$Y$15:$AB$33,3,FALSE))),"") | Q45: =IFERROR((P45*$Z$11)/B45,"") | S45: =IFERROR(L45+Q45+($Z$8/$B$100)+($Z$9/$B$100)+($Z$3/$B$100)+($Z$2/$B$100)+($Z$4/$B$100)+($Z$5/$B$100)+($Z$6/$B$100),"") | T45: =IFERROR(ROUND(S45*'Quote Info'!$O$4+R45,2),"") | U45: =IFERROR(S45*B45,"") | V45: =IFERROR(T45*B45,"") | W45: =IFERROR(S45/((VLOOKUP(N45,'FB Data'!$A$2:$E$150,3,FALSE))*'FB Laser'!M45),"") | AC45: =IFERROR((AA45/12)*(AB45/12)*Z45,"") -> 0 | AD45: =IFERROR(IF($Z$7="JWMCD",VLOOKUP(Y45,'FB Data'!$A$2:$E$151,3,FALSE)*VLOOKUP(Y45,'FB Data'!$A$2:$E$151,5,FALSE)*AC45,IF($Z$7="Customer Supplied",0,"Need Input")),"")
G46: =IFERROR(((E46/60)*$Z$10)/B46,"") | H46: =IF(Forming!G46>0,Forming!G46,0) -> 0 | I46: =IF('Hardware Install'!E46>0,'Hardware Install'!E46,0) -> 0 | J46: =IFERROR(VLOOKUP('FB Laser'!A46,Machining!A46:G136,7,FALSE),"") | K46: =IFERROR(IF(Finishing!G46>0,VLOOKUP('FB Laser'!A46,Finishing!A46:G136,7,FALSE),""),"") | L46: =IFERROR(SUM((H46*$Z$12),G46,I46,J46,K46,'FB Data'!AM45),"") -> 0 | M46: =IFERROR((C46*D46)*0.00694,"") -> 0 | O46: =IFERROR((B46*M46)/(VLOOKUP(N46,$Y$15:$AB$33,2,FALSE)),"") | P46: =IFERROR(VLOOKUP(N46,$Y$15:$AB$33,4,FALSE)*(O46/(VLOOKUP(N46,$Y$15:$AB$33,3,FALSE))),"") | Q46: =IFERROR((P46*$Z$11)/B46,"") | S46: =IFERROR(L46+Q46+($Z$8/$B$100)+($Z$9/$B$100)+($Z$3/$B$100)+($Z$2/$B$100)+($Z$4/$B$100)+($Z$5/$B$100)+($Z$6/$B$100),"") | T46: =IFERROR(ROUND(S46*'Quote Info'!$O$4+R46,2),"") | U46: =IFERROR(S46*B46,"") | V46: =IFERROR(T46*B46,"") | W46: =IFERROR(S46/((VLOOKUP(N46,'FB Data'!$A$2:$E$150,3,FALSE))*'FB Laser'!M46),"") | AC46: =IFERROR((AA46/12)*(AB46/12)*Z46,"") -> 0 | AD46: =IFERROR(IF($Z$7="JWMCD",VLOOKUP(Y46,'FB Data'!$A$2:$E$151,3,FALSE)*VLOOKUP(Y46,'FB Data'!$A$2:$E$151,5,FALSE)*AC46,IF($Z$7="Customer Supplied",0,"Need Input")),"")
G47: =IFERROR(((E47/60)*$Z$10)/B47,"") | H47: =IF(Forming!G47>0,Forming!G47,0) -> 0 | I47: =IF('Hardware Install'!E47>0,'Hardware Install'!E47,0) -> 0 | J47: =IFERROR(VLOOKUP('FB Laser'!A47,Machining!A47:G137,7,FALSE),"") | K47: =IFERROR(IF(Finishing!G47>0,VLOOKUP('FB Laser'!A47,Finishing!A47:G137,7,FALSE),""),"") | L47: =IFERROR(SUM((H47*$Z$12),G47,I47,J47,K47,'FB Data'!AM46),"") -> 0 | M47: =IFERROR((C47*D47)*0.00694,"") -> 0 | O47: =IFERROR((B47*M47)/(VLOOKUP(N47,$Y$15:$AB$33,2,FALSE)),"") | P47: =IFERROR(VLOOKUP(N47,$Y$15:$AB$33,4,FALSE)*(O47/(VLOOKUP(N47,$Y$15:$AB$33,3,FALSE))),"") | Q47: =IFERROR((P47*$Z$11)/B47,"") | S47: =IFERROR(L47+Q47+($Z$8/$B$100)+($Z$9/$B$100)+($Z$3/$B$100)+($Z$2/$B$100)+($Z$4/$B$100)+($Z$5/$B$100)+($Z$6/$B$100),"") | T47: =IFERROR(ROUND(S47*'Quote Info'!$O$4+R47,2),"") | U47: =IFERROR(S47*B47,"") | V47: =IFERROR(T47*B47,"") | W47: =IFERROR(S47/((VLOOKUP(N47,'FB Data'!$A$2:$E$150,3,FALSE))*'FB Laser'!M47),"") | AC47: =IFERROR((AA47/12)*(AB47/12)*Z47,"") -> 0 | AD47: =IFERROR(IF($Z$7="JWMCD",VLOOKUP(Y47,'FB Data'!$A$2:$E$151,3,FALSE)*VLOOKUP(Y47,'FB Data'!$A$2:$E$151,5,FALSE)*AC47,IF($Z$7="Customer Supplied",0,"Need Input")),"")
G48: =IFERROR(((E48/60)*$Z$10)/B48,"") | H48: =IF(Forming!G48>0,Forming!G48,0) -> 0 | I48: =IF('Hardware Install'!E48>0,'Hardware Install'!E48,0) -> 0 | J48: =IFERROR(VLOOKUP('FB Laser'!A48,Machining!A48:G138,7,FALSE),"") | K48: =IFERROR(IF(Finishing!G48>0,VLOOKUP('FB Laser'!A48,Finishing!A48:G138,7,FALSE),""),"") | L48: =IFERROR(SUM((H48*$Z$12),G48,I48,J48,K48,'FB Data'!AM47),"") -> 0 | M48: =IFERROR((C48*D48)*0.00694,"") -> 0 | O48: =IFERROR((B48*M48)/(VLOOKUP(N48,$Y$15:$AB$33,2,FALSE)),"") | P48: =IFERROR(VLOOKUP(N48,$Y$15:$AB$33,4,FALSE)*(O48/(VLOOKUP(N48,$Y$15:$AB$33,3,FALSE))),"") | Q48: =IFERROR((P48*$Z$11)/B48,"") | S48: =IFERROR(L48+Q48+($Z$8/$B$100)+($Z$9/$B$100)+($Z$3/$B$100)+($Z$2/$B$100)+($Z$4/$B$100)+($Z$5/$B$100)+($Z$6/$B$100),"") | T48: =IFERROR(ROUND(S48*'Quote Info'!$O$4+R48,2),"") | U48: =IFERROR(S48*B48,"") | V48: =IFERROR(T48*B48,"") | W48: =IFERROR(S48/((VLOOKUP(N48,'FB Data'!$A$2:$E$150,3,FALSE))*'FB Laser'!M48),"") | AC48: =IFERROR((AA48/12)*(AB48/12)*Z48,"") -> 0 | AD48: =IFERROR(IF($Z$7="JWMCD",VLOOKUP(Y48,'FB Data'!$A$2:$E$151,3,FALSE)*VLOOKUP(Y48,'FB Data'!$A$2:$E$151,5,FALSE)*AC48,IF($Z$7="Customer Supplied",0,"Need Input")),"")
G49: =IFERROR(((E49/60)*$Z$10)/B49,"") | H49: =IF(Forming!G49>0,Forming!G49,0) -> 0 | I49: =IF('Hardware Install'!E49>0,'Hardware Install'!E49,0) -> 0 | J49: =IFERROR(VLOOKUP('FB Laser'!A49,Machining!A49:G139,7,FALSE),"") | K49: =IFERROR(IF(Finishing!G49>0,VLOOKUP('FB Laser'!A49,Finishing!A49:G139,7,FALSE),""),"") | L49: =IFERROR(SUM((H49*$Z$12),G49,I49,J49,K49,'FB Data'!AM48),"") -> 0 | M49: =IFERROR((C49*D49)*0.00694,"") -> 0 | O49: =IFERROR((B49*M49)/(VLOOKUP(N49,$Y$15:$AB$33,2,FALSE)),"") | P49: =IFERROR(VLOOKUP(N49,$Y$15:$AB$33,4,FALSE)*(O49/(VLOOKUP(N49,$Y$15:$AB$33,3,FALSE))),"") | Q49: =IFERROR((P49*$Z$11)/B49,"") | S49: =IFERROR(L49+Q49+($Z$8/$B$100)+($Z$9/$B$100)+($Z$3/$B$100)+($Z$2/$B$100)+($Z$4/$B$100)+($Z$5/$B$100)+($Z$6/$B$100),"") | T49: =IFERROR(ROUND(S49*'Quote Info'!$O$4+R49,2),"") | U49: =IFERROR(S49*B49,"") | V49: =IFERROR(T49*B49,"") | W49: =IFERROR(S49/((VLOOKUP(N49,'FB Data'!$A$2:$E$150,3,FALSE))*'FB Laser'!M49),"") | AC49: =IFERROR((AA49/12)*(AB49/12)*Z49,"") -> 0 | AD49: =IFERROR(IF($Z$7="JWMCD",VLOOKUP(Y49,'FB Data'!$A$2:$E$151,3,FALSE)*VLOOKUP(Y49,'FB Data'!$A$2:$E$151,5,FALSE)*AC49,IF($Z$7="Customer Supplied",0,"Need Input")),"")
G50: =IFERROR(((E50/60)*$Z$10)/B50,"") | H50: =IF(Forming!G50>0,Forming!G50,0) -> 0 | I50: =IF('Hardware Install'!E50>0,'Hardware Install'!E50,0) -> 0 | J50: =IFERROR(VLOOKUP('FB Laser'!A50,Machining!A50:G140,7,FALSE),"") | K50: =IFERROR(IF(Finishing!G50>0,VLOOKUP('FB Laser'!A50,Finishing!A50:G140,7,FALSE),""),"") | L50: =IFERROR(SUM((H50*$Z$12),G50,I50,J50,K50,'FB Data'!AM49),"") -> 0 | M50: =IFERROR((C50*D50)*0.00694,"") -> 0 | O50: =IFERROR((B50*M50)/(VLOOKUP(N50,$Y$15:$AB$33,2,FALSE)),"") | P50: =IFERROR(VLOOKUP(N50,$Y$15:$AB$33,4,FALSE)*(O50/(VLOOKUP(N50,$Y$15:$AB$33,3,FALSE))),"") | Q50: =IFERROR((P50*$Z$11)/B50,"") | S50: =IFERROR(L50+Q50+($Z$8/$B$100)+($Z$9/$B$100)+($Z$3/$B$100)+($Z$2/$B$100)+($Z$4/$B$100)+($Z$5/$B$100)+($Z$6/$B$100),"") | T50: =IFERROR(ROUND(S50*'Quote Info'!$O$4+R50,2),"") | U50: =IFERROR(S50*B50,"") | V50: =IFERROR(T50*B50,"") | W50: =IFERROR(S50/((VLOOKUP(N50,'FB Data'!$A$2:$E$150,3,FALSE))*'FB Laser'!M50),"") | AC50: =IFERROR((AA50/12)*(AB50/12)*Z50,"") -> 0 | AD50: =IFERROR(IF($Z$7="JWMCD",VLOOKUP(Y50,'FB Data'!$A$2:$E$151,3,FALSE)*VLOOKUP(Y50,'FB Data'!$A$2:$E$151,5,FALSE)*AC50,IF($Z$7="Customer Supplied",0,"Need Input")),"")
... G65: =IFERROR(((E65/60)*$Z$10)/B65,"") | H65: =IF(Forming!G65>0,Forming!G65,0) -> 0 | I65: =IF('Hardware Install'!E65>0,'Hardware Install'!E65,0) -> 0 | J65: =IFERROR(VLOOKUP('FB Laser'!A65,Machining!A65:G155,7,FALSE),"") | K65: =IFERROR(IF(Finishing!G65>0,VLOOKUP('FB Laser'!A65,Finishing!A65:G155,7,FALSE),""),"") | L65: =IFERROR(SUM((H65*$Z$12),G65,I65,J65,K65,'FB Data'!AM64),"") -> 0 | M65: =IFERROR((C65*D65)*0.00694,"") -> 0 | O65: =IFERROR((B65*M65)/(VLOOKUP(N65,$Y$15:$AB$33,2,FALSE)),"") | P65: =IFERROR(VLOOKUP(N65,$Y$15:$AB$33,4,FALSE)*(O65/(VLOOKUP(N65,$Y$15:$AB$33,3,FALSE))),"") | Q65: =IFERROR((P65*$Z$11)/B65,"") | S65: =IFERROR(L65+Q65+($Z$8/$B$100)+($Z$9/$B$100)+($Z$3/$B$100)+($Z$2/$B$100)+($Z$4/$B$100)+($Z$5/$B$100)+($Z$6/$B$100),"") | T65: =IFERROR(ROUND(S65*'Quote Info'!$O$4+R65,2),"") | U65: =IFERROR(S65*B65,"") | V65: =IFERROR(T65*B65,"") | W65: =IFERROR(S65/((VLOOKUP(N65,'FB Data'!$A$2:$E$150,3,FALSE))*'FB Laser'!M65),"") | AC65: =IFERROR((AA65/12)*(AB65/12)*Z65,"") -> 0 | AD65: =IFERROR(IF($Z$7="JWMCD",VLOOKUP(Y65,'FB Data'!$A$2:$E$151,3,FALSE)*VLOOKUP(Y65,'FB Data'!$A$2:$E$151,5,FALSE)*AC65,IF($Z$7="Customer Supplied",0,"Need Input")),"")
G66: =IFERROR(((E66/60)*$Z$10)/B66,"") | H66: =IF(Forming!G66>0,Forming!G66,0) -> 0 | I66: =IF('Hardware Install'!E66>0,'Hardware Install'!E66,0) -> 0 | J66: =IFERROR(VLOOKUP('FB Laser'!A66,Machining!A66:G156,7,FALSE),"") | K66: =IFERROR(IF(Finishing!G66>0,VLOOKUP('FB Laser'!A66,Finishing!A66:G156,7,FALSE),""),"") | L66: =IFERROR(SUM((H66*$Z$12),G66,I66,J66,K66,'FB Data'!AM65),"") -> 0 | M66: =IFERROR((C66*D66)*0.00694,"") -> 0 | O66: =IFERROR((B66*M66)/(VLOOKUP(N66,$Y$15:$AB$33,2,FALSE)),"") | P66: =IFERROR(VLOOKUP(N66,$Y$15:$AB$33,4,FALSE)*(O66/(VLOOKUP(N66,$Y$15:$AB$33,3,FALSE))),"") | Q66: =IFERROR((P66*$Z$11)/B66,"") | S66: =IFERROR(L66+Q66+($Z$8/$B$100)+($Z$9/$B$100)+($Z$3/$B$100)+($Z$2/$B$100)+($Z$4/$B$100)+($Z$5/$B$100)+($Z$6/$B$100),"") | T66: =IFERROR(ROUND(S66*'Quote Info'!$O$4+R66,2),"") | U66: =IFERROR(S66*B66,"") | V66: =IFERROR(T66*B66,"") | W66: =IFERROR(S66/((VLOOKUP(N66,'FB Data'!$A$2:$E$150,3,FALSE))*'FB Laser'!M66),"")
G67: =IFERROR(((E67/60)*$Z$10)/B67,"") | H67: =IF(Forming!G67>0,Forming!G67,0) -> 0 | I67: =IF('Hardware Install'!E67>0,'Hardware Install'!E67,0) -> 0 | J67: =IFERROR(VLOOKUP('FB Laser'!A67,Machining!A67:G157,7,FALSE),"") | K67: =IFERROR(IF(Finishing!G67>0,VLOOKUP('FB Laser'!A67,Finishing!A67:G157,7,FALSE),""),"") | L67: =IFERROR(SUM((H67*$Z$12),G67,I67,J67,K67,'FB Data'!AM66),"") -> 0 | M67: =IFERROR((C67*D67)*0.00694,"") -> 0 | O67: =IFERROR((B67*M67)/(VLOOKUP(N67,$Y$15:$AB$33,2,FALSE)),"") | P67: =IFERROR(VLOOKUP(N67,$Y$15:$AB$33,4,FALSE)*(O67/(VLOOKUP(N67,$Y$15:$AB$33,3,FALSE))),"") | Q67: =IFERROR((P67*$Z$11)/B67,"") | S67: =IFERROR(L67+Q67+($Z$8/$B$100)+($Z$9/$B$100)+($Z$3/$B$100)+($Z$2/$B$100)+($Z$4/$B$100)+($Z$5/$B$100)+($Z$6/$B$100),"") | T67: =IFERROR(ROUND(S67*'Quote Info'!$O$4+R67,2),"") | U67: =IFERROR(S67*B67,"") | V67: =IFERROR(T67*B67,"") | W67: =IFERROR(S67/((VLOOKUP(N67,'FB Data'!$A$2:$E$150,3,FALSE))*'FB Laser'!M67),"")
G68: =IFERROR(((E68/60)*$Z$10)/B68,"") | H68: =IF(Forming!G68>0,Forming!G68,0) -> 0 | I68: =IF('Hardware Install'!E68>0,'Hardware Install'!E68,0) -> 0 | J68: =IFERROR(VLOOKUP('FB Laser'!A68,Machining!A68:G158,7,FALSE),"") | K68: =IFERROR(IF(Finishing!G68>0,VLOOKUP('FB Laser'!A68,Finishing!A68:G158,7,FALSE),""),"") | L68: =IFERROR(SUM((H68*$Z$12),G68,I68,J68,K68,'FB Data'!AM67),"") -> 0 | M68: =IFERROR((C68*D68)*0.00694,"") -> 0 | O68: =IFERROR((B68*M68)/(VLOOKUP(N68,$Y$15:$AB$33,2,FALSE)),"") | P68: =IFERROR(VLOOKUP(N68,$Y$15:$AB$33,4,FALSE)*(O68/(VLOOKUP(N68,$Y$15:$AB$33,3,FALSE))),"") | Q68: =IFERROR((P68*$Z$11)/B68,"") | S68: =IFERROR(L68+Q68+($Z$8/$B$100)+($Z$9/$B$100)+($Z$3/$B$100)+($Z$2/$B$100)+($Z$4/$B$100)+($Z$5/$B$100)+($Z$6/$B$100),"") | T68: =IFERROR(ROUND(S68*'Quote Info'!$O$4+R68,2),"") | U68: =IFERROR(S68*B68,"") | V68: =IFERROR(T68*B68,"") | W68: =IFERROR(S68/((VLOOKUP(N68,'FB Data'!$A$2:$E$150,3,FALSE))*'FB Laser'!M68),"")
G69: =IFERROR(((E69/60)*$Z$10)/B69,"") | H69: =IF(Forming!G69>0,Forming!G69,0) -> 0 | I69: =IF('Hardware Install'!E69>0,'Hardware Install'!E69,0) -> 0 | J69: =IFERROR(VLOOKUP('FB Laser'!A69,Machining!A69:G159,7,FALSE),"") | K69: =IFERROR(IF(Finishing!G69>0,VLOOKUP('FB Laser'!A69,Finishing!A69:G159,7,FALSE),""),"") | L69: =IFERROR(SUM((H69*$Z$12),G69,I69,J69,K69,'FB Data'!AM68),"") -> 0 | M69: =IFERROR((C69*D69)*0.00694,"") -> 0 | O69: =IFERROR((B69*M69)/(VLOOKUP(N69,$Y$15:$AB$33,2,FALSE)),"") | P69: =IFERROR(VLOOKUP(N69,$Y$15:$AB$33,4,FALSE)*(O69/(VLOOKUP(N69,$Y$15:$AB$33,3,FALSE))),"") | Q69: =IFERROR((P69*$Z$11)/B69,"") | S69: =IFERROR(L69+Q69+($Z$8/$B$100)+($Z$9/$B$100)+($Z$3/$B$100)+($Z$2/$B$100)+($Z$4/$B$100)+($Z$5/$B$100)+($Z$6/$B$100),"") | T69: =IFERROR(ROUND(S69*'Quote Info'!$O$4+R69,2),"") | U69: =IFERROR(S69*B69,"") | V69: =IFERROR(T69*B69,"") | W69: =IFERROR(S69/((VLOOKUP(N69,'FB Data'!$A$2:$E$150,3,FALSE))*'FB Laser'!M69),"")
G70: =IFERROR(((E70/60)*$Z$10)/B70,"") | H70: =IF(Forming!G70>0,Forming!G70,0) -> 0 | I70: =IF('Hardware Install'!E70>0,'Hardware Install'!E70,0) -> 0 | J70: =IFERROR(VLOOKUP('FB Laser'!A70,Machining!A70:G160,7,FALSE),"") | K70: =IFERROR(IF(Finishing!G70>0,VLOOKUP('FB Laser'!A70,Finishing!A70:G160,7,FALSE),""),"") | L70: =IFERROR(SUM((H70*$Z$12),G70,I70,J70,K70,'FB Data'!AM69),"") -> 0 | M70: =IFERROR((C70*D70)*0.00694,"") -> 0 | O70: =IFERROR((B70*M70)/(VLOOKUP(N70,$Y$15:$AB$33,2,FALSE)),"") | P70: =IFERROR(VLOOKUP(N70,$Y$15:$AB$33,4,FALSE)*(O70/(VLOOKUP(N70,$Y$15:$AB$33,3,FALSE))),"") | Q70: =IFERROR((P70*$Z$11)/B70,"") | S70: =IFERROR(L70+Q70+($Z$8/$B$100)+($Z$9/$B$100)+($Z$3/$B$100)+($Z$2/$B$100)+($Z$4/$B$100)+($Z$5/$B$100)+($Z$6/$B$100),"") | T70: =IFERROR(ROUND(S70*'Quote Info'!$O$4+R70,2),"") | U70: =IFERROR(S70*B70,"") | V70: =IFERROR(T70*B70,"") | W70: =IFERROR(S70/((VLOOKUP(N70,'FB Data'!$A$2:$E$150,3,FALSE))*'FB Laser'!M70),"")
G71: =IFERROR(((E71/60)*$Z$10)/B71,"") | H71: =IF(Forming!G71>0,Forming!G71,0) -> 0 | I71: =IF('Hardware Install'!E71>0,'Hardware Install'!E71,0) -> 0 | J71: =IFERROR(VLOOKUP('FB Laser'!A71,Machining!A71:G161,7,FALSE),"") | K71: =IFERROR(IF(Finishing!G71>0,VLOOKUP('FB Laser'!A71,Finishing!A71:G161,7,FALSE),""),"") | L71: =IFERROR(SUM((H71*$Z$12),G71,I71,J71,K71,'FB Data'!AM70),"") -> 0 | M71: =IFERROR((C71*D71)*0.00694,"") -> 0 | O71: =IFERROR((B71*M71)/(VLOOKUP(N71,$Y$15:$AB$33,2,FALSE)),"") | P71: =IFERROR(VLOOKUP(N71,$Y$15:$AB$33,4,FALSE)*(O71/(VLOOKUP(N71,$Y$15:$AB$33,3,FALSE))),"") | Q71: =IFERROR((P71*$Z$11)/B71,"") | S71: =IFERROR(L71+Q71+($Z$8/$B$100)+($Z$9/$B$100)+($Z$3/$B$100)+($Z$2/$B$100)+($Z$4/$B$100)+($Z$5/$B$100)+($Z$6/$B$100),"") | T71: =IFERROR(ROUND(S71*'Quote Info'!$O$4+R71,2),"") | U71: =IFERROR(S71*B71,"") | V71: =IFERROR(T71*B71,"") | W71: =IFERROR(S71/((VLOOKUP(N71,'FB Data'!$A$2:$E$150,3,FALSE))*'FB Laser'!M71),"")
G72: =IFERROR(((E72/60)*$Z$10)/B72,"") | H72: =IF(Forming!G72>0,Forming!G72,0) -> 0 | I72: =IF('Hardware Install'!E72>0,'Hardware Install'!E72,0) -> 0 | J72: =IFERROR(VLOOKUP('FB Laser'!A72,Machining!A72:G162,7,FALSE),"") | K72: =IFERROR(IF(Finishing!G72>0,VLOOKUP('FB Laser'!A72,Finishing!A72:G162,7,FALSE),""),"") | L72: =IFERROR(SUM((H72*$Z$12),G72,I72,J72,K72,'FB Data'!AM71),"") -> 0 | M72: =IFERROR((C72*D72)*0.00694,"") -> 0 | O72: =IFERROR((B72*M72)/(VLOOKUP(N72,$Y$15:$AB$33,2,FALSE)),"") | P72: =IFERROR(VLOOKUP(N72,$Y$15:$AB$33,4,FALSE)*(O72/(VLOOKUP(N72,$Y$15:$AB$33,3,FALSE))),"") | Q72: =IFERROR((P72*$Z$11)/B72,"") | S72: =IFERROR(L72+Q72+($Z$8/$B$100)+($Z$9/$B$100)+($Z$3/$B$100)+($Z$2/$B$100)+($Z$4/$B$100)+($Z$5/$B$100)+($Z$6/$B$100),"") | T72: =IFERROR(ROUND(S72*'Quote Info'!$O$4+R72,2),"") | U72: =IFERROR(S72*B72,"") | V72: =IFERROR(T72*B72,"") | W72: =IFERROR(S72/((VLOOKUP(N72,'FB Data'!$A$2:$E$150,3,FALSE))*'FB Laser'!M72),"")
G73: =IFERROR(((E73/60)*$Z$10)/B73,"") | H73: =IF(Forming!G73>0,Forming!G73,0) -> 0 | I73: =IF('Hardware Install'!E73>0,'Hardware Install'!E73,0) -> 0 | J73: =IFERROR(VLOOKUP('FB Laser'!A73,Machining!A73:G163,7,FALSE),"") | K73: =IFERROR(IF(Finishing!G73>0,VLOOKUP('FB Laser'!A73,Finishing!A73:G163,7,FALSE),""),"") | L73: =IFERROR(SUM((H73*$Z$12),G73,I73,J73,K73,'FB Data'!AM72),"") -> 0 | M73: =IFERROR((C73*D73)*0.00694,"") -> 0 | O73: =IFERROR((B73*M73)/(VLOOKUP(N73,$Y$15:$AB$33,2,FALSE)),"") | P73: =IFERROR(VLOOKUP(N73,$Y$15:$AB$33,4,FALSE)*(O73/(VLOOKUP(N73,$Y$15:$AB$33,3,FALSE))),"") | Q73: =IFERROR((P73*$Z$11)/B73,"") | S73: =IFERROR(L73+Q73+($Z$8/$B$100)+($Z$9/$B$100)+($Z$3/$B$100)+($Z$2/$B$100)+($Z$4/$B$100)+($Z$5/$B$100)+($Z$6/$B$100),"") | T73: =IFERROR(ROUND(S73*'Quote Info'!$O$4+R73,2),"") | U73: =IFERROR(S73*B73,"") | V73: =IFERROR(T73*B73,"") | W73: =IFERROR(S73/((VLOOKUP(N73,'FB Data'!$A$2:$E$150,3,FALSE))*'FB Laser'!M73),"")
G74: =IFERROR(((E74/60)*$Z$10)/B74,"") | H74: =IF(Forming!G74>0,Forming!G74,0) -> 0 | I74: =IF('Hardware Install'!E74>0,'Hardware Install'!E74,0) -> 0 | J74: =IFERROR(VLOOKUP('FB Laser'!A74,Machining!A74:G164,7,FALSE),"") | K74: =IFERROR(IF(Finishing!G74>0,VLOOKUP('FB Laser'!A74,Finishing!A74:G164,7,FALSE),""),"") | L74: =IFERROR(SUM((H74*$Z$12),G74,I74,J74,K74,'FB Data'!AM73),"") -> 0 | M74: =IFERROR((C74*D74)*0.00694,"") -> 0 | O74: =IFERROR((B74*M74)/(VLOOKUP(N74,$Y$15:$AB$33,2,FALSE)),"") | P74: =IFERROR(VLOOKUP(N74,$Y$15:$AB$33,4,FALSE)*(O74/(VLOOKUP(N74,$Y$15:$AB$33,3,FALSE))),"") | Q74: =IFERROR((P74*$Z$11)/B74,"") | S74: =IFERROR(L74+Q74+($Z$8/$B$100)+($Z$9/$B$100)+($Z$3/$B$100)+($Z$2/$B$100)+($Z$4/$B$100)+($Z$5/$B$100)+($Z$6/$B$100),"") | T74: =IFERROR(ROUND(S74*'Quote Info'!$O$4+R74,2),"") | U74: =IFERROR(S74*B74,"") | V74: =IFERROR(T74*B74,"") | W74: =IFERROR(S74/((VLOOKUP(N74,'FB Data'!$A$2:$E$150,3,FALSE))*'FB Laser'!M74),"")
G75: =IFERROR(((E75/60)*$Z$10)/B75,"") | H75: =IF(Forming!G75>0,Forming!G75,0) -> 0 | I75: =IF('Hardware Install'!E75>0,'Hardware Install'!E75,0) -> 0 | J75: =IFERROR(VLOOKUP('FB Laser'!A75,Machining!A75:G165,7,FALSE),"") | K75: =IFERROR(IF(Finishing!G75>0,VLOOKUP('FB Laser'!A75,Finishing!A75:G165,7,FALSE),""),"") | L75: =IFERROR(SUM((H75*$Z$12),G75,I75,J75,K75,'FB Data'!AM74),"") -> 0 | M75: =IFERROR((C75*D75)*0.00694,"") -> 0 | O75: =IFERROR((B75*M75)/(VLOOKUP(N75,$Y$15:$AB$33,2,FALSE)),"") | P75: =IFERROR(VLOOKUP(N75,$Y$15:$AB$33,4,FALSE)*(O75/(VLOOKUP(N75,$Y$15:$AB$33,3,FALSE))),"") | Q75: =IFERROR((P75*$Z$11)/B75,"") | S75: =IFERROR(L75+Q75+($Z$8/$B$100)+($Z$9/$B$100)+($Z$3/$B$100)+($Z$2/$B$100)+($Z$4/$B$100)+($Z$5/$B$100)+($Z$6/$B$100),"") | T75: =IFERROR(ROUND(S75*'Quote Info'!$O$4+R75,2),"") | U75: =IFERROR(S75*B75,"") | V75: =IFERROR(T75*B75,"") | W75: =IFERROR(S75/((VLOOKUP(N75,'FB Data'!$A$2:$E$150,3,FALSE))*'FB Laser'!M75),"")
G76: =IFERROR(((E76/60)*$Z$10)/B76,"") | H76: =IF(Forming!G76>0,Forming!G76,0) -> 0 | I76: =IF('Hardware Install'!E76>0,'Hardware Install'!E76,0) -> 0 | J76: =IFERROR(VLOOKUP('FB Laser'!A76,Machining!A76:G166,7,FALSE),"") | K76: =IFERROR(IF(Finishing!G76>0,VLOOKUP('FB Laser'!A76,Finishing!A76:G166,7,FALSE),""),"") | L76: =IFERROR(SUM((H76*$Z$12),G76,I76,J76,K76,'FB Data'!AM75),"") -> 0 | M76: =IFERROR((C76*D76)*0.00694,"") -> 0 | O76: =IFERROR((B76*M76)/(VLOOKUP(N76,$Y$15:$AB$33,2,FALSE)),"") | P76: =IFERROR(VLOOKUP(N76,$Y$15:$AB$33,4,FALSE)*(O76/(VLOOKUP(N76,$Y$15:$AB$33,3,FALSE))),"") | Q76: =IFERROR((P76*$Z$11)/B76,"") | S76: =IFERROR(L76+Q76+($Z$8/$B$100)+($Z$9/$B$100)+($Z$3/$B$100)+($Z$2/$B$100)+($Z$4/$B$100)+($Z$5/$B$100)+($Z$6/$B$100),"") | T76: =IFERROR(ROUND(S76*'Quote Info'!$O$4+R76,2),"") | U76: =IFERROR(S76*B76,"") | V76: =IFERROR(T76*B76,"") | W76: =IFERROR(S76/((VLOOKUP(N76,'FB Data'!$A$2:$E$150,3,FALSE))*'FB Laser'!M76),"")
G77: =IFERROR(((E77/60)*$Z$10)/B77,"") | H77: =IF(Forming!G77>0,Forming!G77,0) -> 0 | I77: =IF('Hardware Install'!E77>0,'Hardware Install'!E77,0) -> 0 | J77: =IFERROR(VLOOKUP('FB Laser'!A77,Machining!A77:G167,7,FALSE),"") | K77: =IFERROR(IF(Finishing!G77>0,VLOOKUP('FB Laser'!A77,Finishing!A77:G167,7,FALSE),""),"") | L77: =IFERROR(SUM((H77*$Z$12),G77,I77,J77,K77,'FB Data'!AM76),"") -> 0 | M77: =IFERROR((C77*D77)*0.00694,"") -> 0 | O77: =IFERROR((B77*M77)/(VLOOKUP(N77,$Y$15:$AB$33,2,FALSE)),"") | P77: =IFERROR(VLOOKUP(N77,$Y$15:$AB$33,4,FALSE)*(O77/(VLOOKUP(N77,$Y$15:$AB$33,3,FALSE))),"") | Q77: =IFERROR((P77*$Z$11)/B77,"") | S77: =IFERROR(L77+Q77+($Z$8/$B$100)+($Z$9/$B$100)+($Z$3/$B$100)+($Z$2/$B$100)+($Z$4/$B$100)+($Z$5/$B$100)+($Z$6/$B$100),"") | T77: =IFERROR(ROUND(S77*'Quote Info'!$O$4+R77,2),"") | U77: =IFERROR(S77*B77,"") | V77: =IFERROR(T77*B77,"") | W77: =IFERROR(S77/((VLOOKUP(N77,'FB Data'!$A$2:$E$150,3,FALSE))*'FB Laser'!M77),"")
... G99: =IFERROR(((E99/60)*$Z$10)/B99,"") | H99: =IF(Forming!G99>0,Forming!G99,0) -> 0 | I99: =IF('Hardware Install'!E99>0,'Hardware Install'!E99,0) -> 0 | J99: =IFERROR(VLOOKUP('FB Laser'!A99,Machining!A99:G189,7,FALSE),"") | K99: =IFERROR(IF(Finishing!G99>0,VLOOKUP('FB Laser'!A99,Finishing!A99:G189,7,FALSE),""),"") | L99: =IFERROR(SUM((H99*$Z$12),G99,I99,J99,K99,'FB Data'!AM98),"") -> 0 | M99: =IFERROR((C99*D99)*0.00694,"") -> 0 | O99: =IFERROR((B99*M99)/(VLOOKUP(N99,$Y$15:$AB$33,2,FALSE)),"") | P99: =IFERROR(VLOOKUP(N99,$Y$15:$AB$33,4,FALSE)*(O99/(VLOOKUP(N99,$Y$15:$AB$33,3,FALSE))),"") | Q99: =IFERROR((P99*$Z$11)/B99,"") | S99: =IFERROR(L99+Q99+($Z$8/$B$100)+($Z$9/$B$100)+($Z$3/$B$100)+($Z$2/$B$100)+($Z$4/$B$100)+($Z$5/$B$100)+($Z$6/$B$100),"") | T99: =IFERROR(ROUND(S99*'Quote Info'!$O$4+R99,2),"") | U99: =IFERROR(S99*B99,"") | V99: =IFERROR(T99*B99,"") | W99: =IFERROR(S99/((VLOOKUP(N99,'FB Data'!$A$2:$E$150,3,FALSE))*'FB Laser'!M99),"")
A100: Total Qty- | B100: =SUM(B10:B99) -> 0 | U100: =SUMIF(U10:U99,"<>#DIV/0!") -> 0 | V100: =SUMIF(V10:V99,"<>#DIV/0!") -> 0 | W100: =IFERROR(U100/AC34,"")

Sheet Tube Laser
AC1: Notes
AA2: Outsource | AB2: 0
AA3: Programming Fee | AB3: 60
AA4: QC | AB4: 0
AA5: Welding | AB5: =IF(Welding!G10="Tube",Welding!E10+Welding!D6,IF(Welding!G10="Flat&Tube",(Welding!E10+Welding!D6)/2,0)) -> 0
AA6: Material Source | AB6: JWMCD | AD6: User Defined
AA7: Pallet Charge | AB7: =IF(AC7="Default",(ROUNDUP((AE25/1500),0)*30),IF(AC7="User Defined",AD7,"Need Input")) -> 0 | AC7: Default | AD7: 0
A8: dwg# | B8: Qty | C8: Length (in) | D8: Tube Laser Each (sec) | E8: Bevel | F8: Etch | G8: Tap Holes | H8: Seam | I8: Notes? | J8: Laser Cost (Each) | K8: Tube Bending (Each) | L8: Machining (Each) | M8: Finishing (Each) | N8: Labor (Each) | O8: linear ft (Each) | P8: Material ID | Q8: % Material Used | R8: Material Cost (LOT) | S8: Material PRICE (EACH) | T8: Adjustment | U8: Total Cost (Each) | V8: Total Price (Each) | W8: Lot Cost | X8: Lot Price | Y8: Cost/Lbs | AA8: Delivery Charge | AB8: =IF(AC8="Delivery",ROUNDUP((AE25/8000),0)*100,IF(AC8="Will-Call",0,"Need Input")) -> 0 | AC8: Delivery
J9: =IFERROR((((D9)/60)/60)*$AB$9,"") -> 0 | K9: ='Tube Bending'!E9 -> 0 | L9: =IFERROR(VLOOKUP('Tube Laser'!A9,Machining!A10:G100,7,FALSE),"") | M9: =IFERROR(IF(Finishing!G10>0,VLOOKUP('Tube Laser'!A9,Finishing!A10:G100,7,FALSE),0),"") -> 0 | N9: =SUM(J9,K9,L9,M9,'FB Data'!AR9) -> 0 | O9: =C9/12 -> 0 | Q9: =IFERROR((B9*O9)/(VLOOKUP(P9,$AA$14:$AD$24,2,FALSE)),"") | R9: =IFERROR(VLOOKUP(P9,$AA$14:$AD$24,4,FALSE)*(Q9/(VLOOKUP(P9,$AA$14:$AD$24,3,FALSE))),"") | S9: =IFERROR((R9*$AB$10)/B9,"") | U9: =IFERROR(N9+S9+'FB Data'!AE9+'FB Data'!AF9+'FB Data'!AG9+'FB Data'!AH9+($AB$7/$B$99)+($AB$8/$B$99)+($AB$3/$B$99)+($AB$2/$B$99)+($AB$4/$B$99)+($AB$5/$B$99),"") | V9: =IFERROR(ROUND(U9*'Quote Info'!$O$4+T9,2),"") | W9: =IFERROR(U9*B9,"") | X9: =IFERROR(V9*B9,"") | Y9: =IFERROR(U9/((VLOOKUP(P9,'TL Data'!$A$2:$E$1226,3,FALSE))*'Tube Laser'!O9),"") | AA9: Tube Laser/Hr (Cost) | AB9: 188.17 | AC9: =AB9*'Quote Info'!O4 -> 255.9112
J10: =IFERROR((((D10)/60)/60)*$AB$9,"") -> 0 | K10: ='Tube Bending'!E10 -> 0 | L10: =IFERROR(VLOOKUP('Tube Laser'!A10,Machining!A11:G101,7,FALSE),"") | M10: =IFERROR(IF(Finishing!G11>0,VLOOKUP('Tube Laser'!A10,Finishing!A11:G101,7,FALSE),0),"") -> 0 | N10: =SUM(J10,K10,L10,M10,'FB Data'!AR10) -> 0 | O10: =C10/12 -> 0 | Q10: =IFERROR((B10*O10)/(VLOOKUP(P10,$AA$14:$AD$24,2,FALSE)),"") | R10: =IFERROR(VLOOKUP(P10,$AA$14:$AD$24,4,FALSE)*(Q10/(VLOOKUP(P10,$AA$14:$AD$24,3,FALSE))),"") | S10: =IFERROR((R10*$AB$10)/B10,"") | U10: =IFERROR(N10+S10+'FB Data'!AE10+'FB Data'!AF10+'FB Data'!AG10+'FB Data'!AH10+($AB$7/$B$99)+($AB$8/$B$99)+($AB$3/$B$99)+($AB$2/$B$99)+($AB$4/$B$99)+($AB$5/$B$99),"") | V10: =IFERROR(ROUND(U10*'Quote Info'!$O$4+T10,2),"") | W10: =IFERROR(U10*B10,"") | X10: =IFERROR(V10*B10,"") | Y10: =IFERROR(U10/((VLOOKUP(P10,'TL Data'!$A$2:$E$1226,3,FALSE))*'Tube Laser'!O10),"") | AA10: Material Mark-Up | AB10: 1
J11: =IFERROR((((D11)/60)/60)*$AB$9,"") -> 0 | K11: ='Tube Bending'!E11 -> 0 | L11: =IFERROR(VLOOKUP('Tube Laser'!A11,Machining!A12:G102,7,FALSE),"") | M11: =IFERROR(IF(Finishing!G12>0,VLOOKUP('Tube Laser'!A11,Finishing!A12:G102,7,FALSE),0),"") -> 0 | N11: =SUM(J11,K11,L11,M11,'FB Data'!AR11) -> 0 | O11: =C11/12 -> 0 | Q11: =IFERROR((B11*O11)/(VLOOKUP(P11,$AA$14:$AD$24,2,FALSE)),"") | R11: =IFERROR(VLOOKUP(P11,$AA$14:$AD$24,4,FALSE)*(Q11/(VLOOKUP(P11,$AA$14:$AD$24,3,FALSE))),"") | S11: =IFERROR((R11*$AB$10)/B11,"") | U11: =IFERROR(N11+S11+'FB Data'!AE11+'FB Data'!AF11+'FB Data'!AG11+'FB Data'!AH11+($AB$7/$B$99)+($AB$8/$B$99)+($AB$3/$B$99)+($AB$2/$B$99)+($AB$4/$B$99)+($AB$5/$B$99),"") | V11: =IFERROR(ROUND(U11*'Quote Info'!$O$4+T11,2),"") | W11: =IFERROR(U11*B11,"") | X11: =IFERROR(V11*B11,"") | Y11: =IFERROR(U11/((VLOOKUP(P11,'TL Data'!$A$2:$E$1226,3,FALSE))*'Tube Laser'!O11),"")
J12: =IFERROR((((D12)/60)/60)*$AB$9,"") -> 0 | K12: ='Tube Bending'!E12 -> 0 | L12: =IFERROR(VLOOKUP('Tube Laser'!A12,Machining!A13:G103,7,FALSE),"") | M12: =IFERROR(IF(Finishing!G13>0,VLOOKUP('Tube Laser'!A12,Finishing!A13:G103,7,FALSE),0),"") -> 0 | N12: =SUM(J12,K12,L12,M12,'FB Data'!AR12) -> 0 | O12: =C12/12 -> 0 | Q12: =IFERROR((B12*O12)/(VLOOKUP(P12,$AA$14:$AD$24,2,FALSE)),"") | R12: =IFERROR(VLOOKUP(P12,$AA$14:$AD$24,4,FALSE)*(Q12/(VLOOKUP(P12,$AA$14:$AD$24,3,FALSE))),"") | S12: =IFERROR((R12*$AB$10)/B12,"") | U12: =IFERROR(N12+S12+'FB Data'!AE12+'FB Data'!AF12+'FB Data'!AG12+'FB Data'!AH12+($AB$7/$B$99)+($AB$8/$B$99)+($AB$3/$B$99)+($AB$2/$B$99)+($AB$4/$B$99)+($AB$5/$B$99),"") | V12: =IFERROR(ROUND(U12*'Quote Info'!$O$4+T12,2),"") | W12: =IFERROR(U12*B12,"") | X12: =IFERROR(V12*B12,"") | Y12: =IFERROR(U12/((VLOOKUP(P12,'TL Data'!$A$2:$E$1226,3,FALSE))*'Tube Laser'!O12),"")
J13: =IFERROR((((D13)/60)/60)*$AB$9,"") -> 0 | K13: ='Tube Bending'!E13 -> 0 | L13: =IFERROR(VLOOKUP('Tube Laser'!A13,Machining!A14:G104,7,FALSE),"") | M13: =IFERROR(IF(Finishing!G14>0,VLOOKUP('Tube Laser'!A13,Finishing!A14:G104,7,FALSE),0),"") -> 0 | N13: =SUM(J13,K13,L13,M13,'FB Data'!AR13) -> 0 | O13: =C13/12 -> 0 | Q13: =IFERROR((B13*O13)/(VLOOKUP(P13,$AA$14:$AD$24,2,FALSE)),"") | R13: =IFERROR(VLOOKUP(P13,$AA$14:$AD$24,4,FALSE)*(Q13/(VLOOKUP(P13,$AA$14:$AD$24,3,FALSE))),"") | S13: =IFERROR((R13*$AB$10)/B13,"") | U13: =IFERROR(N13+S13+'FB Data'!AE13+'FB Data'!AF13+'FB Data'!AG13+'FB Data'!AH13+($AB$7/$B$99)+($AB$8/$B$99)+($AB$3/$B$99)+($AB$2/$B$99)+($AB$4/$B$99)+($AB$5/$B$99),"") | V13: =IFERROR(ROUND(U13*'Quote Info'!$O$4+T13,2),"") | W13: =IFERROR(U13*B13,"") | X13: =IFERROR(V13*B13,"") | Y13: =IFERROR(U13/((VLOOKUP(P13,'TL Data'!$A$2:$E$1226,3,FALSE))*'Tube Laser'!O13),"") | AA13: Material ID | AB13: Total Linear ft | AC13: Yield % | AD13: Total Cost | AE13: Total Weight (lbs)
J14: =IFERROR((((D14)/60)/60)*$AB$9,"") -> 0 | K14: ='Tube Bending'!E14 -> 0 | L14: =IFERROR(VLOOKUP('Tube Laser'!A14,Machining!A15:G105,7,FALSE),"") | M14: =IFERROR(IF(Finishing!G15>0,VLOOKUP('Tube Laser'!A14,Finishing!A15:G105,7,FALSE),0),"") -> 0 | N14: =SUM(J14,K14,L14,M14,'FB Data'!AR14) -> 0 | O14: =C14/12 -> 0 | Q14: =IFERROR((B14*O14)/(VLOOKUP(P14,$AA$14:$AD$24,2,FALSE)),"") | R14: =IFERROR(VLOOKUP(P14,$AA$14:$AD$24,4,FALSE)*(Q14/(VLOOKUP(P14,$AA$14:$AD$24,3,FALSE))),"") | S14: =IFERROR((R14*$AB$10)/B14,"") | U14: =IFERROR(N14+S14+'FB Data'!AE14+'FB Data'!AF14+'FB Data'!AG14+'FB Data'!AH14+($AB$7/$B$99)+($AB$8/$B$99)+($AB$3/$B$99)+($AB$2/$B$99)+($AB$4/$B$99)+($AB$5/$B$99),"") | V14: =IFERROR(ROUND(U14*'Quote Info'!$O$4+T14,2),"") | W14: =IFERROR(U14*B14,"") | X14: =IFERROR(V14*B14,"") | Y14: =IFERROR(U14/((VLOOKUP(P14,'TL Data'!$A$2:$E$1226,3,FALSE))*'Tube Laser'!O14),"") | AA14: {=IFERROR(INDEX($AA$30:$AA$56, MATCH(0,IF(ISBLANK($AA$30:$AA$56),1,COUNTIF($AA$13:AA13, $AA$30:$AA$56)), 0)),"")} | AB14: =SUMIF($AA$30:$AA$56,AA14,$AD$30:$AD$56) -> 0 | AC14: =SUMIF($P$9:$P$98,AA14,$Q$9:$Q$98) -> 0 | AD14: =SUMIF($AA$30:$AA$56,AA14,$AE$30:$AE$56) -> 0 | AE14: =IFERROR(AB14*AC14*VLOOKUP(AA14,'TL Data'!$A$2:$E$1226,3,FALSE),"")
J15: =IFERROR((((D15)/60)/60)*$AB$9,"") -> 0 | K15: ='Tube Bending'!E15 -> 0 | L15: =IFERROR(VLOOKUP('Tube Laser'!A15,Machining!A16:G106,7,FALSE),"") | M15: =IFERROR(IF(Finishing!G16>0,VLOOKUP('Tube Laser'!A15,Finishing!A16:G106,7,FALSE),0),"") -> 0 | N15: =SUM(J15,K15,L15,M15,'FB Data'!AR15) -> 0 | O15: =C15/12 -> 0 | Q15: =IFERROR((B15*O15)/(VLOOKUP(P15,$AA$14:$AD$24,2,FALSE)),"") | R15: =IFERROR(VLOOKUP(P15,$AA$14:$AD$24,4,FALSE)*(Q15/(VLOOKUP(P15,$AA$14:$AD$24,3,FALSE))),"") | S15: =IFERROR((R15*$AB$10)/B15,"") | U15: =IFERROR(N15+S15+'FB Data'!AE15+'FB Data'!AF15+'FB Data'!AG15+'FB Data'!AH15+($AB$7/$B$99)+($AB$8/$B$99)+($AB$3/$B$99)+($AB$2/$B$99)+($AB$4/$B$99)+($AB$5/$B$99),"") | V15: =IFERROR(ROUND(U15*'Quote Info'!$O$4+T15,2),"") | W15: =IFERROR(U15*B15,"") | X15: =IFERROR(V15*B15,"") | Y15: =IFERROR(U15/((VLOOKUP(P15,'TL Data'!$A$2:$E$1226,3,FALSE))*'Tube Laser'!O15),"") | AA15: {=IFERROR(INDEX($AA$30:$AA$56, MATCH(0,IF(ISBLANK($AA$30:$AA$56),1,COUNTIF($AA$13:AA14, $AA$30:$AA$56)), 0)),"")} | AB15: =SUMIF($AA$30:$AA$56,AA15,$AD$30:$AD$56) -> 0 | AC15: =SUMIF($P$9:$P$98,AA15,$Q$9:$Q$98) -> 0 | AD15: =SUMIF($AA$30:$AA$56,AA15,$AE$30:$AE$56) -> 0 | AE15: =IFERROR(AB15*AC15*VLOOKUP(AA15,'TL Data'!$A$2:$E$1226,3,FALSE),"")
J16: =IFERROR((((D16)/60)/60)*$AB$9,"") -> 0 | K16: ='Tube Bending'!E16 -> 0 | L16: =IFERROR(VLOOKUP('Tube Laser'!A16,Machining!A17:G107,7,FALSE),"") | M16: =IFERROR(IF(Finishing!G17>0,VLOOKUP('Tube Laser'!A16,Finishing!A17:G107,7,FALSE),0),"") -> 0 | N16: =SUM(J16,K16,L16,M16,'FB Data'!AR16) -> 0 | O16: =C16/12 -> 0 | Q16: =IFERROR((B16*O16)/(VLOOKUP(P16,$AA$14:$AD$24,2,FALSE)),"") | R16: =IFERROR(VLOOKUP(P16,$AA$14:$AD$24,4,FALSE)*(Q16/(VLOOKUP(P16,$AA$14:$AD$24,3,FALSE))),"") | S16: =IFERROR((R16*$AB$10)/B16,"") | U16: =IFERROR(N16+S16+'FB Data'!AE16+'FB Data'!AF16+'FB Data'!AG16+'FB Data'!AH16+($AB$7/$B$99)+($AB$8/$B$99)+($AB$3/$B$99)+($AB$2/$B$99)+($AB$4/$B$99)+($AB$5/$B$99),"") | V16: =IFERROR(ROUND(U16*'Quote Info'!$O$4+T16,2),"") | W16: =IFERROR(U16*B16,"") | X16: =IFERROR(V16*B16,"") | Y16: =IFERROR(U16/((VLOOKUP(P16,'TL Data'!$A$2:$E$1226,3,FALSE))*'Tube Laser'!O16),"") | AA16: {=IFERROR(INDEX($AA$30:$AA$56, MATCH(0,IF(ISBLANK($AA$30:$AA$56),1,COUNTIF($AA$13:AA15, $AA$30:$AA$56)), 0)),"")} | AB16: =SUMIF($AA$30:$AA$56,AA16,$AD$30:$AD$56) -> 0 | AC16: =SUMIF($P$9:$P$98,AA16,$Q$9:$Q$98) -> 0 | AD16: =SUMIF($AA$30:$AA$56,AA16,$AE$30:$AE$56) -> 0 | AE16: =IFERROR(AB16*AC16*VLOOKUP(AA16,'TL Data'!$A$2:$E$1226,3,FALSE),"")
J17: =IFERROR((((D17)/60)/60)*$AB$9,"") -> 0 | K17: ='Tube Bending'!E17 -> 0 | L17: =IFERROR(VLOOKUP('Tube Laser'!A17,Machining!A18:G108,7,FALSE),"") | M17: =IFERROR(IF(Finishing!G18>0,VLOOKUP('Tube Laser'!A17,Finishing!A18:G108,7,FALSE),0),"") -> 0 | N17: =SUM(J17,K17,L17,M17,'FB Data'!AR17) -> 0 | O17: =C17/12 -> 0 | Q17: =IFERROR((B17*O17)/(VLOOKUP(P17,$AA$14:$AD$24,2,FALSE)),"") | R17: =IFERROR(VLOOKUP(P17,$AA$14:$AD$24,4,FALSE)*(Q17/(VLOOKUP(P17,$AA$14:$AD$24,3,FALSE))),"") | S17: =IFERROR((R17*$AB$10)/B17,"") | U17: =IFERROR(N17+S17+'FB Data'!AE17+'FB Data'!AF17+'FB Data'!AG17+'FB Data'!AH17+($AB$7/$B$99)+($AB$8/$B$99)+($AB$3/$B$99)+($AB$2/$B$99)+($AB$4/$B$99)+($AB$5/$B$99),"") | V17: =IFERROR(ROUND(U17*'Quote Info'!$O$4+T17,2),"") | W17: =IFERROR(U17*B17,"") | X17: =IFERROR(V17*B17,"") | Y17: =IFERROR(U17/((VLOOKUP(P17,'TL Data'!$A$2:$E$1226,3,FALSE))*'Tube Laser'!O17),"") | AA17: {=IFERROR(INDEX($AA$30:$AA$56, MATCH(0,IF(ISBLANK($AA$30:$AA$56),1,COUNTIF($AA$13:AA16, $AA$30:$AA$56)), 0)),"")} | AB17: =SUMIF($AA$30:$AA$56,AA17,$AD$30:$AD$56) -> 0 | AC17: =SUMIF($P$9:$P$98,AA17,$Q$9:$Q$98) -> 0 | AD17: =SUMIF($AA$30:$AA$56,AA17,$AE$30:$AE$56) -> 0 | AE17: =IFERROR(AB17*AC17*VLOOKUP(AA17,'TL Data'!$A$2:$E$1226,3,FALSE),"")
J18: =IFERROR((((D18)/60)/60)*$AB$9,"") -> 0 | K18: ='Tube Bending'!E18 -> 0 | L18: =IFERROR(VLOOKUP('Tube Laser'!A18,Machining!A19:G109,7,FALSE),"") | M18: =IFERROR(IF(Finishing!G19>0,VLOOKUP('Tube Laser'!A18,Finishing!A19:G109,7,FALSE),0),"") -> 0 | N18: =SUM(J18,K18,L18,M18,'FB Data'!AR18) -> 0 | O18: =C18/12 -> 0 | Q18: =IFERROR((B18*O18)/(VLOOKUP(P18,$AA$14:$AD$24,2,FALSE)),"") | R18: =IFERROR(VLOOKUP(P18,$AA$14:$AD$24,4,FALSE)*(Q18/(VLOOKUP(P18,$AA$14:$AD$24,3,FALSE))),"") | S18: =IFERROR((R18*$AB$10)/B18,"") | U18: =IFERROR(N18+S18+'FB Data'!AE18+'FB Data'!AF18+'FB Data'!AG18+'FB Data'!AH18+($AB$7/$B$99)+($AB$8/$B$99)+($AB$3/$B$99)+($AB$2/$B$99)+($AB$4/$B$99)+($AB$5/$B$99),"") | V18: =IFERROR(ROUND(U18*'Quote Info'!$O$4+T18,2),"") | W18: =IFERROR(U18*B18,"") | X18: =IFERROR(V18*B18,"") | Y18: =IFERROR(U18/((VLOOKUP(P18,'TL Data'!$A$2:$E$1226,3,FALSE))*'Tube Laser'!O18),"") | AA18: {=IFERROR(INDEX($AA$30:$AA$56, MATCH(0,IF(ISBLANK($AA$30:$AA$56),1,COUNTIF($AA$13:AA17, $AA$30:$AA$56)), 0)),"")} | AB18: =SUMIF($AA$30:$AA$56,AA18,$AD$30:$AD$56) -> 0 | AC18: =SUMIF($P$9:$P$98,AA18,$Q$9:$Q$98) -> 0 | AD18: =SUMIF($AA$30:$AA$56,AA18,$AE$30:$AE$56) -> 0 | AE18: =IFERROR(AB18*AC18*VLOOKUP(AA18,'TL Data'!$A$2:$E$1226,3,FALSE),"")
J19: =IFERROR((((D19)/60)/60)*$AB$9,"") -> 0 | K19: ='Tube Bending'!E19 -> 0 | L19: =IFERROR(VLOOKUP('Tube Laser'!A19,Machining!A20:G110,7,FALSE),"") | M19: =IFERROR(IF(Finishing!G20>0,VLOOKUP('Tube Laser'!A19,Finishing!A20:G110,7,FALSE),0),"") -> 0 | N19: =SUM(J19,K19,L19,M19,'FB Data'!AR19) -> 0 | O19: =C19/12 -> 0 | Q19: =IFERROR((B19*O19)/(VLOOKUP(P19,$AA$14:$AD$24,2,FALSE)),"") | R19: =IFERROR(VLOOKUP(P19,$AA$14:$AD$24,4,FALSE)*(Q19/(VLOOKUP(P19,$AA$14:$AD$24,3,FALSE))),"") | S19: =IFERROR((R19*$AB$10)/B19,"") | U19: =IFERROR(N19+S19+'FB Data'!AE19+'FB Data'!AF19+'FB Data'!AG19+'FB Data'!AH19+($AB$7/$B$99)+($AB$8/$B$99)+($AB$3/$B$99)+($AB$2/$B$99)+($AB$4/$B$99)+($AB$5/$B$99),"") | V19: =IFERROR(ROUND(U19*'Quote Info'!$O$4+T19,2),"") | W19: =IFERROR(U19*B19,"") | X19: =IFERROR(V19*B19,"") | Y19: =IFERROR(U19/((VLOOKUP(P19,'TL Data'!$A$2:$E$1226,3,FALSE))*'Tube Laser'!O19),"") | AA19: {=IFERROR(INDEX($AA$30:$AA$56, MATCH(0,IF(ISBLANK($AA$30:$AA$56),1,COUNTIF($AA$13:AA18, $AA$30:$AA$56)), 0)),"")} | AB19: =SUMIF($AA$30:$AA$56,AA19,$AD$30:$AD$56) -> 0 | AC19: =SUMIF($P$9:$P$98,AA19,$Q$9:$Q$98) -> 0 | AD19: =SUMIF($AA$30:$AA$56,AA19,$AE$30:$AE$56) -> 0 | AE19: =IFERROR(AB19*AC19*VLOOKUP(AA19,'TL Data'!$A$2:$E$1226,3,FALSE),"")
J20: =IFERROR((((D20)/60)/60)*$AB$9,"") -> 0 | K20: ='Tube Bending'!E20 -> 0 | L20: =IFERROR(VLOOKUP('Tube Laser'!A20,Machining!A21:G111,7,FALSE),"") | M20: =IFERROR(IF(Finishing!G21>0,VLOOKUP('Tube Laser'!A20,Finishing!A21:G111,7,FALSE),0),"") -> 0 | N20: =SUM(J20,K20,L20,M20,'FB Data'!AR20) -> 0 | O20: =C20/12 -> 0 | Q20: =IFERROR((B20*O20)/(VLOOKUP(P20,$AA$14:$AD$24,2,FALSE)),"") | R20: =IFERROR(VLOOKUP(P20,$AA$14:$AD$24,4,FALSE)*(Q20/(VLOOKUP(P20,$AA$14:$AD$24,3,FALSE))),"") | S20: =IFERROR((R20*$AB$10)/B20,"") | U20: =IFERROR(N20+S20+'FB Data'!AE20+'FB Data'!AF20+'FB Data'!AG20+'FB Data'!AH20+($AB$7/$B$99)+($AB$8/$B$99)+($AB$3/$B$99)+($AB$2/$B$99)+($AB$4/$B$99)+($AB$5/$B$99),"") | V20: =IFERROR(ROUND(U20*'Quote Info'!$O$4+T20,2),"") | W20: =IFERROR(U20*B20,"") | X20: =IFERROR(V20*B20,"") | Y20: =IFERROR(U20/((VLOOKUP(P20,'TL Data'!$A$2:$E$1226,3,FALSE))*'Tube Laser'!O20),"") | AA20: {=IFERROR(INDEX($AA$30:$AA$56, MATCH(0,IF(ISBLANK($AA$30:$AA$56),1,COUNTIF($AA$13:AA19, $AA$30:$AA$56)), 0)),"")} | AB20: =SUMIF($AA$30:$AA$56,AA20,$AD$30:$AD$56) -> 0 | AC20: =SUMIF($P$9:$P$98,AA20,$Q$9:$Q$98) -> 0 | AD20: =SUMIF($AA$30:$AA$56,AA20,$AE$30:$AE$56) -> 0 | AE20: =IFERROR(AB20*AC20*VLOOKUP(AA20,'TL Data'!$A$2:$E$1226,3,FALSE),"")
J21: =IFERROR((((D21)/60)/60)*$AB$9,"") -> 0 | K21: ='Tube Bending'!E21 -> 0 | L21: =IFERROR(VLOOKUP('Tube Laser'!A21,Machining!A22:G112,7,FALSE),"") | M21: =IFERROR(IF(Finishing!G22>0,VLOOKUP('Tube Laser'!A21,Finishing!A22:G112,7,FALSE),0),"") -> 0 | N21: =SUM(J21,K21,L21,M21,'FB Data'!AR21) -> 0 | O21: =C21/12 -> 0 | Q21: =IFERROR((B21*O21)/(VLOOKUP(P21,$AA$14:$AD$24,2,FALSE)),"") | R21: =IFERROR(VLOOKUP(P21,$AA$14:$AD$24,4,FALSE)*(Q21/(VLOOKUP(P21,$AA$14:$AD$24,3,FALSE))),"") | S21: =IFERROR((R21*$AB$10)/B21,"") | U21: =IFERROR(N21+S21+'FB Data'!AE21+'FB Data'!AF21+'FB Data'!AG21+'FB Data'!AH21+($AB$7/$B$99)+($AB$8/$B$99)+($AB$3/$B$99)+($AB$2/$B$99)+($AB$4/$B$99)+($AB$5/$B$99),"") | V21: =IFERROR(ROUND(U21*'Quote Info'!$O$4+T21,2),"") | W21: =IFERROR(U21*B21,"") | X21: =IFERROR(V21*B21,"") | Y21: =IFERROR(U21/((VLOOKUP(P21,'TL Data'!$A$2:$E$1226,3,FALSE))*'Tube Laser'!O21),"") | AA21: {=IFERROR(INDEX($AA$30:$AA$56, MATCH(0,IF(ISBLANK($AA$30:$AA$56),1,COUNTIF($AA$13:AA20, $AA$30:$AA$56)), 0)),"")} | AB21: =SUMIF($AA$30:$AA$56,AA21,$AD$30:$AD$56) -> 0 | AC21: =SUMIF($P$9:$P$98,AA21,$Q$9:$Q$98) -> 0 | AD21: =SUMIF($AA$30:$AA$56,AA21,$AE$30:$AE$56) -> 0 | AE21: =IFERROR(AB21*AC21*VLOOKUP(AA21,'TL Data'!$A$2:$E$1226,3,FALSE),"")
J22: =IFERROR((((D22)/60)/60)*$AB$9,"") -> 0 | K22: ='Tube Bending'!E22 -> 0 | L22: =IFERROR(VLOOKUP('Tube Laser'!A22,Machining!A23:G113,7,FALSE),"") | M22: =IFERROR(IF(Finishing!G23>0,VLOOKUP('Tube Laser'!A22,Finishing!A23:G113,7,FALSE),0),"") -> 0 | N22: =SUM(J22,K22,L22,M22,'FB Data'!AR22) -> 0 | O22: =C22/12 -> 0 | Q22: =IFERROR((B22*O22)/(VLOOKUP(P22,$AA$14:$AD$24,2,FALSE)),"") | R22: =IFERROR(VLOOKUP(P22,$AA$14:$AD$24,4,FALSE)*(Q22/(VLOOKUP(P22,$AA$14:$AD$24,3,FALSE))),"") | S22: =IFERROR((R22*$AB$10)/B22,"") | U22: =IFERROR(N22+S22+'FB Data'!AE22+'FB Data'!AF22+'FB Data'!AG22+'FB Data'!AH22+($AB$7/$B$99)+($AB$8/$B$99)+($AB$3/$B$99)+($AB$2/$B$99)+($AB$4/$B$99)+($AB$5/$B$99),"") | V22: =IFERROR(ROUND(U22*'Quote Info'!$O$4+T22,2),"") | W22: =IFERROR(U22*B22,"") | X22: =IFERROR(V22*B22,"") | Y22: =IFERROR(U22/((VLOOKUP(P22,'TL Data'!$A$2:$E$1226,3,FALSE))*'Tube Laser'!O22),"") | AA22: {=IFERROR(INDEX($AA$30:$AA$56, MATCH(0,IF(ISBLANK($AA$30:$AA$56),1,COUNTIF($AA$13:AA21, $AA$30:$AA$56)), 0)),"")} | AB22: =SUMIF($AA$30:$AA$56,AA22,$AD$30:$AD$56) -> 0 | AC22: =SUMIF($P$9:$P$98,AA22,$Q$9:$Q$98) -> 0 | AD22: =SUMIF($AA$30:$AA$56,AA22,$AE$30:$AE$56) -> 0 | AE22: =IFERROR(AB22*AC22*VLOOKUP(AA22,'TL Data'!$A$2:$E$1226,3,FALSE),"")
J23: =IFERROR((((D23)/60)/60)*$AB$9,"") -> 0 | K23: ='Tube Bending'!E23 -> 0 | L23: =IFERROR(VLOOKUP('Tube Laser'!A23,Machining!A24:G114,7,FALSE),"") | M23: =IFERROR(IF(Finishing!G24>0,VLOOKUP('Tube Laser'!A23,Finishing!A24:G114,7,FALSE),0),"") -> 0 | N23: =SUM(J23,K23,L23,M23,'FB Data'!AR23) -> 0 | O23: =C23/12 -> 0 | Q23: =IFERROR((B23*O23)/(VLOOKUP(P23,$AA$14:$AD$24,2,FALSE)),"") | R23: =IFERROR(VLOOKUP(P23,$AA$14:$AD$24,4,FALSE)*(Q23/(VLOOKUP(P23,$AA$14:$AD$24,3,FALSE))),"") | S23: =IFERROR((R23*$AB$10)/B23,"") | U23: =IFERROR(N23+S23+'FB Data'!AE23+'FB Data'!AF23+'FB Data'!AG23+'FB Data'!AH23+($AB$7/$B$99)+($AB$8/$B$99)+($AB$3/$B$99)+($AB$2/$B$99)+($AB$4/$B$99)+($AB$5/$B$99),"") | V23: =IFERROR(ROUND(U23*'Quote Info'!$O$4+T23,2),"") | W23: =IFERROR(U23*B23,"") | X23: =IFERROR(V23*B23,"") | Y23: =IFERROR(U23/((VLOOKUP(P23,'TL Data'!$A$2:$E$1226,3,FALSE))*'Tube Laser'!O23),"") | AA23: {=IFERROR(INDEX($AA$30:$AA$56, MATCH(0,IF(ISBLANK($AA$30:$AA$56),1,COUNTIF($AA$13:AA22, $AA$30:$AA$56)), 0)),"")} | AB23: =SUMIF($AA$30:$AA$56,AA23,$AD$30:$AD$56) -> 0 | AC23: =SUMIF($P$9:$P$98,AA23,$Q$9:$Q$98) -> 0 | AD23: =SUMIF($AA$30:$AA$56,AA23,$AE$30:$AE$56) -> 0 | AE23: =IFERROR(AB23*AC23*VLOOKUP(AA23,'TL Data'!$A$2:$E$1226,3,FALSE),"")
J24: =IFERROR((((D24)/60)/60)*$AB$9,"") -> 0 | K24: ='Tube Bending'!E24 -> 0 | L24: =IFERROR(VLOOKUP('Tube Laser'!A24,Machining!A25:G115,7,FALSE),"") | M24: =IFERROR(IF(Finishing!G25>0,VLOOKUP('Tube Laser'!A24,Finishing!A25:G115,7,FALSE),0),"") -> 0 | N24: =SUM(J24,K24,L24,M24,'FB Data'!AR24) -> 0 | O24: =C24/12 -> 0 | Q24: =IFERROR((B24*O24)/(VLOOKUP(P24,$AA$14:$AD$24,2,FALSE)),"") | R24: =IFERROR(VLOOKUP(P24,$AA$14:$AD$24,4,FALSE)*(Q24/(VLOOKUP(P24,$AA$14:$AD$24,3,FALSE))),"") | S24: =IFERROR((R24*$AB$10)/B24,"") | U24: =IFERROR(N24+S24+'FB Data'!AE24+'FB Data'!AF24+'FB Data'!AG24+'FB Data'!AH24+($AB$7/$B$99)+($AB$8/$B$99)+($AB$3/$B$99)+($AB$2/$B$99)+($AB$4/$B$99)+($AB$5/$B$99),"") | V24: =IFERROR(ROUND(U24*'Quote Info'!$O$4+T24,2),"") | W24: =IFERROR(U24*B24,"") | X24: =IFERROR(V24*B24,"") | Y24: =IFERROR(U24/((VLOOKUP(P24,'TL Data'!$A$2:$E$1226,3,FALSE))*'Tube Laser'!O24),"") | AA24: {=IFERROR(INDEX($AA$30:$AA$56, MATCH(0,IF(ISBLANK($AA$30:$AA$56),1,COUNTIF($AA$13:AA23, $AA$30:$AA$56)), 0)),"")} | AB24: =SUMIF($AA$30:$AA$56,AA24,$AD$30:$AD$56) -> 0 | AC24: =SUMIF($P$9:$P$98,AA24,$Q$9:$Q$98) -> 0 | AD24: =SUMIF($AA$30:$AA$56,AA24,$AE$30:$AE$56) -> 0 | AE24: =IFERROR(AB24*AC24*VLOOKUP(AA24,'TL Data'!$A$2:$E$1226,3,FALSE),"")
J25: =IFERROR((((D25)/60)/60)*$AB$9,"") -> 0 | K25: ='Tube Bending'!E25 -> 0 | L25: =IFERROR(VLOOKUP('Tube Laser'!A25,Machining!A26:G116,7,FALSE),"") | M25: =IFERROR(IF(Finishing!G26>0,VLOOKUP('Tube Laser'!A25,Finishing!A26:G116,7,FALSE),0),"") -> 0 | N25: =SUM(J25,K25,L25,M25,'FB Data'!AR25) -> 0 | O25: =C25/12 -> 0 | Q25: =IFERROR((B25*O25)/(VLOOKUP(P25,$AA$14:$AD$24,2,FALSE)),"") | R25: =IFERROR(VLOOKUP(P25,$AA$14:$AD$24,4,FALSE)*(Q25/(VLOOKUP(P25,$AA$14:$AD$24,3,FALSE))),"") | S25: =IFERROR((R25*$AB$10)/B25,"") | U25: =IFERROR(N25+S25+'FB Data'!AE25+'FB Data'!AF25+'FB Data'!AG25+'FB Data'!AH25+($AB$7/$B$99)+($AB$8/$B$99)+($AB$3/$B$99)+($AB$2/$B$99)+($AB$4/$B$99)+($AB$5/$B$99),"") | V25: =IFERROR(ROUND(U25*'Quote Info'!$O$4+T25,2),"") | W25: =IFERROR(U25*B25,"") | X25: =IFERROR(V25*B25,"") | Y25: =IFERROR(U25/((VLOOKUP(P25,'TL Data'!$A$2:$E$1226,3,FALSE))*'Tube Laser'!O25),"") | AE25: =SUMIF(AE14:AE24,"<>#N/A") -> 0
J26: =IFERROR((((D26)/60)/60)*$AB$9,"") -> 0 | K26: ='Tube Bending'!E26 -> 0 | L26: =IFERROR(VLOOKUP('Tube Laser'!A26,Machining!A27:G117,7,FALSE),"") | M26: =IFERROR(IF(Finishing!G27>0,VLOOKUP('Tube Laser'!A26,Finishing!A27:G117,7,FALSE),0),"") -> 0 | N26: =SUM(J26,K26,L26,M26,'FB Data'!AR26) -> 0 | O26: =C26/12 -> 0 | Q26: =IFERROR((B26*O26)/(VLOOKUP(P26,$AA$14:$AD$24,2,FALSE)),"") | R26: =IFERROR(VLOOKUP(P26,$AA$14:$AD$24,4,FALSE)*(Q26/(VLOOKUP(P26,$AA$14:$AD$24,3,FALSE))),"") | S26: =IFERROR((R26*$AB$10)/B26,"") | U26: =IFERROR(N26+S26+'FB Data'!AE26+'FB Data'!AF26+'FB Data'!AG26+'FB Data'!AH26+($AB$7/$B$99)+($AB$8/$B$99)+($AB$3/$B$99)+($AB$2/$B$99)+($AB$4/$B$99)+($AB$5/$B$99),"") | V26: =IFERROR(ROUND(U26*'Quote Info'!$O$4+T26,2),"") | W26: =IFERROR(U26*B26,"") | X26: =IFERROR(V26*B26,"") | Y26: =IFERROR(U26/((VLOOKUP(P26,'TL Data'!$A$2:$E$1226,3,FALSE))*'Tube Laser'!O26),"")
J27: =IFERROR((((D27)/60)/60)*$AB$9,"") -> 0 | K27: ='Tube Bending'!E27 -> 0 | L27: =IFERROR(VLOOKUP('Tube Laser'!A27,Machining!A28:G118,7,FALSE),"") | M27: =IFERROR(IF(Finishing!G28>0,VLOOKUP('Tube Laser'!A27,Finishing!A28:G118,7,FALSE),0),"") -> 0 | N27: =SUM(J27,K27,L27,M27,'FB Data'!AR27) -> 0 | O27: =C27/12 -> 0 | Q27: =IFERROR((B27*O27)/(VLOOKUP(P27,$AA$14:$AD$24,2,FALSE)),"") | R27: =IFERROR(VLOOKUP(P27,$AA$14:$AD$24,4,FALSE)*(Q27/(VLOOKUP(P27,$AA$14:$AD$24,3,FALSE))),"") | S27: =IFERROR((R27*$AB$10)/B27,"") | U27: =IFERROR(N27+S27+'FB Data'!AE27+'FB Data'!AF27+'FB Data'!AG27+'FB Data'!AH27+($AB$7/$B$99)+($AB$8/$B$99)+($AB$3/$B$99)+($AB$2/$B$99)+($AB$4/$B$99)+($AB$5/$B$99),"") | V27: =IFERROR(ROUND(U27*'Quote Info'!$O$4+T27,2),"") | W27: =IFERROR(U27*B27,"") | X27: =IFERROR(V27*B27,"") | Y27: =IFERROR(U27/((VLOOKUP(P27,'TL Data'!$A$2:$E$1226,3,FALSE))*'Tube Laser'!O27),"")
J28: =IFERROR((((D28)/60)/60)*$AB$9,"") -> 0 | K28: ='Tube Bending'!E28 -> 0 | L28: =IFERROR(VLOOKUP('Tube Laser'!A28,Machining!A29:G119,7,FALSE),"") | M28: =IFERROR(IF(Finishing!G29>0,VLOOKUP('Tube Laser'!A28,Finishing!A29:G119,7,FALSE),0),"") -> 0 | N28: =SUM(J28,K28,L28,M28,'FB Data'!AR28) -> 0 | O28: =C28/12 -> 0 | Q28: =IFERROR((B28*O28)/(VLOOKUP(P28,$AA$14:$AD$24,2,FALSE)),"") | R28: =IFERROR(VLOOKUP(P28,$AA$14:$AD$24,4,FALSE)*(Q28/(VLOOKUP(P28,$AA$14:$AD$24,3,FALSE))),"") | S28: =IFERROR((R28*$AB$10)/B28,"") | U28: =IFERROR(N28+S28+'FB Data'!AE28+'FB Data'!AF28+'FB Data'!AG28+'FB Data'!AH28+($AB$7/$B$99)+($AB$8/$B$99)+($AB$3/$B$99)+($AB$2/$B$99)+($AB$4/$B$99)+($AB$5/$B$99),"") | V28: =IFERROR(ROUND(U28*'Quote Info'!$O$4+T28,2),"") | W28: =IFERROR(U28*B28,"") | X28: =IFERROR(V28*B28,"") | Y28: =IFERROR(U28/((VLOOKUP(P28,'TL Data'!$A$2:$E$1226,3,FALSE))*'Tube Laser'!O28),"") | AA28: Material Required
J29: =IFERROR((((D29)/60)/60)*$AB$9,"") -> 0 | K29: ='Tube Bending'!E29 -> 0 | L29: =IFERROR(VLOOKUP('Tube Laser'!A29,Machining!A30:G120,7,FALSE),"") | M29: =IFERROR(IF(Finishing!G30>0,VLOOKUP('Tube Laser'!A29,Finishing!A30:G120,7,FALSE),0),"") -> 0 | N29: =SUM(J29,K29,L29,M29,'FB Data'!AR29) -> 0 | O29: =C29/12 -> 0 | Q29: =IFERROR((B29*O29)/(VLOOKUP(P29,$AA$14:$AD$24,2,FALSE)),"") | R29: =IFERROR(VLOOKUP(P29,$AA$14:$AD$24,4,FALSE)*(Q29/(VLOOKUP(P29,$AA$14:$AD$24,3,FALSE))),"") | S29: =IFERROR((R29*$AB$10)/B29,"") | U29: =IFERROR(N29+S29+'FB Data'!AE29+'FB Data'!AF29+'FB Data'!AG29+'FB Data'!AH29+($AB$7/$B$99)+($AB$8/$B$99)+($AB$3/$B$99)+($AB$2/$B$99)+($AB$4/$B$99)+($AB$5/$B$99),"") | V29: =IFERROR(ROUND(U29*'Quote Info'!$O$4+T29,2),"") | W29: =IFERROR(U29*B29,"") | X29: =IFERROR(V29*B29,"") | Y29: =IFERROR(U29/((VLOOKUP(P29,'TL Data'!$A$2:$E$1226,3,FALSE))*'Tube Laser'!O29),"") | AA29: Material ID | AB29: Qty | AC29: Length (in) | AD29: Total Linear ft | AE29: Material Cost
J30: =IFERROR((((D30)/60)/60)*$AB$9,"") -> 0 | K30: ='Tube Bending'!E30 -> 0 | L30: =IFERROR(VLOOKUP('Tube Laser'!A30,Machining!A31:G121,7,FALSE),"") | M30: =IFERROR(IF(Finishing!G31>0,VLOOKUP('Tube Laser'!A30,Finishing!A31:G121,7,FALSE),0),"") -> 0 | N30: =SUM(J30,K30,L30,M30,'FB Data'!AR30) -> 0 | O30: =C30/12 -> 0 | Q30: =IFERROR((B30*O30)/(VLOOKUP(P30,$AA$14:$AD$24,2,FALSE)),"") | R30: =IFERROR(VLOOKUP(P30,$AA$14:$AD$24,4,FALSE)*(Q30/(VLOOKUP(P30,$AA$14:$AD$24,3,FALSE))),"") | S30: =IFERROR((R30*$AB$10)/B30,"") | U30: =IFERROR(N30+S30+'FB Data'!AE30+'FB Data'!AF30+'FB Data'!AG30+'FB Data'!AH30+($AB$7/$B$99)+($AB$8/$B$99)+($AB$3/$B$99)+($AB$2/$B$99)+($AB$4/$B$99)+($AB$5/$B$99),"") | V30: =IFERROR(ROUND(U30*'Quote Info'!$O$4+T30,2),"") | W30: =IFERROR(U30*B30,"") | X30: =IFERROR(V30*B30,"") | Y30: =IFERROR(U30/((VLOOKUP(P30,'TL Data'!$A$2:$E$1226,3,FALSE))*'Tube Laser'!O30),"") | AD30: =(AC30/12)*AB30 -> 0 | AE30: =IFERROR(IF($AB$6="JWMCD",VLOOKUP(AA30,'TL Data'!$A$2:$E$1226,3,FALSE)*VLOOKUP(AA30,'TL Data'!$A$2:$E$1226,5,FALSE)*AD30,IF($AB$6="Customer Supplied",0,"Need Input")),"")
J31: =IFERROR((((D31)/60)/60)*$AB$9,"") -> 0 | K31: ='Tube Bending'!E31 -> 0 | L31: =IFERROR(VLOOKUP('Tube Laser'!A31,Machining!A32:G122,7,FALSE),"") | M31: =IFERROR(IF(Finishing!G32>0,VLOOKUP('Tube Laser'!A31,Finishing!A32:G122,7,FALSE),0),"") -> 0 | N31: =SUM(J31,K31,L31,M31,'FB Data'!AR31) -> 0 | O31: =C31/12 -> 0 | Q31: =IFERROR((B31*O31)/(VLOOKUP(P31,$AA$14:$AD$24,2,FALSE)),"") | R31: =IFERROR(VLOOKUP(P31,$AA$14:$AD$24,4,FALSE)*(Q31/(VLOOKUP(P31,$AA$14:$AD$24,3,FALSE))),"") | S31: =IFERROR((R31*$AB$10)/B31,"") | U31: =IFERROR(N31+S31+'FB Data'!AE31+'FB Data'!AF31+'FB Data'!AG31+'FB Data'!AH31+($AB$7/$B$99)+($AB$8/$B$99)+($AB$3/$B$99)+($AB$2/$B$99)+($AB$4/$B$99)+($AB$5/$B$99),"") | V31: =IFERROR(ROUND(U31*'Quote Info'!$O$4+T31,2),"") | W31: =IFERROR(U31*B31,"") | X31: =IFERROR(V31*B31,"") | Y31: =IFERROR(U31/((VLOOKUP(P31,'TL Data'!$A$2:$E$1226,3,FALSE))*'Tube Laser'!O31),"") | AD31: =(AC31/12)*AB31 -> 0 | AE31: =IFERROR(IF($AB$6="JWMCD",VLOOKUP(AA31,'TL Data'!$A$2:$E$1226,3,FALSE)*VLOOKUP(AA31,'TL Data'!$A$2:$E$1226,5,FALSE)*AD31,IF($AB$6="Customer Supplied",0,"Need Input")),"")
J32: =IFERROR((((D32)/60)/60)*$AB$9,"") -> 0 | K32: ='Tube Bending'!E32 -> 0 | L32: =IFERROR(VLOOKUP('Tube Laser'!A32,Machining!A33:G123,7,FALSE),"") | M32: =IFERROR(IF(Finishing!G33>0,VLOOKUP('Tube Laser'!A32,Finishing!A33:G123,7,FALSE),0),"") -> 0 | N32: =SUM(J32,K32,L32,M32,'FB Data'!AR32) -> 0 | O32: =C32/12 -> 0 | Q32: =IFERROR((B32*O32)/(VLOOKUP(P32,$AA$14:$AD$24,2,FALSE)),"") | R32: =IFERROR(VLOOKUP(P32,$AA$14:$AD$24,4,FALSE)*(Q32/(VLOOKUP(P32,$AA$14:$AD$24,3,FALSE))),"") | S32: =IFERROR((R32*$AB$10)/B32,"") | U32: =IFERROR(N32+S32+'FB Data'!AE32+'FB Data'!AF32+'FB Data'!AG32+'FB Data'!AH32+($AB$7/$B$99)+($AB$8/$B$99)+($AB$3/$B$99)+($AB$2/$B$99)+($AB$4/$B$99)+($AB$5/$B$99),"") | V32: =IFERROR(ROUND(U32*'Quote Info'!$O$4+T32,2),"") | W32: =IFERROR(U32*B32,"") | X32: =IFERROR(V32*B32,"") | Y32: =IFERROR(U32/((VLOOKUP(P32,'TL Data'!$A$2:$E$1226,3,FALSE))*'Tube Laser'!O32),"") | AD32: =(AC32/12)*AB32 -> 0 | AE32: =IFERROR(IF($AB$6="JWMCD",VLOOKUP(AA32,'TL Data'!$A$2:$E$1226,3,FALSE)*VLOOKUP(AA32,'TL Data'!$A$2:$E$1226,5,FALSE)*AD32,IF($AB$6="Customer Supplied",0,"Need Input")),"")
J33: =IFERROR((((D33)/60)/60)*$AB$9,"") -> 0 | K33: ='Tube Bending'!E33 -> 0 | L33: =IFERROR(VLOOKUP('Tube Laser'!A33,Machining!A34:G124,7,FALSE),"") | M33: =IFERROR(IF(Finishing!G34>0,VLOOKUP('Tube Laser'!A33,Finishing!A34:G124,7,FALSE),0),"") -> 0 | N33: =SUM(J33,K33,L33,M33,'FB Data'!AR33) -> 0 | O33: =C33/12 -> 0 | Q33: =IFERROR((B33*O33)/(VLOOKUP(P33,$AA$14:$AD$24,2,FALSE)),"") | R33: =IFERROR(VLOOKUP(P33,$AA$14:$AD$24,4,FALSE)*(Q33/(VLOOKUP(P33,$AA$14:$AD$24,3,FALSE))),"") | S33: =IFERROR((R33*$AB$10)/B33,"") | U33: =IFERROR(N33+S33+'FB Data'!AE33+'FB Data'!AF33+'FB Data'!AG33+'FB Data'!AH33+($AB$7/$B$99)+($AB$8/$B$99)+($AB$3/$B$99)+($AB$2/$B$99)+($AB$4/$B$99)+($AB$5/$B$99),"") | V33: =IFERROR(ROUND(U33*'Quote Info'!$O$4+T33,2),"") | W33: =IFERROR(U33*B33,"") | X33: =IFERROR(V33*B33,"") | Y33: =IFERROR(U33/((VLOOKUP(P33,'TL Data'!$A$2:$E$1226,3,FALSE))*'Tube Laser'!O33),"") | AD33: =(AC33/12)*AB33 -> 0 | AE33: =IFERROR(IF($AB$6="JWMCD",VLOOKUP(AA33,'TL Data'!$A$2:$E$1226,3,FALSE)*VLOOKUP(AA33,'TL Data'!$A$2:$E$1226,5,FALSE)*AD33,IF($AB$6="Customer Supplied",0,"Need Input")),"")
J34: =IFERROR((((D34)/60)/60)*$AB$9,"") -> 0 | K34: ='Tube Bending'!E34 -> 0 | L34: =IFERROR(VLOOKUP('Tube Laser'!A34,Machining!A35:G125,7,FALSE),"") | M34: =IFERROR(IF(Finishing!G35>0,VLOOKUP('Tube Laser'!A34,Finishing!A35:G125,7,FALSE),0),"") -> 0 | N34: =SUM(J34,K34,L34,M34,'FB Data'!AR34) -> 0 | O34: =C34/12 -> 0 | Q34: =IFERROR((B34*O34)/(VLOOKUP(P34,$AA$14:$AD$24,2,FALSE)),"") | R34: =IFERROR(VLOOKUP(P34,$AA$14:$AD$24,4,FALSE)*(Q34/(VLOOKUP(P34,$AA$14:$AD$24,3,FALSE))),"") | S34: =IFERROR((R34*$AB$10)/B34,"") | U34: =IFERROR(N34+S34+'FB Data'!AE34+'FB Data'!AF34+'FB Data'!AG34+'FB Data'!AH34+($AB$7/$B$99)+($AB$8/$B$99)+($AB$3/$B$99)+($AB$2/$B$99)+($AB$4/$B$99)+($AB$5/$B$99),"") | V34: =IFERROR(ROUND(U34*'Quote Info'!$O$4+T34,2),"") | W34: =IFERROR(U34*B34,"") | X34: =IFERROR(V34*B34,"") | Y34: =IFERROR(U34/((VLOOKUP(P34,'TL Data'!$A$2:$E$1226,3,FALSE))*'Tube Laser'!O34),"") | AD34: =(AC34/12)*AB34 -> 0 | AE34: =IFERROR(IF($AB$6="JWMCD",VLOOKUP(AA34,'TL Data'!$A$2:$E$1226,3,FALSE)*VLOOKUP(AA34,'TL Data'!$A$2:$E$1226,5,FALSE)*AD34,IF($AB$6="Customer Supplied",0,"Need Input")),"")
J35: =IFERROR((((D35)/60)/60)*$AB$9,"") -> 0 | K35: ='Tube Bending'!E35 -> 0 | L35: =IFERROR(VLOOKUP('Tube Laser'!A35,Machining!A36:G126,7,FALSE),"") | M35: =IFERROR(IF(Finishing!G36>0,VLOOKUP('Tube Laser'!A35,Finishing!A36:G126,7,FALSE),0),"") -> 0 | N35: =SUM(J35,K35,L35,M35,'FB Data'!AR35) -> 0 | O35: =C35/12 -> 0 | Q35: =IFERROR((B35*O35)/(VLOOKUP(P35,$AA$14:$AD$24,2,FALSE)),"") | R35: =IFERROR(VLOOKUP(P35,$AA$14:$AD$24,4,FALSE)*(Q35/(VLOOKUP(P35,$AA$14:$AD$24,3,FALSE))),"") | S35: =IFERROR((R35*$AB$10)/B35,"") | U35: =IFERROR(N35+S35+'FB Data'!AE35+'FB Data'!AF35+'FB Data'!AG35+'FB Data'!AH35+($AB$7/$B$99)+($AB$8/$B$99)+($AB$3/$B$99)+($AB$2/$B$99)+($AB$4/$B$99)+($AB$5/$B$99),"") | V35: =IFERROR(ROUND(U35*'Quote Info'!$O$4+T35,2),"") | W35: =IFERROR(U35*B35,"") | X35: =IFERROR(V35*B35,"") | Y35: =IFERROR(U35/((VLOOKUP(P35,'TL Data'!$A$2:$E$1226,3,FALSE))*'Tube Laser'!O35),"") | AD35: =(AC35/12)*AB35 -> 0 | AE35: =IFERROR(IF($AB$6="JWMCD",VLOOKUP(AA35,'TL Data'!$A$2:$E$1226,3,FALSE)*VLOOKUP(AA35,'TL Data'!$A$2:$E$1226,5,FALSE)*AD35,IF($AB$6="Customer Supplied",0,"Need Input")),"")
J36: =IFERROR((((D36)/60)/60)*$AB$9,"") -> 0 | K36: ='Tube Bending'!E36 -> 0 | L36: =IFERROR(VLOOKUP('Tube Laser'!A36,Machining!A37:G127,7,FALSE),"") | M36: =IFERROR(IF(Finishing!G37>0,VLOOKUP('Tube Laser'!A36,Finishing!A37:G127,7,FALSE),0),"") -> 0 | N36: =SUM(J36,K36,L36,M36,'FB Data'!AR36) -> 0 | O36: =C36/12 -> 0 | Q36: =IFERROR((B36*O36)/(VLOOKUP(P36,$AA$14:$AD$24,2,FALSE)),"") | R36: =IFERROR(VLOOKUP(P36,$AA$14:$AD$24,4,FALSE)*(Q36/(VLOOKUP(P36,$AA$14:$AD$24,3,FALSE))),"") | S36: =IFERROR((R36*$AB$10)/B36,"") | U36: =IFERROR(N36+S36+'FB Data'!AE36+'FB Data'!AF36+'FB Data'!AG36+'FB Data'!AH36+($AB$7/$B$99)+($AB$8/$B$99)+($AB$3/$B$99)+($AB$2/$B$99)+($AB$4/$B$99)+($AB$5/$B$99),"") | V36: =IFERROR(ROUND(U36*'Quote Info'!$O$4+T36,2),"") | W36: =IFERROR(U36*B36,"") | X36: =IFERROR(V36*B36,"") | Y36: =IFERROR(U36/((VLOOKUP(P36,'TL Data'!$A$2:$E$1226,3,FALSE))*'Tube Laser'!O36),"") | AD36: =(AC36/12)*AB36 -> 0 | AE36: =IFERROR(IF($AB$6="JWMCD",VLOOKUP(AA36,'TL Data'!$A$2:$E$1226,3,FALSE)*VLOOKUP(AA36,'TL Data'!$A$2:$E$1226,5,FALSE)*AD36,IF($AB$6="Customer Supplied",0,"Need Input")),"")
J37: =IFERROR((((D37)/60)/60)*$AB$9,"") -> 0 | K37: ='Tube Bending'!E37 -> 0 | L37: =IFERROR(VLOOKUP('Tube Laser'!A37,Machining!A38:G128,7,FALSE),"") | M37: =IFERROR(IF(Finishing!G38>0,VLOOKUP('Tube Laser'!A37,Finishing!A38:G128,7,FALSE),0),"") -> 0 | N37: =SUM(J37,K37,L37,M37,'FB Data'!AR37) -> 0 | O37: =C37/12 -> 0 | Q37: =IFERROR((B37*O37)/(VLOOKUP(P37,$AA$14:$AD$24,2,FALSE)),"") | R37: =IFERROR(VLOOKUP(P37,$AA$14:$AD$24,4,FALSE)*(Q37/(VLOOKUP(P37,$AA$14:$AD$24,3,FALSE))),"") | S37: =IFERROR((R37*$AB$10)/B37,"") | U37: =IFERROR(N37+S37+'FB Data'!AE37+'FB Data'!AF37+'FB Data'!AG37+'FB Data'!AH37+($AB$7/$B$99)+($AB$8/$B$99)+($AB$3/$B$99)+($AB$2/$B$99)+($AB$4/$B$99)+($AB$5/$B$99),"") | V37: =IFERROR(ROUND(U37*'Quote Info'!$O$4+T37,2),"") | W37: =IFERROR(U37*B37,"") | X37: =IFERROR(V37*B37,"") | Y37: =IFERROR(U37/((VLOOKUP(P37,'TL Data'!$A$2:$E$1226,3,FALSE))*'Tube Laser'!O37),"") | AD37: =(AC37/12)*AB37 -> 0 | AE37: =IFERROR(IF($AB$6="JWMCD",VLOOKUP(AA37,'TL Data'!$A$2:$E$1226,3,FALSE)*VLOOKUP(AA37,'TL Data'!$A$2:$E$1226,5,FALSE)*AD37,IF($AB$6="Customer Supplied",0,"Need Input")),"")
J38: =IFERROR((((D38)/60)/60)*$AB$9,"") -> 0 | K38: ='Tube Bending'!E38 -> 0 | L38: =IFERROR(VLOOKUP('Tube Laser'!A38,Machining!A39:G129,7,FALSE),"") | M38: =IFERROR(IF(Finishing!G39>0,VLOOKUP('Tube Laser'!A38,Finishing!A39:G129,7,FALSE),0),"") -> 0 | N38: =SUM(J38,K38,L38,M38,'FB Data'!AR38) -> 0 | O38: =C38/12 -> 0 | Q38: =IFERROR((B38*O38)/(VLOOKUP(P38,$AA$14:$AD$24,2,FALSE)),"") | R38: =IFERROR(VLOOKUP(P38,$AA$14:$AD$24,4,FALSE)*(Q38/(VLOOKUP(P38,$AA$14:$AD$24,3,FALSE))),"") | S38: =IFERROR((R38*$AB$10)/B38,"") | U38: =IFERROR(N38+S38+'FB Data'!AE38+'FB Data'!AF38+'FB Data'!AG38+'FB Data'!AH38+($AB$7/$B$99)+($AB$8/$B$99)+($AB$3/$B$99)+($AB$2/$B$99)+($AB$4/$B$99)+($AB$5/$B$99),"") | V38: =IFERROR(ROUND(U38*'Quote Info'!$O$4+T38,2),"") | W38: =IFERROR(U38*B38,"") | X38: =IFERROR(V38*B38,"") | Y38: =IFERROR(U38/((VLOOKUP(P38,'TL Data'!$A$2:$E$1226,3,FALSE))*'Tube Laser'!O38),"") | AD38: =(AC38/12)*AB38 -> 0 | AE38: =IFERROR(IF($AB$6="JWMCD",VLOOKUP(AA38,'TL Data'!$A$2:$E$1226,3,FALSE)*VLOOKUP(AA38,'TL Data'!$A$2:$E$1226,5,FALSE)*AD38,IF($AB$6="Customer Supplied",0,"Need Input")),"")
J39: =IFERROR((((D39)/60)/60)*$AB$9,"") -> 0 | K39: ='Tube Bending'!E39 -> 0 | L39: =IFERROR(VLOOKUP('Tube Laser'!A39,Machining!A40:G130,7,FALSE),"") | M39: =IFERROR(IF(Finishing!G40>0,VLOOKUP('Tube Laser'!A39,Finishing!A40:G130,7,FALSE),0),"") -> 0 | N39: =SUM(J39,K39,L39,M39,'FB Data'!AR39) -> 0 | O39: =C39/12 -> 0 | Q39: =IFERROR((B39*O39)/(VLOOKUP(P39,$AA$14:$AD$24,2,FALSE)),"") | R39: =IFERROR(VLOOKUP(P39,$AA$14:$AD$24,4,FALSE)*(Q39/(VLOOKUP(P39,$AA$14:$AD$24,3,FALSE))),"") | S39: =IFERROR((R39*$AB$10)/B39,"") | U39: =IFERROR(N39+S39+'FB Data'!AE39+'FB Data'!AF39+'FB Data'!AG39+'FB Data'!AH39+($AB$7/$B$99)+($AB$8/$B$99)+($AB$3/$B$99)+($AB$2/$B$99)+($AB$4/$B$99)+($AB$5/$B$99),"") | V39: =IFERROR(ROUND(U39*'Quote Info'!$O$4+T39,2),"") | W39: =IFERROR(U39*B39,"") | X39: =IFERROR(V39*B39,"") | Y39: =IFERROR(U39/((VLOOKUP(P39,'TL Data'!$A$2:$E$1226,3,FALSE))*'Tube Laser'!O39),"") | AD39: =(AC39/12)*AB39 -> 0 | AE39: =IFERROR(IF($AB$6="JWMCD",VLOOKUP(AA39,'TL Data'!$A$2:$E$1226,3,FALSE)*VLOOKUP(AA39,'TL Data'!$A$2:$E$1226,5,FALSE)*AD39,IF($AB$6="Customer Supplied",0,"Need Input")),"")
J40: =IFERROR((((D40)/60)/60)*$AB$9,"") -> 0 | K40: ='Tube Bending'!E40 -> 0 | L40: =IFERROR(VLOOKUP('Tube Laser'!A40,Machining!A41:G131,7,FALSE),"") | M40: =IFERROR(IF(Finishing!G41>0,VLOOKUP('Tube Laser'!A40,Finishing!A41:G131,7,FALSE),0),"") -> 0 | N40: =SUM(J40,K40,L40,M40,'FB Data'!AR40) -> 0 | O40: =C40/12 -> 0 | Q40: =IFERROR((B40*O40)/(VLOOKUP(P40,$AA$14:$AD$24,2,FALSE)),"") | R40: =IFERROR(VLOOKUP(P40,$AA$14:$AD$24,4,FALSE)*(Q40/(VLOOKUP(P40,$AA$14:$AD$24,3,FALSE))),"") | S40: =IFERROR((R40*$AB$10)/B40,"") | U40: =IFERROR(N40+S40+'FB Data'!AE40+'FB Data'!AF40+'FB Data'!AG40+'FB Data'!AH40+($AB$7/$B$99)+($AB$8/$B$99)+($AB$3/$B$99)+($AB$2/$B$99)+($AB$4/$B$99)+($AB$5/$B$99),"") | V40: =IFERROR(ROUND(U40*'Quote Info'!$O$4+T40,2),"") | W40: =IFERROR(U40*B40,"") | X40: =IFERROR(V40*B40,"") | Y40: =IFERROR(U40/((VLOOKUP(P40,'TL Data'!$A$2:$E$1226,3,FALSE))*'Tube Laser'!O40),"") | AD40: =(AC40/12)*AB40 -> 0 | AE40: =IFERROR(IF($AB$6="JWMCD",VLOOKUP(AA40,'TL Data'!$A$2:$E$1226,3,FALSE)*VLOOKUP(AA40,'TL Data'!$A$2:$E$1226,5,FALSE)*AD40,IF($AB$6="Customer Supplied",0,"Need Input")),"")
J41: =IFERROR((((D41)/60)/60)*$AB$9,"") -> 0 | K41: ='Tube Bending'!E41 -> 0 | L41: =IFERROR(VLOOKUP('Tube Laser'!A41,Machining!A42:G132,7,FALSE),"") | M41: =IFERROR(IF(Finishing!G42>0,VLOOKUP('Tube Laser'!A41,Finishing!A42:G132,7,FALSE),0),"") -> 0 | N41: =SUM(J41,K41,L41,M41,'FB Data'!AR41) -> 0 | O41: =C41/12 -> 0 | Q41: =IFERROR((B41*O41)/(VLOOKUP(P41,$AA$14:$AD$24,2,FALSE)),"") | R41: =IFERROR(VLOOKUP(P41,$AA$14:$AD$24,4,FALSE)*(Q41/(VLOOKUP(P41,$AA$14:$AD$24,3,FALSE))),"") | S41: =IFERROR((R41*$AB$10)/B41,"") | U41: =IFERROR(N41+S41+'FB Data'!AE41+'FB Data'!AF41+'FB Data'!AG41+'FB Data'!AH41+($AB$7/$B$99)+($AB$8/$B$99)+($AB$3/$B$99)+($AB$2/$B$99)+($AB$4/$B$99)+($AB$5/$B$99),"") | V41: =IFERROR(ROUND(U41*'Quote Info'!$O$4+T41,2),"") | W41: =IFERROR(U41*B41,"") | X41: =IFERROR(V41*B41,"") | Y41: =IFERROR(U41/((VLOOKUP(P41,'TL Data'!$A$2:$E$1226,3,FALSE))*'Tube Laser'!O41),"") | AD41: =(AC41/12)*AB41 -> 0 | AE41: =IFERROR(IF($AB$6="JWMCD",VLOOKUP(AA41,'TL Data'!$A$2:$E$1226,3,FALSE)*VLOOKUP(AA41,'TL Data'!$A$2:$E$1226,5,FALSE)*AD41,IF($AB$6="Customer Supplied",0,"Need Input")),"")
... J56: =IFERROR((((D56)/60)/60)*$AB$9,"") -> 0 | K56: ='Tube Bending'!E56 -> 0 | L56: =IFERROR(VLOOKUP('Tube Laser'!A56,Machining!A57:G147,7,FALSE),"") | M56: =IFERROR(IF(Finishing!G57>0,VLOOKUP('Tube Laser'!A56,Finishing!A57:G147,7,FALSE),0),"") -> 0 | N56: =SUM(J56,K56,L56,M56,'FB Data'!AR56) -> 0 | O56: =C56/12 -> 0 | Q56: =IFERROR((B56*O56)/(VLOOKUP(P56,$AA$14:$AD$24,2,FALSE)),"") | R56: =IFERROR(VLOOKUP(P56,$AA$14:$AD$24,4,FALSE)*(Q56/(VLOOKUP(P56,$AA$14:$AD$24,3,FALSE))),"") | S56: =IFERROR((R56*$AB$10)/B56,"") | U56: =IFERROR(N56+S56+'FB Data'!AE56+'FB Data'!AF56+'FB Data'!AG56+'FB Data'!AH56+($AB$7/$B$99)+($AB$8/$B$99)+($AB$3/$B$99)+($AB$2/$B$99)+($AB$4/$B$99)+($AB$5/$B$99),"") | V56: =IFERROR(ROUND(U56*'Quote Info'!$O$4+T56,2),"") | W56: =IFERROR(U56*B56,"") | X56: =IFERROR(V56*B56,"") | Y56: =IFERROR(U56/((VLOOKUP(P56,'TL Data'!$A$2:$E$1226,3,FALSE))*'Tube Laser'!O56),"") | AD56: =(AC56/12)*AB56 -> 0 | AE56: =IFERROR(IF($AB$6="JWMCD",VLOOKUP(AA56,'TL Data'!$A$2:$E$1226,3,FALSE)*VLOOKUP(AA56,'TL Data'!$A$2:$E$1226,5,FALSE)*AD56,IF($AB$6="Customer Supplied",0,"Need Input")),"")
J57: =IFERROR((((D57)/60)/60)*$AB$9,"") -> 0 | K57: ='Tube Bending'!E57 -> 0 | L57: =IFERROR(VLOOKUP('Tube Laser'!A57,Machining!A58:G148,7,FALSE),"") | M57: =IFERROR(IF(Finishing!G58>0,VLOOKUP('Tube Laser'!A57,Finishing!A58:G148,7,FALSE),0),"") -> 0 | N57: =SUM(J57,K57,L57,M57,'FB Data'!AR57) -> 0 | O57: =C57/12 -> 0 | Q57: =IFERROR((B57*O57)/(VLOOKUP(P57,$AA$14:$AD$24,2,FALSE)),"") | R57: =IFERROR(VLOOKUP(P57,$AA$14:$AD$24,4,FALSE)*(Q57/(VLOOKUP(P57,$AA$14:$AD$24,3,FALSE))),"") | S57: =IFERROR((R57*$AB$10)/B57,"") | U57: =IFERROR(N57+S57+'FB Data'!AE57+'FB Data'!AF57+'FB Data'!AG57+'FB Data'!AH57+($AB$7/$B$99)+($AB$8/$B$99)+($AB$3/$B$99)+($AB$2/$B$99)+($AB$4/$B$99)+($AB$5/$B$99),"") | V57: =IFERROR(ROUND(U57*'Quote Info'!$O$4+T57,2),"") | W57: =IFERROR(U57*B57,"") | X57: =IFERROR(V57*B57,"") | Y57: =IFERROR(U57/((VLOOKUP(P57,'TL Data'!$A$2:$E$1226,3,FALSE))*'Tube Laser'!O57),"")
J58: =IFERROR((((D58)/60)/60)*$AB$9,"") -> 0 | K58: ='Tube Bending'!E58 -> 0 | L58: =IFERROR(VLOOKUP('Tube Laser'!A58,Machining!A59:G149,7,FALSE),"") | M58: =IFERROR(IF(Finishing!G59>0,VLOOKUP('Tube Laser'!A58,Finishing!A59:G149,7,FALSE),0),"") -> 0 | N58: =SUM(J58,K58,L58,M58,'FB Data'!AR58) -> 0 | O58: =C58/12 -> 0 | Q58: =IFERROR((B58*O58)/(VLOOKUP(P58,$AA$14:$AD$24,2,FALSE)),"") | R58: =IFERROR(VLOOKUP(P58,$AA$14:$AD$24,4,FALSE)*(Q58/(VLOOKUP(P58,$AA$14:$AD$24,3,FALSE))),"") | S58: =IFERROR((R58*$AB$10)/B58,"") | U58: =IFERROR(N58+S58+'FB Data'!AE58+'FB Data'!AF58+'FB Data'!AG58+'FB Data'!AH58+($AB$7/$B$99)+($AB$8/$B$99)+($AB$3/$B$99)+($AB$2/$B$99)+($AB$4/$B$99)+($AB$5/$B$99),"") | V58: =IFERROR(ROUND(U58*'Quote Info'!$O$4+T58,2),"") | W58: =IFERROR(U58*B58,"") | X58: =IFERROR(V58*B58,"") | Y58: =IFERROR(U58/((VLOOKUP(P58,'TL Data'!$A$2:$E$1226,3,FALSE))*'Tube Laser'!O58),"")
J59: =IFERROR((((D59)/60)/60)*$AB$9,"") -> 0 | K59: ='Tube Bending'!E59 -> 0 | L59: =IFERROR(VLOOKUP('Tube Laser'!A59,Machining!A60:G150,7,FALSE),"") | M59: =IFERROR(IF(Finishing!G60>0,VLOOKUP('Tube Laser'!A59,Finishing!A60:G150,7,FALSE),0),"") -> 0 | N59: =SUM(J59,K59,L59,M59,'FB Data'!AR59) -> 0 | O59: =C59/12 -> 0 | Q59: =IFERROR((B59*O59)/(VLOOKUP(P59,$AA$14:$AD$24,2,FALSE)),"") | R59: =IFERROR(VLOOKUP(P59,$AA$14:$AD$24,4,FALSE)*(Q59/(VLOOKUP(P59,$AA$14:$AD$24,3,FALSE))),"") | S59: =IFERROR((R59*$AB$10)/B59,"") | U59: =IFERROR(N59+S59+'FB Data'!AE59+'FB Data'!AF59+'FB Data'!AG59+'FB Data'!AH59+($AB$7/$B$99)+($AB$8/$B$99)+($AB$3/$B$99)+($AB$2/$B$99)+($AB$4/$B$99)+($AB$5/$B$99),"") | V59: =IFERROR(ROUND(U59*'Quote Info'!$O$4+T59,2),"") | W59: =IFERROR(U59*B59,"") | X59: =IFERROR(V59*B59,"") | Y59: =IFERROR(U59/((VLOOKUP(P59,'TL Data'!$A$2:$E$1226,3,FALSE))*'Tube Laser'!O59),"")
J60: =IFERROR((((D60)/60)/60)*$AB$9,"") -> 0 | K60: ='Tube Bending'!E60 -> 0 | L60: =IFERROR(VLOOKUP('Tube Laser'!A60,Machining!A61:G151,7,FALSE),"") | M60: =IFERROR(IF(Finishing!G61>0,VLOOKUP('Tube Laser'!A60,Finishing!A61:G151,7,FALSE),0),"") -> 0 | N60: =SUM(J60,K60,L60,M60,'FB Data'!AR60) -> 0 | O60: =C60/12 -> 0 | Q60: =IFERROR((B60*O60)/(VLOOKUP(P60,$AA$14:$AD$24,2,FALSE)),"") | R60: =IFERROR(VLOOKUP(P60,$AA$14:$AD$24,4,FALSE)*(Q60/(VLOOKUP(P60,$AA$14:$AD$24,3,FALSE))),"") | S60: =IFERROR((R60*$AB$10)/B60,"") | U60: =IFERROR(N60+S60+'FB Data'!AE60+'FB Data'!AF60+'FB Data'!AG60+'FB Data'!AH60+($AB$7/$B$99)+($AB$8/$B$99)+($AB$3/$B$99)+($AB$2/$B$99)+($AB$4/$B$99)+($AB$5/$B$99),"") | V60: =IFERROR(ROUND(U60*'Quote Info'!$O$4+T60,2),"") | W60: =IFERROR(U60*B60,"") | X60: =IFERROR(V60*B60,"") | Y60: =IFERROR(U60/((VLOOKUP(P60,'TL Data'!$A$2:$E$1226,3,FALSE))*'Tube Laser'!O60),"")
J61: =IFERROR((((D61)/60)/60)*$AB$9,"") -> 0 | K61: ='Tube Bending'!E61 -> 0 | L61: =IFERROR(VLOOKUP('Tube Laser'!A61,Machining!A62:G152,7,FALSE),"") | M61: =IFERROR(IF(Finishing!G62>0,VLOOKUP('Tube Laser'!A61,Finishing!A62:G152,7,FALSE),0),"") -> 0 | N61: =SUM(J61,K61,L61,M61,'FB Data'!AR61) -> 0 | O61: =C61/12 -> 0 | Q61: =IFERROR((B61*O61)/(VLOOKUP(P61,$AA$14:$AD$24,2,FALSE)),"") | R61: =IFERROR(VLOOKUP(P61,$AA$14:$AD$24,4,FALSE)*(Q61/(VLOOKUP(P61,$AA$14:$AD$24,3,FALSE))),"") | S61: =IFERROR((R61*$AB$10)/B61,"") | U61: =IFERROR(N61+S61+'FB Data'!AE61+'FB Data'!AF61+'FB Data'!AG61+'FB Data'!AH61+($AB$7/$B$99)+($AB$8/$B$99)+($AB$3/$B$99)+($AB$2/$B$99)+($AB$4/$B$99)+($AB$5/$B$99),"") | V61: =IFERROR(ROUND(U61*'Quote Info'!$O$4+T61,2),"") | W61: =IFERROR(U61*B61,"") | X61: =IFERROR(V61*B61,"") | Y61: =IFERROR(U61/((VLOOKUP(P61,'TL Data'!$A$2:$E$1226,3,FALSE))*'Tube Laser'!O61),"")
J62: =IFERROR((((D62)/60)/60)*$AB$9,"") -> 0 | K62: ='Tube Bending'!E62 -> 0 | L62: =IFERROR(VLOOKUP('Tube Laser'!A62,Machining!A63:G153,7,FALSE),"") | M62: =IFERROR(IF(Finishing!G63>0,VLOOKUP('Tube Laser'!A62,Finishing!A63:G153,7,FALSE),0),"") -> 0 | N62: =SUM(J62,K62,L62,M62,'FB Data'!AR62) -> 0 | O62: =C62/12 -> 0 | Q62: =IFERROR((B62*O62)/(VLOOKUP(P62,$AA$14:$AD$24,2,FALSE)),"") | R62: =IFERROR(VLOOKUP(P62,$AA$14:$AD$24,4,FALSE)*(Q62/(VLOOKUP(P62,$AA$14:$AD$24,3,FALSE))),"") | S62: =IFERROR((R62*$AB$10)/B62,"") | U62: =IFERROR(N62+S62+'FB Data'!AE62+'FB Data'!AF62+'FB Data'!AG62+'FB Data'!AH62+($AB$7/$B$99)+($AB$8/$B$99)+($AB$3/$B$99)+($AB$2/$B$99)+($AB$4/$B$99)+($AB$5/$B$99),"") | V62: =IFERROR(ROUND(U62*'Quote Info'!$O$4+T62,2),"") | W62: =IFERROR(U62*B62,"") | X62: =IFERROR(V62*B62,"") | Y62: =IFERROR(U62/((VLOOKUP(P62,'TL Data'!$A$2:$E$1226,3,FALSE))*'Tube Laser'!O62),"")
J63: =IFERROR((((D63)/60)/60)*$AB$9,"") -> 0 | K63: ='Tube Bending'!E63 -> 0 | L63: =IFERROR(VLOOKUP('Tube Laser'!A63,Machining!A64:G154,7,FALSE),"") | M63: =IFERROR(IF(Finishing!G64>0,VLOOKUP('Tube Laser'!A63,Finishing!A64:G154,7,FALSE),0),"") -> 0 | N63: =SUM(J63,K63,L63,M63,'FB Data'!AR63) -> 0 | O63: =C63/12 -> 0 | Q63: =IFERROR((B63*O63)/(VLOOKUP(P63,$AA$14:$AD$24,2,FALSE)),"") | R63: =IFERROR(VLOOKUP(P63,$AA$14:$AD$24,4,FALSE)*(Q63/(VLOOKUP(P63,$AA$14:$AD$24,3,FALSE))),"") | S63: =IFERROR((R63*$AB$10)/B63,"") | U63: =IFERROR(N63+S63+'FB Data'!AE63+'FB Data'!AF63+'FB Data'!AG63+'FB Data'!AH63+($AB$7/$B$99)+($AB$8/$B$99)+($AB$3/$B$99)+($AB$2/$B$99)+($AB$4/$B$99)+($AB$5/$B$99),"") | V63: =IFERROR(ROUND(U63*'Quote Info'!$O$4+T63,2),"") | W63: =IFERROR(U63*B63,"") | X63: =IFERROR(V63*B63,"") | Y63: =IFERROR(U63/((VLOOKUP(P63,'TL Data'!$A$2:$E$1226,3,FALSE))*'Tube Laser'!O63),"")
J64: =IFERROR((((D64)/60)/60)*$AB$9,"") -> 0 | K64: ='Tube Bending'!E64 -> 0 | L64: =IFERROR(VLOOKUP('Tube Laser'!A64,Machining!A65:G155,7,FALSE),"") | M64: =IFERROR(IF(Finishing!G65>0,VLOOKUP('Tube Laser'!A64,Finishing!A65:G155,7,FALSE),0),"") -> 0 | N64: =SUM(J64,K64,L64,M64,'FB Data'!AR64) -> 0 | O64: =C64/12 -> 0 | Q64: =IFERROR((B64*O64)/(VLOOKUP(P64,$AA$14:$AD$24,2,FALSE)),"") | R64: =IFERROR(VLOOKUP(P64,$AA$14:$AD$24,4,FALSE)*(Q64/(VLOOKUP(P64,$AA$14:$AD$24,3,FALSE))),"") | S64: =IFERROR((R64*$AB$10)/B64,"") | U64: =IFERROR(N64+S64+'FB Data'!AE64+'FB Data'!AF64+'FB Data'!AG64+'FB Data'!AH64+($AB$7/$B$99)+($AB$8/$B$99)+($AB$3/$B$99)+($AB$2/$B$99)+($AB$4/$B$99)+($AB$5/$B$99),"") | V64: =IFERROR(ROUND(U64*'Quote Info'!$O$4+T64,2),"") | W64: =IFERROR(U64*B64,"") | X64: =IFERROR(V64*B64,"") | Y64: =IFERROR(U64/((VLOOKUP(P64,'TL Data'!$A$2:$E$1226,3,FALSE))*'Tube Laser'!O64),"")
J65: =IFERROR((((D65)/60)/60)*$AB$9,"") -> 0 | K65: ='Tube Bending'!E65 -> 0 | L65: =IFERROR(VLOOKUP('Tube Laser'!A65,Machining!A66:G156,7,FALSE),"") | M65: =IFERROR(IF(Finishing!G66>0,VLOOKUP('Tube Laser'!A65,Finishing!A66:G156,7,FALSE),0),"") -> 0 | N65: =SUM(J65,K65,L65,M65,'FB Data'!AR65) -> 0 | O65: =C65/12 -> 0 | Q65: =IFERROR((B65*O65)/(VLOOKUP(P65,$AA$14:$AD$24,2,FALSE)),"") | R65: =IFERROR(VLOOKUP(P65,$AA$14:$AD$24,4,FALSE)*(Q65/(VLOOKUP(P65,$AA$14:$AD$24,3,FALSE))),"") | S65: =IFERROR((R65*$AB$10)/B65,"") | U65: =IFERROR(N65+S65+'FB Data'!AE65+'FB Data'!AF65+'FB Data'!AG65+'FB Data'!AH65+($AB$7/$B$99)+($AB$8/$B$99)+($AB$3/$B$99)+($AB$2/$B$99)+($AB$4/$B$99)+($AB$5/$B$99),"") | V65: =IFERROR(ROUND(U65*'Quote Info'!$O$4+T65,2),"") | W65: =IFERROR(U65*B65,"") | X65: =IFERROR(V65*B65,"") | Y65: =IFERROR(U65/((VLOOKUP(P65,'TL Data'!$A$2:$E$1226,3,FALSE))*'Tube Laser'!O65),"")
J66: =IFERROR((((D66)/60)/60)*$AB$9,"") -> 0 | K66: ='Tube Bending'!E66 -> 0 | L66: =IFERROR(VLOOKUP('Tube Laser'!A66,Machining!A67:G157,7,FALSE),"") | M66: =IFERROR(IF(Finishing!G67>0,VLOOKUP('Tube Laser'!A66,Finishing!A67:G157,7,FALSE),0),"") -> 0 | N66: =SUM(J66,K66,L66,M66,'FB Data'!AR66) -> 0 | O66: =C66/12 -> 0 | Q66: =IFERROR((B66*O66)/(VLOOKUP(P66,$AA$14:$AD$24,2,FALSE)),"") | R66: =IFERROR(VLOOKUP(P66,$AA$14:$AD$24,4,FALSE)*(Q66/(VLOOKUP(P66,$AA$14:$AD$24,3,FALSE))),"") | S66: =IFERROR((R66*$AB$10)/B66,"") | U66: =IFERROR(N66+S66+'FB Data'!AE66+'FB Data'!AF66+'FB Data'!AG66+'FB Data'!AH66+($AB$7/$B$99)+($AB$8/$B$99)+($AB$3/$B$99)+($AB$2/$B$99)+($AB$4/$B$99)+($AB$5/$B$99),"") | V66: =IFERROR(ROUND(U66*'Quote Info'!$O$4+T66,2),"") | W66: =IFERROR(U66*B66,"") | X66: =IFERROR(V66*B66,"") | Y66: =IFERROR(U66/((VLOOKUP(P66,'TL Data'!$A$2:$E$1226,3,FALSE))*'Tube Laser'!O66),"")
J67: =IFERROR((((D67)/60)/60)*$AB$9,"") -> 0 | K67: ='Tube Bending'!E67 -> 0 | L67: =IFERROR(VLOOKUP('Tube Laser'!A67,Machining!A68:G158,7,FALSE),"") | M67: =IFERROR(IF(Finishing!G68>0,VLOOKUP('Tube Laser'!A67,Finishing!A68:G158,7,FALSE),0),"") -> 0 | N67: =SUM(J67,K67,L67,M67,'FB Data'!AR67) -> 0 | O67: =C67/12 -> 0 | Q67: =IFERROR((B67*O67)/(VLOOKUP(P67,$AA$14:$AD$24,2,FALSE)),"") | R67: =IFERROR(VLOOKUP(P67,$AA$14:$AD$24,4,FALSE)*(Q67/(VLOOKUP(P67,$AA$14:$AD$24,3,FALSE))),"") | S67: =IFERROR((R67*$AB$10)/B67,"") | U67: =IFERROR(N67+S67+'FB Data'!AE67+'FB Data'!AF67+'FB Data'!AG67+'FB Data'!AH67+($AB$7/$B$99)+($AB$8/$B$99)+($AB$3/$B$99)+($AB$2/$B$99)+($AB$4/$B$99)+($AB$5/$B$99),"") | V67: =IFERROR(ROUND(U67*'Quote Info'!$O$4+T67,2),"") | W67: =IFERROR(U67*B67,"") | X67: =IFERROR(V67*B67,"") | Y67: =IFERROR(U67/((VLOOKUP(P67,'TL Data'!$A$2:$E$1226,3,FALSE))*'Tube Laser'!O67),"")
J68: =IFERROR((((D68)/60)/60)*$AB$9,"") -> 0 | K68: ='Tube Bending'!E68 -> 0 | L68: =IFERROR(VLOOKUP('Tube Laser'!A68,Machining!A69:G159,7,FALSE),"") | M68: =IFERROR(IF(Finishing!G69>0,VLOOKUP('Tube Laser'!A68,Finishing!A69:G159,7,FALSE),0),"") -> 0 | N68: =SUM(J68,K68,L68,M68,'FB Data'!AR68) -> 0 | O68: =C68/12 -> 0 | Q68: =IFERROR((B68*O68)/(VLOOKUP(P68,$AA$14:$AD$24,2,FALSE)),"") | R68: =IFERROR(VLOOKUP(P68,$AA$14:$AD$24,4,FALSE)*(Q68/(VLOOKUP(P68,$AA$14:$AD$24,3,FALSE))),"") | S68: =IFERROR((R68*$AB$10)/B68,"") | U68: =IFERROR(N68+S68+'FB Data'!AE68+'FB Data'!AF68+'FB Data'!AG68+'FB Data'!AH68+($AB$7/$B$99)+($AB$8/$B$99)+($AB$3/$B$99)+($AB$2/$B$99)+($AB$4/$B$99)+($AB$5/$B$99),"") | V68: =IFERROR(ROUND(U68*'Quote Info'!$O$4+T68,2),"") | W68: =IFERROR(U68*B68,"") | X68: =IFERROR(V68*B68,"") | Y68: =IFERROR(U68/((VLOOKUP(P68,'TL Data'!$A$2:$E$1226,3,FALSE))*'Tube Laser'!O68),"")
... J98: =IFERROR((((D98)/60)/60)*$AB$9,"") -> 0 | K98: ='Tube Bending'!E98 -> 0 | L98: =IFERROR(VLOOKUP('Tube Laser'!A98,Machining!A99:G189,7,FALSE),"") | M98: =IFERROR(IF(Finishing!G99>0,VLOOKUP('Tube Laser'!A98,Finishing!A99:G189,7,FALSE),0),"") -> 0 | N98: =SUM(J98,K98,L98,M98,'FB Data'!AR98) -> 0 | O98: =C98/12 -> 0 | Q98: =IFERROR((B98*O98)/(VLOOKUP(P98,$AA$14:$AD$24,2,FALSE)),"") | R98: =IFERROR(VLOOKUP(P98,$AA$14:$AD$24,4,FALSE)*(Q98/(VLOOKUP(P98,$AA$14:$AD$24,3,FALSE))),"") | S98: =IFERROR((R98*$AB$10)/B98,"") | U98: =IFERROR(N98+S98+'FB Data'!AE98+'FB Data'!AF98+'FB Data'!AG98+'FB Data'!AH98+($AB$7/$B$99)+($AB$8/$B$99)+($AB$3/$B$99)+($AB$2/$B$99)+($AB$4/$B$99)+($AB$5/$B$99),"") | V98: =IFERROR(ROUND(U98*'Quote Info'!$O$4+T98,2),"") | W98: =IFERROR(U98*B98,"") | X98: =IFERROR(V98*B98,"") | Y98: =IFERROR(U98/((VLOOKUP(P98,'TL Data'!$A$2:$E$1226,3,FALSE))*'Tube Laser'!O98),"")
A99: Total Qty- | B99: =SUM(B9:B98) -> 0 | W99: =SUMIF(W9:W98,"<>#N/A") -> 0 | X99: =SUMIF(X9:X98,"<>#N/A") -> 0 | Y99: =IFERROR(W99/AE25,"")

Sheet Notes
A2: Notes
A4: dwg# | B4: Note
A5: ='FB Data'!O9
A6: ='FB Data'!O10
A7: ='FB Data'!O11
A8: ='FB Data'!O12
A9: ='FB Data'!O13
A10: ='FB Data'!O14
A11: ='FB Data'!O15
A12: ='FB Data'!O16
A13: ='FB Data'!O17
A14: ='FB Data'!O18
A15: ='FB Data'!O19
A16: ='FB Data'!O20
... A56: ='FB Data'!O60

Sheet Forming
B4: Forming Cost | C4: 61.62
C5: =C4*'Quote Info'!O4 -> 83.8032
A9: dwg# | B9: Qty | C9: Longest Dim | D9: Men | E9: Setup (min) | F9: PPH | G9: Price (Each) | H9: Lot | I9: Run Time Lot (min) | J9: Helper Labor Lot (min)
A10: ='FB Laser'!A10 -> 0 | B10: ='FB Laser'!B10 -> 0 | C10: =IF('FB Laser'!C10>'FB Laser'!D10,'FB Laser'!C10,'FB Laser'!D10) -> 0 | D10: =IF(C10<48.01,1,1.5) -> 1 | G10: =IFERROR((((E10/60)*$C$4)/B10)+((60/F10/60*$C$4)*D10),0) -> 0 | H10: =IFERROR(G10*B10,0) -> 0 | I10: =IFERROR((B10/F10)*60+(E10/60)*60,0) -> 0 | J10: =IF(D10=1.5,I10,0) -> 0
A11: ='FB Laser'!A11 -> 0 | B11: ='FB Laser'!B11 -> 0 | C11: =IF('FB Laser'!C11>'FB Laser'!D11,'FB Laser'!C11,'FB Laser'!D11) -> 0 | D11: =IF(C11<48.01,1,1.5) -> 1 | G11: =IFERROR((((E11/60)*$C$4)/B11)+((60/F11/60*$C$4)*D11),0) -> 0 | H11: =IFERROR(G11*B11,0) -> 0 | I11: =IFERROR((B11/F11)*60+(E11/60)*60,0) -> 0 | J11: =IF(D11=1.5,I11,0) -> 0
A12: ='FB Laser'!A12 -> 0 | B12: ='FB Laser'!B12 -> 0 | C12: =IF('FB Laser'!C12>'FB Laser'!D12,'FB Laser'!C12,'FB Laser'!D12) -> 0 | D12: =IF(C12<48.01,1,1.5) -> 1 | G12: =IFERROR((((E12/60)*$C$4)/B12)+((60/F12/60*$C$4)*D12),0) -> 0 | H12: =IFERROR(G12*B12,0) -> 0 | I12: =IFERROR((B12/F12)*60+(E12/60)*60,0) -> 0 | J12: =IF(D12=1.5,I12,0) -> 0
A13: ='FB Laser'!A13 -> 0 | B13: ='FB Laser'!B13 -> 0 | C13: =IF('FB Laser'!C13>'FB Laser'!D13,'FB Laser'!C13,'FB Laser'!D13) -> 0 | D13: =IF(C13<48.01,1,1.5) -> 1 | G13: =IFERROR((((E13/60)*$C$4)/B13)+((60/F13/60*$C$4)*D13),0) -> 0 | H13: =IFERROR(G13*B13,0) -> 0 | I13: =IFERROR((B13/F13)*60+(E13/60)*60,0) -> 0 | J13: =IF(D13=1.5,I13,0) -> 0
A14: ='FB Laser'!A14 -> 0 | B14: ='FB Laser'!B14 -> 0 | C14: =IF('FB Laser'!C14>'FB Laser'!D14,'FB Laser'!C14,'FB Laser'!D14) -> 0 | D14: =IF(C14<48.01,1,1.5) -> 1 | G14: =IFERROR((((E14/60)*$C$4)/B14)+((60/F14/60*$C$4)*D14),0) -> 0 | H14: =IFERROR(G14*B14,0) -> 0 | I14: =IFERROR((B14/F14)*60+(E14/60)*60,0) -> 0 | J14: =IF(D14=1.5,I14,0) -> 0
A15: ='FB Laser'!A15 -> 0 | B15: ='FB Laser'!B15 -> 0 | C15: =IF('FB Laser'!C15>'FB Laser'!D15,'FB Laser'!C15,'FB Laser'!D15) -> 0 | D15: =IF(C15<48.01,1,1.5) -> 1 | G15: =IFERROR((((E15/60)*$C$4)/B15)+((60/F15/60*$C$4)*D15),0) -> 0 | H15: =IFERROR(G15*B15,0) -> 0 | I15: =IFERROR((B15/F15)*60+(E15/60)*60,0) -> 0 | J15: =IF(D15=1.5,I15,0) -> 0
A16: ='FB Laser'!A16 -> 0 | B16: ='FB Laser'!B16 -> 0 | C16: =IF('FB Laser'!C16>'FB Laser'!D16,'FB Laser'!C16,'FB Laser'!D16) -> 0 | D16: =IF(C16<48.01,1,1.5) -> 1 | G16: =IFERROR((((E16/60)*$C$4)/B16)+((60/F16/60*$C$4)*D16),0) -> 0 | H16: =IFERROR(G16*B16,0) -> 0 | I16: =IFERROR((B16/F16)*60+(E16/60)*60,0) -> 0 | J16: =IF(D16=1.5,I16,0) -> 0
A17: ='FB Laser'!A17 -> 0 | B17: ='FB Laser'!B17 -> 0 | C17: =IF('FB Laser'!C17>'FB Laser'!D17,'FB Laser'!C17,'FB Laser'!D17) -> 0 | D17: =IF(C17<48.01,1,1.5) -> 1 | G17: =IFERROR((((E17/60)*$C$4)/B17)+((60/F17/60*$C$4)*D17),0) -> 0 | H17: =IFERROR(G17*B17,0) -> 0 | I17: =IFERROR((B17/F17)*60+(E17/60)*60,0) -> 0 | J17: =IF(D17=1.5,I17,0) -> 0
A18: ='FB Laser'!A18 -> 0 | B18: ='FB Laser'!B18 -> 0 | C18: =IF('FB Laser'!C18>'FB Laser'!D18,'FB Laser'!C18,'FB Laser'!D18) -> 0 | D18: =IF(C18<48.01,1,1.5) -> 1 | G18: =IFERROR((((E18/60)*$C$4)/B18)+((60/F18/60*$C$4)*D18),0) -> 0 | H18: =IFERROR(G18*B18,0) -> 0 | I18: =IFERROR((B18/F18)*60+(E18/60)*60,0) -> 0 | J18: =IF(D18=1.5,I18,0) -> 0
A19: ='FB Laser'!A19 -> 0 | B19: ='FB Laser'!B19 -> 0 | C19: =IF('FB Laser'!C19>'FB Laser'!D19,'FB Laser'!C19,'FB Laser'!D19) -> 0 | D19: =IF(C19<48.01,1,1.5) -> 1 | G19: =IFERROR((((E19/60)*$C$4)/B19)+((60/F19/60*$C$4)*D19),0) -> 0 | H19: =IFERROR(G19*B19,0) -> 0 | I19: =IFERROR((B19/F19)*60+(E19/60)*60,0) -> 0 | J19: =IF(D19=1.5,I19,0) -> 0
A20: ='FB Laser'!A20 -> 0 | B20: ='FB Laser'!B20 -> 0 | C20: =IF('FB Laser'!C20>'FB Laser'!D20,'FB Laser'!C20,'FB Laser'!D20) -> 0 | D20: =IF(C20<48.01,1,1.5) -> 1 | G20: =IFERROR((((E20/60)*$C$4)/B20)+((60/F20/60*$C$4)*D20),0) -> 0 | H20: =IFERROR(G20*B20,0) -> 0 | I20: =IFERROR((B20/F20)*60+(E20/60)*60,0) -> 0 | J20: =IF(D20=1.5,I20,0) -> 0
A21: ='FB Laser'!A21 -> 0 | B21: ='FB Laser'!B21 -> 0 | C21: =IF('FB Laser'!C21>'FB Laser'!D21,'FB Laser'!C21,'FB Laser'!D21) -> 0 | D21: =IF(C21<48.01,1,1.5) -> 1 | G21: =IFERROR((((E21/60)*$C$4)/B21)+((60/F21/60*$C$4)*D21),0) -> 0 | H21: =IFERROR(G21*B21,0) -> 0 | I21: =IFERROR((B21/F21)*60+(E21/60)*60,0) -> 0 | J21: =IF(D21=1.5,I21,0) -> 0
... A99: ='FB Laser'!A99 -> 0 | B99: ='FB Laser'!B99 -> 0 | C99: =IF('FB Laser'!C99>'FB Laser'!D99,'FB Laser'!C99,'FB Laser'!D99) -> 0 | D99: =IF(C99<48.01,1,1.5) -> 1 | G99: =IFERROR((((E99/60)*$C$4)/B99)+((60/F99/60*$C$4)*D99),0) -> 0 | H99: =IFERROR(G99*B99,0) -> 0 | I99: =IFERROR((B99/F99)*60+(E99/60)*60,0) -> 0 | J99: =IF(D99=1.5,I99,0) -> 0

Sheet Tube Bending
B4: Tube Bending Rate | C4: 65
A8: dwg# | B8: Qty | C8: Setup (min) | D8: PPH | E8: Price (Each) | F8: Price (Lot) | G8: Run Time Lot (min)
A9: ='Tube Laser'!A9 -> 0 | B9: ='Tube Laser'!B9 -> 0 | E9: =IFERROR(ROUND((((C9/60)*$C$4)/B9)+(60/D9/60*$C$4),2),0) -> 0 | F9: =IFERROR(E9*B9,0) -> 0 | G9: =IFERROR((B9/D9)*60+(C9/60)*60,0) -> 0
A10: ='Tube Laser'!A10 -> 0 | B10: ='Tube Laser'!B10 -> 0 | E10: =IFERROR(ROUND((((C10/60)*$C$4)/B10)+(60/D10/60*$C$4),2),0) -> 0 | F10: =IFERROR(E10*B10,0) -> 0 | G10: =IFERROR((B10/D10)*60+(C10/60)*60,0) -> 0
A11: ='Tube Laser'!A11 -> 0 | B11: ='Tube Laser'!B11 -> 0 | E11: =IFERROR(ROUND((((C11/60)*$C$4)/B11)+(60/D11/60*$C$4),2),0) -> 0 | F11: =IFERROR(E11*B11,0) -> 0 | G11: =IFERROR((B11/D11)*60+(C11/60)*60,0) -> 0
A12: ='Tube Laser'!A12 -> 0 | B12: ='Tube Laser'!B12 -> 0 | E12: =IFERROR(ROUND((((C12/60)*$C$4)/B12)+(60/D12/60*$C$4),2),0) -> 0 | F12: =IFERROR(E12*B12,0) -> 0 | G12: =IFERROR((B12/D12)*60+(C12/60)*60,0) -> 0
A13: ='Tube Laser'!A13 -> 0 | B13: ='Tube Laser'!B13 -> 0 | E13: =IFERROR(ROUND((((C13/60)*$C$4)/B13)+(60/D13/60*$C$4),2),0) -> 0 | F13: =IFERROR(E13*B13,0) -> 0 | G13: =IFERROR((B13/D13)*60+(C13/60)*60,0) -> 0
A14: ='Tube Laser'!A14 -> 0 | B14: ='Tube Laser'!B14 -> 0 | E14: =IFERROR(ROUND((((C14/60)*$C$4)/B14)+(60/D14/60*$C$4),2),0) -> 0 | F14: =IFERROR(E14*B14,0) -> 0 | G14: =IFERROR((B14/D14)*60+(C14/60)*60,0) -> 0
A15: ='Tube Laser'!A15 -> 0 | B15: ='Tube Laser'!B15 -> 0 | E15: =IFERROR(ROUND((((C15/60)*$C$4)/B15)+(60/D15/60*$C$4),2),0) -> 0 | F15: =IFERROR(E15*B15,0) -> 0 | G15: =IFERROR((B15/D15)*60+(C15/60)*60,0) -> 0
A16: ='Tube Laser'!A16 -> 0 | B16: ='Tube Laser'!B16 -> 0 | E16: =IFERROR(ROUND((((C16/60)*$C$4)/B16)+(60/D16/60*$C$4),2),0) -> 0 | F16: =IFERROR(E16*B16,0) -> 0 | G16: =IFERROR((B16/D16)*60+(C16/60)*60,0) -> 0
A17: ='Tube Laser'!A17 -> 0 | B17: ='Tube Laser'!B17 -> 0 | E17: =IFERROR(ROUND((((C17/60)*$C$4)/B17)+(60/D17/60*$C$4),2),0) -> 0 | F17: =IFERROR(E17*B17,0) -> 0 | G17: =IFERROR((B17/D17)*60+(C17/60)*60,0) -> 0
A18: ='Tube Laser'!A18 -> 0 | B18: ='Tube Laser'!B18 -> 0 | E18: =IFERROR(ROUND((((C18/60)*$C$4)/B18)+(60/D18/60*$C$4),2),0) -> 0 | F18: =IFERROR(E18*B18,0) -> 0 | G18: =IFERROR((B18/D18)*60+(C18/60)*60,0) -> 0
A19: ='Tube Laser'!A19 -> 0 | B19: ='Tube Laser'!B19 -> 0 | E19: =IFERROR(ROUND((((C19/60)*$C$4)/B19)+(60/D19/60*$C$4),2),0) -> 0 | F19: =IFERROR(E19*B19,0) -> 0 | G19: =IFERROR((B19/D19)*60+(C19/60)*60,0) -> 0
A20: ='Tube Laser'!A20 -> 0 | B20: ='Tube Laser'!B20 -> 0 | E20: =IFERROR(ROUND((((C20/60)*$C$4)/B20)+(60/D20/60*$C$4),2),0) -> 0 | F20: =IFERROR(E20*B20,0) -> 0 | G20: =IFERROR((B20/D20)*60+(C20/60)*60,0) -> 0
... A98: ='Tube Laser'!A98 -> 0 | B98: ='Tube Laser'!B98 -> 0 | E98: =IFERROR(ROUND((((C98/60)*$C$4)/B98)+(60/D98/60*$C$4),2),0) -> 0 | F98: =IFERROR(E98*B98,0) -> 0 | G98: =IFERROR((B98/D98)*60+(C98/60)*60,0) -> 0

Sheet Welding
C5: Welding Cost | D5: 57.14 | E5: =D5*'Quote Info'!O4 -> 77.7104
C6: Fixture Cost | D6: 0
A9: Assembly Name | B9: Qty | C9: min/assembly | D9: Price (each) | E9: Price (lot) | F9: Weld Time Lot (hrs) | G9: Type
D10: =C10/60*$D$5 -> 0 | E10: =IFERROR(D10*B10,"") -> 0 | F10: =(C10/60)*B10 -> 0 | G10: Flat&Tube

Sheet Machining
C4: Machining Cost | D4: 83.58
A9: dwg# | B9: Qty | C9: Tooling Cost (Lot) | D9: Setup (min) | E9: Programming (min) | F9: min/part | G9: Cost (Each) | H9: Cost (Lot) | I9: Run Time Lot (min)
A10: ='FB Data'!K9 | B10: =IFERROR(IF(ISNA(VLOOKUP(A10,'FB Laser'!$A$10:$B$99,2,FALSE)),VLOOKUP(A10,'Tube Laser'!$A$9:$B$98,2,FALSE),VLOOKUP(A10,'FB Laser'!$A$10:$B$99,2,FALSE)),"") | G10: =IFERROR(ROUND((C10/B10)+(D10/60/B10*$D$4)+(E10/60/B10*60)+(F10/60*$D$4),2),"") | H10: =IFERROR(ROUND(G10*B10,2),"") | I10: =IFERROR(D10+(F10*B10),"")
A11: ='FB Data'!K10 | B11: =IFERROR(IF(ISNA(VLOOKUP(A11,'FB Laser'!$A$10:$B$99,2,FALSE)),VLOOKUP(A11,'Tube Laser'!$A$9:$B$98,2,FALSE),VLOOKUP(A11,'FB Laser'!$A$10:$B$99,2,FALSE)),"") | G11: =IFERROR(ROUND((C11/B11)+(D11/60/B11*$D$4)+(E11/60/B11*60)+(F11/60*$D$4),2),"") | H11: =IFERROR(ROUND(G11*B11,2),"") | I11: =IFERROR(D11+(F11*B11),"")
A12: ='FB Data'!K11 | B12: =IFERROR(IF(ISNA(VLOOKUP(A12,'FB Laser'!$A$10:$B$99,2,FALSE)),VLOOKUP(A12,'Tube Laser'!$A$9:$B$98,2,FALSE),VLOOKUP(A12,'FB Laser'!$A$10:$B$99,2,FALSE)),"") | G12: =IFERROR(ROUND((C12/B12)+(D12/60/B12*$D$4)+(E12/60/B12*60)+(F12/60*$D$4),2),"") | H12: =IFERROR(ROUND(G12*B12,2),"") | I12: =IFERROR(D12+(F12*B12),"")
A13: ='FB Data'!K12 | B13: =IFERROR(IF(ISNA(VLOOKUP(A13,'FB Laser'!$A$10:$B$99,2,FALSE)),VLOOKUP(A13,'Tube Laser'!$A$9:$B$98,2,FALSE),VLOOKUP(A13,'FB Laser'!$A$10:$B$99,2,FALSE)),"") | G13: =IFERROR(ROUND((C13/B13)+(D13/60/B13*$D$4)+(E13/60/B13*60)+(F13/60*$D$4),2),"") | H13: =IFERROR(ROUND(G13*B13,2),"") | I13: =IFERROR(D13+(F13*B13),"")
A14: ='FB Data'!K13 | B14: =IFERROR(IF(ISNA(VLOOKUP(A14,'FB Laser'!$A$10:$B$99,2,FALSE)),VLOOKUP(A14,'Tube Laser'!$A$9:$B$98,2,FALSE),VLOOKUP(A14,'FB Laser'!$A$10:$B$99,2,FALSE)),"") | G14: =IFERROR(ROUND((C14/B14)+(D14/60/B14*$D$4)+(E14/60/B14*60)+(F14/60*$D$4),2),"") | H14: =IFERROR(ROUND(G14*B14,2),"") | I14: =IFERROR(D14+(F14*B14),"")
A15: ='FB Data'!K14 | B15: =IFERROR(IF(ISNA(VLOOKUP(A15,'FB Laser'!$A$10:$B$99,2,FALSE)),VLOOKUP(A15,'Tube Laser'!$A$9:$B$98,2,FALSE),VLOOKUP(A15,'FB Laser'!$A$10:$B$99,2,FALSE)),"") | G15: =IFERROR(ROUND((C15/B15)+(D15/60/B15*$D$4)+(E15/60/B15*60)+(F15/60*$D$4),2),"") | H15: =IFERROR(ROUND(G15*B15,2),"") | I15: =IFERROR(D15+(F15*B15),"")
A16: ='FB Data'!K15 | B16: =IFERROR(IF(ISNA(VLOOKUP(A16,'FB Laser'!$A$10:$B$99,2,FALSE)),VLOOKUP(A16,'Tube Laser'!$A$9:$B$98,2,FALSE),VLOOKUP(A16,'FB Laser'!$A$10:$B$99,2,FALSE)),"") | G16: =IFERROR(ROUND((C16/B16)+(D16/60/B16*$D$4)+(E16/60/B16*60)+(F16/60*$D$4),2),"") | H16: =IFERROR(ROUND(G16*B16,2),"") | I16: =IFERROR(D16+(F16*B16),"")
A17: ='FB Data'!K16 | B17: =IFERROR(IF(ISNA(VLOOKUP(A17,'FB Laser'!$A$10:$B$99,2,FALSE)),VLOOKUP(A17,'Tube Laser'!$A$9:$B$98,2,FALSE),VLOOKUP(A17,'FB Laser'!$A$10:$B$99,2,FALSE)),"") | G17: =IFERROR(ROUND((C17/B17)+(D17/60/B17*$D$4)+(E17/60/B17*60)+(F17/60*$D$4),2),"") | H17: =IFERROR(ROUND(G17*B17,2),"") | I17: =IFERROR(D17+(F17*B17),"")
A18: ='FB Data'!K17 | B18: =IFERROR(IF(ISNA(VLOOKUP(A18,'FB Laser'!$A$10:$B$99,2,FALSE)),VLOOKUP(A18,'Tube Laser'!$A$9:$B$98,2,FALSE),VLOOKUP(A18,'FB Laser'!$A$10:$B$99,2,FALSE)),"") | G18: =IFERROR(ROUND((C18/B18)+(D18/60/B18*$D$4)+(E18/60/B18*60)+(F18/60*$D$4),2),"") | H18: =IFERROR(ROUND(G18*B18,2),"") | I18: =IFERROR(D18+(F18*B18),"")
A19: ='FB Data'!K18 | B19: =IFERROR(IF(ISNA(VLOOKUP(A19,'FB Laser'!$A$10:$B$99,2,FALSE)),VLOOKUP(A19,'Tube Laser'!$A$9:$B$98,2,FALSE),VLOOKUP(A19,'FB Laser'!$A$10:$B$99,2,FALSE)),"") | G19: =IFERROR(ROUND((C19/B19)+(D19/60/B19*$D$4)+(E19/60/B19*60)+(F19/60*$D$4),2),"") | H19: =IFERROR(ROUND(G19*B19,2),"") | I19: =IFERROR(D19+(F19*B19),"")
A20: ='FB Data'!K19 | B20: =IFERROR(IF(ISNA(VLOOKUP(A20,'FB Laser'!$A$10:$B$99,2,FALSE)),VLOOKUP(A20,'Tube Laser'!$A$9:$B$98,2,FALSE),VLOOKUP(A20,'FB Laser'!$A$10:$B$99,2,FALSE)),"") | G20: =IFERROR(ROUND((C20/B20)+(D20/60/B20*$D$4)+(E20/60/B20*60)+(F20/60*$D$4),2),"") | H20: =IFERROR(ROUND(G20*B20,2),"") | I20: =IFERROR(D20+(F20*B20),"")
A21: ='FB Data'!K20 | B21: =IFERROR(IF(ISNA(VLOOKUP(A21,'FB Laser'!$A$10:$B$99,2,FALSE)),VLOOKUP(A21,'Tube Laser'!$A$9:$B$98,2,FALSE),VLOOKUP(A21,'FB Laser'!$A$10:$B$99,2,FALSE)),"") | G21: =IFERROR(ROUND((C21/B21)+(D21/60/B21*$D$4)+(E21/60/B21*60)+(F21/60*$D$4),2),"") | H21: =IFERROR(ROUND(G21*B21,2),"") | I21: =IFERROR(D21+(F21*B21),"")
... A100: ='FB Data'!K99 | B100: =IFERROR(IF(ISNA(VLOOKUP(A100,'FB Laser'!$A$10:$B$99,2,FALSE)),VLOOKUP(A100,'Tube Laser'!$A$9:$B$98,2,FALSE),VLOOKUP(A100,'FB Laser'!$A$10:$B$99,2,FALSE)),"") | G100: =IFERROR(ROUND((C100/B100)+(D100/60/B100*$D$4)+(E100/60/B100*60)+(F100/60*$D$4),2),"") | H100: =IFERROR(ROUND(G100*B100,2),"") | I100: =IFERROR(D100+(F100*B100),"")
H101: =SUM(H10:H100) -> 0 | I101: =SUM(I10:I100) -> 0

Sheet Hardware Install
B4: Labor Cost | C4: 45
C5: =C4*'Quote Info'!O4 -> 61.2
A9: dwg# | B9: Qty | C9: Setup (min) | D9: # of PEMS | E9: Price (Each) | F9: Lot | G9: Run Time Lot (min) | H9: Hardware Required (Notes)
A10: ='FB Laser'!A10 -> 0 | B10: ='FB Laser'!B10 -> 0 | E10: =IFERROR(ROUND(((D10*20)/60/60*$C$4)+(C10/60*$C$4/B10),2),0) -> 0 | F10: =IFERROR(E10*B10,"") -> 0 | G10: =D10*20/60*B10+C10 -> 0
A11: ='FB Laser'!A11 -> 0 | B11: ='FB Laser'!B11 -> 0 | E11: =IFERROR(ROUND(((D11*20)/60/60*$C$4)+(C11/60*$C$4/B11),2),0) -> 0 | F11: =IFERROR(E11*B11,"") -> 0 | G11: =D11*20/60*B11+C11 -> 0
A12: ='FB Laser'!A12 -> 0 | B12: ='FB Laser'!B12 -> 0 | E12: =IFERROR(ROUND(((D12*20)/60/60*$C$4)+(C12/60*$C$4/B12),2),0) -> 0 | F12: =IFERROR(E12*B12,"") -> 0 | G12: =D12*20/60*B12+C12 -> 0
A13: ='FB Laser'!A13 -> 0 | B13: ='FB Laser'!B13 -> 0 | E13: =IFERROR(ROUND(((D13*20)/60/60*$C$4)+(C13/60*$C$4/B13),2),0) -> 0 | F13: =IFERROR(E13*B13,"") -> 0 | G13: =D13*20/60*B13+C13 -> 0
A14: ='FB Laser'!A14 -> 0 | B14: ='FB Laser'!B14 -> 0 | E14: =IFERROR(ROUND(((D14*20)/60/60*$C$4)+(C14/60*$C$4/B14),2),0) -> 0 | F14: =IFERROR(E14*B14,"") -> 0 | G14: =D14*20/60*B14+C14 -> 0
A15: ='FB Laser'!A15 -> 0 | B15: ='FB Laser'!B15 -> 0 | E15: =IFERROR(ROUND(((D15*20)/60/60*$C$4)+(C15/60*$C$4/B15),2),0) -> 0 | F15: =IFERROR(E15*B15,"") -> 0 | G15: =D15*20/60*B15+C15 -> 0
A16: ='FB Laser'!A16 -> 0 | B16: ='FB Laser'!B16 -> 0 | E16: =IFERROR(ROUND(((D16*20)/60/60*$C$4)+(C16/60*$C$4/B16),2),0) -> 0 | F16: =IFERROR(E16*B16,"") -> 0 | G16: =D16*20/60*B16+C16 -> 0
A17: ='FB Laser'!A17 -> 0 | B17: ='FB Laser'!B17 -> 0 | E17: =IFERROR(ROUND(((D17*20)/60/60*$C$4)+(C17/60*$C$4/B17),2),0) -> 0 | F17: =IFERROR(E17*B17,"") -> 0 | G17: =D17*20/60*B17+C17 -> 0
A18: ='FB Laser'!A18 -> 0 | B18: ='FB Laser'!B18 -> 0 | E18: =IFERROR(ROUND(((D18*20)/60/60*$C$4)+(C18/60*$C$4/B18),2),0) -> 0 | F18: =IFERROR(E18*B18,"") -> 0 | G18: =D18*20/60*B18+C18 -> 0
A19: ='FB Laser'!A19 -> 0 | B19: ='FB Laser'!B19 -> 0 | E19: =IFERROR(ROUND(((D19*20)/60/60*$C$4)+(C19/60*$C$4/B19),2),0) -> 0 | F19: =IFERROR(E19*B19,"") -> 0 | G19: =D19*20/60*B19+C19 -> 0
A20: ='FB Laser'!A20 -> 0 | B20: ='FB Laser'!B20 -> 0 | E20: =IFERROR(ROUND(((D20*20)/60/60*$C$4)+(C20/60*$C$4/B20),2),0) -> 0 | F20: =IFERROR(E20*B20,"") -> 0 | G20: =D20*20/60*B20+C20 -> 0
A21: ='FB Laser'!A21 -> 0 | B21: ='FB Laser'!B21 -> 0 | E21: =IFERROR(ROUND(((D21*20)/60/60*$C$4)+(C21/60*$C$4/B21),2),0) -> 0 | F21: =IFERROR(E21*B21,"") -> 0 | G21: =D21*20/60*B21+C21 -> 0
... A99: ='FB Laser'!A99 -> 0 | B99: ='FB Laser'!B99 -> 0 | E99: =IFERROR(ROUND(((D99*20)/60/60*$C$4)+(C99/60*$C$4/B99),2),0) -> 0 | F99: =IFERROR(E99*B99,"") -> 0 | G99: =D99*20/60*B99+C99 -> 0

Sheet Finishing
D4: Finishing Cost | E4: 100
D5: in/s | E5: 1.67
A9: dwg# | B9: Qty | C9: Length | D9: s/part | E9: # of Sides | F9: Setup (min) | G9: Cost (Each) | H9: Cost (Lot) | I9: Run Time Lot (min)
A10: ='FB Data'!K9 | B10: =IFERROR(IF(ISNA(VLOOKUP(A10,'FB Laser'!$A$10:$B$99,2,FALSE)),VLOOKUP(A10,'Tube Laser'!$A$9:$B$98,2,FALSE),VLOOKUP(A10,'FB Laser'!$A$10:$B$99,2,FALSE)),"") | C10: =IFERROR(IF(ISNA(VLOOKUP(A10,Forming!$A$10:$C$99,3,FALSE)),VLOOKUP(A10,'Tube Laser'!$A$9:$C$98,3,FALSE),VLOOKUP(A10,Forming!$A$10:$C$99,3,FALSE)),"") | D10: =IFERROR(C10/$E$5,"") | G10: =IFERROR((IF(ISBLANK(F10),0,(F10/60/B10*$E$4)+(D10/60/60*$E$4*E10))),"") -> 0 | H10: =IFERROR(ROUND(G10*B10,2),"") | I10: =IFERROR(IF(G10=0,0,(F10+(D10/60*B10))),"") -> 0
A11: ='FB Data'!K10 | B11: =IFERROR(IF(ISNA(VLOOKUP(A11,'FB Laser'!$A$10:$B$99,2,FALSE)),VLOOKUP(A11,'Tube Laser'!$A$9:$B$98,2,FALSE),VLOOKUP(A11,'FB Laser'!$A$10:$B$99,2,FALSE)),"") | C11: =IFERROR(IF(ISNA(VLOOKUP(A11,Forming!$A$10:$C$99,3,FALSE)),VLOOKUP(A11,'Tube Laser'!$A$9:$C$98,3,FALSE),VLOOKUP(A11,Forming!$A$10:$C$99,3,FALSE)),"") | D11: =IFERROR(C11/$E$5,"") | G11: =IFERROR((IF(ISBLANK(F11),0,(F11/60/B11*$E$4)+(D11/60/60*$E$4*E11))),"") -> 0 | H11: =IFERROR(ROUND(G11*B11,2),"") | I11: =IFERROR(IF(G11=0,0,(F11+(D11/60*B11))),"") -> 0
A12: ='FB Data'!K11 | B12: =IFERROR(IF(ISNA(VLOOKUP(A12,'FB Laser'!$A$10:$B$99,2,FALSE)),VLOOKUP(A12,'Tube Laser'!$A$9:$B$98,2,FALSE),VLOOKUP(A12,'FB Laser'!$A$10:$B$99,2,FALSE)),"") | C12: =IFERROR(IF(ISNA(VLOOKUP(A12,Forming!$A$10:$C$99,3,FALSE)),VLOOKUP(A12,'Tube Laser'!$A$9:$C$98,3,FALSE),VLOOKUP(A12,Forming!$A$10:$C$99,3,FALSE)),"") | D12: =IFERROR(C12/$E$5,"") | G12: =IFERROR((IF(ISBLANK(F12),0,(F12/60/B12*$E$4)+(D12/60/60*$E$4*E12))),"") -> 0 | H12: =IFERROR(ROUND(G12*B12,2),"") | I12: =IFERROR(IF(G12=0,0,(F12+(D12/60*B12))),"") -> 0
A13: ='FB Data'!K12 | B13: =IFERROR(IF(ISNA(VLOOKUP(A13,'FB Laser'!$A$10:$B$99,2,FALSE)),VLOOKUP(A13,'Tube Laser'!$A$9:$B$98,2,FALSE),VLOOKUP(A13,'FB Laser'!$A$10:$B$99,2,FALSE)),"") | C13: =IFERROR(IF(ISNA(VLOOKUP(A13,Forming!$A$10:$C$99,3,FALSE)),VLOOKUP(A13,'Tube Laser'!$A$9:$C$98,3,FALSE),VLOOKUP(A13,Forming!$A$10:$C$99,3,FALSE)),"") | D13: =IFERROR(C13/$E$5,"") | G13: =IFERROR((IF(ISBLANK(F13),0,(F13/60/B13*$E$4)+(D13/60/60*$E$4*E13))),"") -> 0 | H13: =IFERROR(ROUND(G13*B13,2),"") | I13: =IFERROR(IF(G13=0,0,(F13+(D13/60*B13))),"") -> 0
A14: ='FB Data'!K13 | B14: =IFERROR(IF(ISNA(VLOOKUP(A14,'FB Laser'!$A$10:$B$99,2,FALSE)),VLOOKUP(A14,'Tube Laser'!$A$9:$B$98,2,FALSE),VLOOKUP(A14,'FB Laser'!$A$10:$B$99,2,FALSE)),"") | C14: =IFERROR(IF(ISNA(VLOOKUP(A14,Forming!$A$10:$C$99,3,FALSE)),VLOOKUP(A14,'Tube Laser'!$A$9:$C$98,3,FALSE),VLOOKUP(A14,Forming!$A$10:$C$99,3,FALSE)),"") | D14: =IFERROR(C14/$E$5,"") | G14: =IFERROR((IF(ISBLANK(F14),0,(F14/60/B14*$E$4)+(D14/60/60*$E$4*E14))),"") -> 0 | H14: =IFERROR(ROUND(G14*B14,2),"") | I14: =IFERROR(IF(G14=0,0,(F14+(D14/60*B14))),"") -> 0
A15: ='FB Data'!K14 | B15: =IFERROR(IF(ISNA(VLOOKUP(A15,'FB Laser'!$A$10:$B$99,2,FALSE)),VLOOKUP(A15,'Tube Laser'!$A$9:$B$98,2,FALSE),VLOOKUP(A15,'FB Laser'!$A$10:$B$99,2,FALSE)),"") | C15: =IFERROR(IF(ISNA(VLOOKUP(A15,Forming!$A$10:$C$99,3,FALSE)),VLOOKUP(A15,'Tube Laser'!$A$9:$C$98,3,FALSE),VLOOKUP(A15,Forming!$A$10:$C$99,3,FALSE)),"") | D15: =IFERROR(C15/$E$5,"") | G15: =IFERROR((IF(ISBLANK(F15),0,(F15/60/B15*$E$4)+(D15/60/60*$E$4*E15))),"") -> 0 | H15: =IFERROR(ROUND(G15*B15,2),"") | I15: =IFERROR(IF(G15=0,0,(F15+(D15/60*B15))),"") -> 0
A16: ='FB Data'!K15 | B16: =IFERROR(IF(ISNA(VLOOKUP(A16,'FB Laser'!$A$10:$B$99,2,FALSE)),VLOOKUP(A16,'Tube Laser'!$A$9:$B$98,2,FALSE),VLOOKUP(A16,'FB Laser'!$A$10:$B$99,2,FALSE)),"") | C16: =IFERROR(IF(ISNA(VLOOKUP(A16,Forming!$A$10:$C$99,3,FALSE)),VLOOKUP(A16,'Tube Laser'!$A$9:$C$98,3,FALSE),VLOOKUP(A16,Forming!$A$10:$C$99,3,FALSE)),"") | D16: =IFERROR(C16/$E$5,"") | G16: =IFERROR((IF(ISBLANK(F16),0,(F16/60/B16*$E$4)+(D16/60/60*$E$4*E16))),"") -> 0 | H16: =IFERROR(ROUND(G16*B16,2),"") | I16: =IFERROR(IF(G16=0,0,(F16+(D16/60*B16))),"") -> 0
A17: ='FB Data'!K16 | B17: =IFERROR(IF(ISNA(VLOOKUP(A17,'FB Laser'!$A$10:$B$99,2,FALSE)),VLOOKUP(A17,'Tube Laser'!$A$9:$B$98,2,FALSE),VLOOKUP(A17,'FB Laser'!$A$10:$B$99,2,FALSE)),"") | C17: =IFERROR(IF(ISNA(VLOOKUP(A17,Forming!$A$10:$C$99,3,FALSE)),VLOOKUP(A17,'Tube Laser'!$A$9:$C$98,3,FALSE),VLOOKUP(A17,Forming!$A$10:$C$99,3,FALSE)),"") | D17: =IFERROR(C17/$E$5,"") | G17: =IFERROR((IF(ISBLANK(F17),0,(F17/60/B17*$E$4)+(D17/60/60*$E$4*E17))),"") -> 0 | H17: =IFERROR(ROUND(G17*B17,2),"") | I17: =IFERROR(IF(G17=0,0,(F17+(D17/60*B17))),"") -> 0
A18: ='FB Data'!K17 | B18: =IFERROR(IF(ISNA(VLOOKUP(A18,'FB Laser'!$A$10:$B$99,2,FALSE)),VLOOKUP(A18,'Tube Laser'!$A$9:$B$98,2,FALSE),VLOOKUP(A18,'FB Laser'!$A$10:$B$99,2,FALSE)),"") | C18: =IFERROR(IF(ISNA(VLOOKUP(A18,Forming!$A$10:$C$99,3,FALSE)),VLOOKUP(A18,'Tube Laser'!$A$9:$C$98,3,FALSE),VLOOKUP(A18,Forming!$A$10:$C$99,3,FALSE)),"") | D18: =IFERROR(C18/$E$5,"") | G18: =IFERROR((IF(ISBLANK(F18),0,(F18/60/B18*$E$4)+(D18/60/60*$E$4*E18))),"") -> 0 | H18: =IFERROR(ROUND(G18*B18,2),"") | I18: =IFERROR(IF(G18=0,0,(F18+(D18/60*B18))),"") -> 0
A19: ='FB Data'!K18 | B19: =IFERROR(IF(ISNA(VLOOKUP(A19,'FB Laser'!$A$10:$B$99,2,FALSE)),VLOOKUP(A19,'Tube Laser'!$A$9:$B$98,2,FALSE),VLOOKUP(A19,'FB Laser'!$A$10:$B$99,2,FALSE)),"") | C19: =IFERROR(IF(ISNA(VLOOKUP(A19,Forming!$A$10:$C$99,3,FALSE)),VLOOKUP(A19,'Tube Laser'!$A$9:$C$98,3,FALSE),VLOOKUP(A19,Forming!$A$10:$C$99,3,FALSE)),"") | D19: =IFERROR(C19/$E$5,"") | G19: =IFERROR((IF(ISBLANK(F19),0,(F19/60/B19*$E$4)+(D19/60/60*$E$4*E19))),"") -> 0 | H19: =IFERROR(ROUND(G19*B19,2),"") | I19: =IFERROR(IF(G19=0,0,(F19+(D19/60*B19))),"") -> 0
A20: ='FB Data'!K19 | B20: =IFERROR(IF(ISNA(VLOOKUP(A20,'FB Laser'!$A$10:$B$99,2,FALSE)),VLOOKUP(A20,'Tube Laser'!$A$9:$B$98,2,FALSE),VLOOKUP(A20,'FB Laser'!$A$10:$B$99,2,FALSE)),"") | C20: =IFERROR(IF(ISNA(VLOOKUP(A20,Forming!$A$10:$C$99,3,FALSE)),VLOOKUP(A20,'Tube Laser'!$A$9:$C$98,3,FALSE),VLOOKUP(A20,Forming!$A$10:$C$99,3,FALSE)),"") | D20: =IFERROR(C20/$E$5,"") | G20: =IFERROR((IF(ISBLANK(F20),0,(F20/60/B20*$E$4)+(D20/60/60*$E$4*E20))),"") -> 0 | H20: =IFERROR(ROUND(G20*B20,2),"") | I20: =IFERROR(IF(G20=0,0,(F20+(D20/60*B20))),"") -> 0
A21: ='FB Data'!K20 | B21: =IFERROR(IF(ISNA(VLOOKUP(A21,'FB Laser'!$A$10:$B$99,2,FALSE)),VLOOKUP(A21,'Tube Laser'!$A$9:$B$98,2,FALSE),VLOOKUP(A21,'FB Laser'!$A$10:$B$99,2,FALSE)),"") | C21: =IFERROR(IF(ISNA(VLOOKUP(A21,Forming!$A$10:$C$99,3,FALSE)),VLOOKUP(A21,'Tube Laser'!$A$9:$C$98,3,FALSE),VLOOKUP(A21,Forming!$A$10:$C$99,3,FALSE)),"") | D21: =IFERROR(C21/$E$5,"") | G21: =IFERROR((IF(ISBLANK(F21),0,(F21/60/B21*$E$4)+(D21/60/60*$E$4*E21))),"") -> 0 | H21: =IFERROR(ROUND(G21*B21,2),"") | I21: =IFERROR(IF(G21=0,0,(F21+(D21/60*B21))),"") -> 0
... A100: ='FB Data'!K99 | B100: =IFERROR(IF(ISNA(VLOOKUP(A100,'FB Laser'!$A$10:$B$99,2,FALSE)),VLOOKUP(A100,'Tube Laser'!$A$9:$B$98,2,FALSE),VLOOKUP(A100,'FB Laser'!$A$10:$B$99,2,FALSE)),"") | C100: =IFERROR(IF(ISNA(VLOOKUP(A100,Forming!$A$10:$C$99,3,FALSE)),VLOOKUP(A100,'Tube Laser'!$A$9:$C$98,3,FALSE),VLOOKUP(A100,Forming!$A$10:$C$99,3,FALSE)),"") | D100: =IFERROR(C100/$E$5,"") | G100: =IFERROR((IF(ISBLANK(F100),0,(F100/60/B100*$E$4)+(D100/60/60*$E$4*E100))),"") -> 0 | H100: =IFERROR(ROUND(G100*B100,2),"") | I100: =IFERROR(IF(G100=0,0,(F100+(D100/60*B100))),"") -> 0
H101: =SUM(H10:H100) -> 0 | I101: =ROUND(SUM(I10:I100),2) -> 0

Sheet Quote Info
B2: Process | C2: In-House? | D2: Outsourced? | E2: Vendor | F2: Estimated Hours | G2: Outsource Lead Time (Days) | H2: Notes | J2: Job Total
B3: Flatbed Laser | F3: ='Quote Info'!K7*1.2 -> 0 | K3: Revenue | L3: Cost | M3: Profit | N3: Margin | O3: Multiplier
B4: Tube Laser | F4: ='Quote Info'!L7*1.4 -> 0 | J4: Total | K4: ='FB Laser'!V100+'Tube Laser'!X99 -> 0 | L4: =SUM(K8:P8)+L10+L11+L12+L13+L14+O10+O11+O12+O13+O14+O15+O16+O17+R10+R11 -> 120 | M4: =K4-L4 -> -120 | N4: =IFERROR(M4/K4,"") | O4: 1.36
B5: Plasma
B6: Trumatic | K6: Flat Laser (hr) | L6: Tube Laser (hr) | M6: Forming (hr) | N6: Tube Bending (hr) | O6: Welding (hr) | P6: Hardware Install (hr) | Q6: Machining (hr) | R6: Total (hr)
B7: Trubend | J7: Run Time | K7: =SUM('FB Laser'!E10:E99)/60 -> 0 | L7: ='FB Data'!X118 -> 0 | M7: =SUM(Forming!I10:I99)/60 -> 0 | N7: =SUM('Tube Bending'!G9:G98)/60 -> 0 | O7: =Welding!F10 -> 0 | P7: =SUM('Hardware Install'!G10:G99)/60 -> 0 | Q7: =Machining!I101/60 -> 0 | R7: =K7+L7+M7+O7+N7+P7 -> 0
B8: Tube Bending | F8: =N7*1.2 -> 0 | J8: Cost | K8: =IF(K7=0,0,IF(K7*112.06<56.03,56.03,K7*112.06)) -> 0 | L8: =IF(L7=0,0,IF(L7*188.17<94.09,94.09,L7*188.17)) -> 0 | M8: =M7*61.62 -> 0 | N8: =N7*65 -> 0 | O8: =O7*57.14 -> 0 | P8: =P7*45 -> 0
B9: Shear
B10: Saw Cutting | J10: Cost | K10: Flat Material | L10: =SUM('FB Laser'!AD39:AD65) -> 0 | M10: GO VOLS!!! | N10: Delivery Cost | O10: ='FB Laser'!Z9+'Tube Laser'!AB8 -> 0 | P10: Rocky top | Q10: Fixture Cost | R10: =Welding!D6 -> 0
B11: Forming | F11: =M7*1.05 -> 0 | K11: Tube Material | L11: =SUM('Tube Laser'!AE30:AE56) -> 0 | N11: Packaging Cost | O11: ='FB Laser'!Z8+'Tube Laser'!AB7 -> 0 | P11: You'll always be | Q11: Finishing | R11: =Finishing!H101 -> 0
B12: Welding | F12: ='Quote Info'!O7*1.05 -> 0 | J12: Helper Labor Cost | K12: Flat | L12: ='FB Data'!AL118 -> 0 | N12: Outsource Cost | O12: ='FB Laser'!Z2+'Tube Laser'!AB2 -> 0 | P12: Home, sweet home to me
B13: Machining | F13: ='Phase Codes'!D13 -> 0 | K13: Tube | L13: ='FB Data'!AQ118 -> 0 | N13: Programming | O13: ='FB Laser'!Z3+'Tube Laser'!AB3+(SUM(Machining!E10:E100)/60*60) -> 120 | P13: Good ol' Rocky top
B14: Leveling | K14: Form | L14: =SUM(Forming!J10:J99)/60*35 -> 0 | N14: Hardware Cost | O14: ='FB Laser'!Z5 -> 0 | P14: Woooooooo!!!!
B15: Finishing | F15: =Finishing!I101/60 -> 0 | N15: QC Cost | O15: ='FB Laser'!Z6+'Tube Laser'!AB4 -> 0 | P15: Rocky top, Tennessee!
B16: Assembly | N16: Machining Cost | O16: ='FB Data'!AT118+'FB Data'!AU118-O17-(SUM(Machining!E10:E100)/60*60) -> 0 | P16: Rocky top, Tennessee!!!
B17: Hardware | N17: Tooling Cost | O17: =SUM(Machining!C10:C100) -> 0 | P17: 52-49!!!
B18: Hardware Install | F18: ='Quote Info'!P7*1.05 -> 0 | J18: Job Notes:
B19: Powder Coating/Paint
B20: Special Packaging
B21: Special Delivery
B24: Estimated Lead Time - | D24: Days

Sheet Phase Codes
B2: Phase Code | C2: Description | D2: Hours | E2: Cost | H2: Job Notes | I2: ='Quote Info'!K18 -> 0
B3: 1010 | C3: Materials | E3: ='Quote Info'!L10+'Quote Info'!L11 -> 0
B4: 2120 | C4: Shop Materials (toolcrib) | E4: ='Quote Info'!O14+'Quote Info'!O17+'Quote Info'!R10 -> 0 | H4: Part Notes
B5: 3070 | C5: Coding/Programming | D5: =E5/60 -> 2 | E5: ='Quote Info'!O13 -> 120 | H5: Part# | I5: Note
B6: 4310 | C6: Driving Labor | D6: =E6/75 -> 0 | E6: ='Quote Info'!O10 -> 0 | H6: =Notes!A5 | I6: =Notes!B5 -> 0
B7: 4410 | C7: Forming Labor | D7: ='Quote Info'!F11 -> 0 | E7: =D7*(44.5/1.05) -> 0 | H7: =Notes!A6 | I7: =Notes!B6 -> 0
B8: 4420 | C8: Welding Labor | D8: ='Quote Info'!F12 -> 0 | E8: ='Quote Info'!O8 -> 0 | H8: =Notes!A7 | I8: =Notes!B7 -> 0
B9: 4430 | C9: Flat Laser Labor | D9: =IF('Quote Info'!F3=0,0,IF('Quote Info'!F3<0.5,0.5,'Quote Info'!F3)) -> 0 | E9: =D9*(72.44/1.2) -> 0 | H9: =Notes!A8 | I9: =Notes!B8 -> 0
B10: 4440 | C10: Tube laser Labor | D10: =IF('Quote Info'!F4=0,0,IF('Quote Info'!F4<0.5,0.5,'Quote Info'!F4)) -> 0 | E10: =D10*(107.54/1.4) -> 0 | H10: =Notes!A9 | I10: =Notes!B9 -> 0
B11: 4450 | C11: Labor | D11: ='FB Data'!AL5 -> 0 | E11: ='FB Data'!AK5 -> 0 | H11: =Notes!A10 | I11: =Notes!B10 -> 0
B12: 4460 | C12: QC Labor | D12: =E12/60 -> 0 | E12: ='Quote Info'!O15 -> 0 | H12: =Notes!A11 | I12: =Notes!B11 -> 0
B13: 4470 | C13: CNC Labor | D13: ='Quote Info'!Q7 -> 0 | E13: =D13*55.5 -> 0 | H13: =Notes!A12 | I13: =Notes!B12 -> 0
B14: 4480 | C14: Metal Finishing | D14: =Finishing!I101/60 -> 0 | E14: =D14*100 -> 0 | H14: =Notes!A13 | I14: =Notes!B13 -> 0
B15: 5010 | C15: Crating Lumber | E15: ='Quote Info'!O11 -> 0 | H15: =Notes!A14 | I15: =Notes!B14 -> 0
B16: 5550 | C16: Crate Fab/Assembly | H16: =Notes!A15 | I16: =Notes!B15 -> 0
B17: 5620 | C17: Outbound Freight | H17: =Notes!A16 | I17: =Notes!B16 -> 0
B18: 7410 | C18: Press Brake Payment | D18: ='Quote Info'!M7 -> 0 | E18: =D18*12.12 -> 0 | H18: =Notes!A17 | I18: =Notes!B17 -> 0
B19: 7430 | C19: Flat Laser Payment | D19: ='Quote Info'!K7 -> 0 | E19: =D19*34.62 -> 0 | H19: =Notes!A18 | I19: =Notes!B18 -> 0
B20: 7440 | C20: Tube Laser Payment | D20: ='Quote Info'!L7 -> 0 | E20: =D20*75.63 -> 0 | H20: =Notes!A19 | I20: =Notes!B19 -> 0
B21: 7450 | C21: CNC Mill Payment | D21: ='Quote Info'!Q7 -> 0 | E21: =D21*23.08 -> 0 | H21: =Notes!A20 | I21: =Notes!B20 -> 0
B22: 7460 | C22: Maintenance | D22: =SUM('Quote Info'!K7:M7,'Quote Info'!Q7) -> 0 | E22: =D22*5 -> 0 | H22: =Notes!A21 | I22: =Notes!B21 -> 0
B23: 9410 | C23: Outsourced Processing | E23: ='Quote Info'!O12 -> 0 | H23: =Notes!A22 | I23: =Notes!B22 -> 0
B24: 9500 | C24: Contingency | H24: =Notes!A23 | I24: =Notes!B23 -> 0
E25: =SUM(E3:E24) -> 120 | H25: =Notes!A24 | I25: =Notes!B24 -> 0
H26: =Notes!A25 | I26: =Notes!B25 -> 0
H27: =Notes!A26 | I27: =Notes!B26 -> 0
H28: =Notes!A27 | I28: =Notes!B27 -> 0
H29: =Notes!A28 | I29: =Notes!B28 -> 0
H30: =Notes!A29 | I30: =Notes!B29 -> 0
H31: =Notes!A30 | I31: =Notes!B30 -> 0
H32: =Notes!A31 | I32: =Notes!B31 -> 0
H33: =Notes!A32 | I33: =Notes!B32 -> 0
H34: =Notes!A33 | I34: =Notes!B33 -> 0
H35: =Notes!A34 | I35: =Notes!B34 -> 0
H36: =Notes!A35 | I36: =Notes!B35 -> 0
H37: =Notes!A36 | I37: =Notes!B36 -> 0
... H57: =Notes!A56 | I57: =Notes!B56 -> 0

Sheet FB Data
A1: Item ID | B1: Name | C1: Unit Weight | AK1: Cost | AL1: Hours
A2: APL123003 | B2: AL PL 1/2" 3003 | C2: 7.128 | D2: LBS/SQFT | E2: 3 | K2: Choose Method | M2: Yes | O2: Choose Method | Q2: Choose Method | S2: Flat | AI2: General Labor Breakout | AJ2: Flat, Tube, Form | AK2: =SUM('Quote Info'!L12:L14) -> 0 | AL2: =AK2/35 -> 0
A3: APL125052 | B3: AL PL 1/2" 5052 | C3: 6.984 | D3: LBS/SQFT | E3: 3 | K3: Delivery | M3: No | O3: Default | Q3: JWMCD | S3: Tube | AJ3: Hardware Install | AK3: ='Quote Info'!P8 -> 0 | AL3: =AK3/45 -> 0
A4: APL126061 | B4: AL PL 1/2" 6061 | C4: 7.25 | D4: LBS/SQFT | E4: 3 | K4: Will-Call | O4: User Defined | Q4: Customer Supplied | S4: Flat&Tube | AJ4: Tube Bending | AK4: ='Quote Info'!N8 -> 0 | AL4: =AK4/65 -> 0
A5: APL143003 | B5: AL PL 1/4" 3003 | C5: 3.564 | D5: LBS/SQFT | E5: 3 | AK5: =SUM(AK2:AK4) -> 0 | AL5: =SUM(AL2:AL4) -> 0
A6: APL145052 | B6: AL PL 1/4" 5052 | C6: 3.492 | D6: LBS/SQFT | E6: 3
A7: APL146061 | B7: AL PL 1/4" 6061 | C7: 3.66 | D7: LBS/SQFT | E7: 3 | K7: For Machining | O7: For Notes | AJ7: Flat Laser | AO7: Tube Laser | AT7: Machining
A8: APL16061 | B8: AL PL 1" 6061 | C8: 14.44 | D8: LBS/SQFT | E8: 3 | K8: FL&TL | L8: FL | M8: TL | O8: FL&TL | P8: FL | Q8: TL | R8: Laser Revenue | S8: Bending Cost | U8: Tube Laser Cost | V8: Tube Laser Revenue | X8: Tube Laser Run Time | Z8: Bevel | AA8: Etch | AB8: Tap | AC8: Seam | AE8: Bevel | AF8: Etch | AG8: Tap | AH8: Seam | AJ8: Weight (lb) | AK8: Helper? | AL8: Helper Cost (Lot) | AM8: Helper Cost (Each) | AO8: Weight (lb) | AP8: Helper? | AQ8: Helper Cost (Lot) | AR8: Helper Cost (Each) | AT8: Flat | AU8: Tube
A9: APL346061 | B9: AL PL 3/4" 6061 | C9: 10.84 | D9: LBS/SQFT | E9: 3 | K9: {=INDIRECT(TEXT(MIN(IF(($L$9:$M$100<>"")*(COUNTIF($K$8:K8,$L$9:$M$100)=0),ROW($9:$100)*100+COLUMN($L:$M),7^8)),"R0C00"),)&""} | L9: =IF('FB Laser'!A10=0,"",'FB Laser'!A10) | M9: =IF('Tube Laser'!A9=0,"",'Tube Laser'!A9) | O9: {=INDIRECT(TEXT(MIN(IF(($P$9:$Q$100<>"")*(COUNTIF($O$8:O8,$P$9:$Q$100)=0),ROW($9:$100)*100+COLUMN($P:$Q),7^8)),"R0C00"),)&""} | P9: =IF('FB Laser'!F10="Yes",'FB Laser'!A10,"") | Q9: =IF('Tube Laser'!I9="Yes",'Tube Laser'!A9,"") | R9: =IFERROR(('FB Laser'!G10*'FB Laser'!B10),"") | S9: =IFERROR('FB Laser'!H10*'FB Laser'!B10,"") -> 0 | U9: =IFERROR(((((('Tube Laser'!D9)*'Tube Laser'!B9)/60)/60)*188.17)+(AE9*'Tube Laser'!B9),"") -> 0 | V9: =IFERROR(('Tube Laser'!N9*'Tube Laser'!B9)+(AE9*'Tube Laser'!B9)+(AF9*'Tube Laser'!B9)+(AG9*'Tube Laser'!B9)+('FB Data'!AH9*'Tube Laser'!B9),"") -> 0 | X9: =IFERROR(('Tube Laser'!D9*'Tube Laser'!B9)/60/60,"") -> 0 | Z9: One Side | AA9: Yes | AB9: 1 | AC9: Yes | AE9: =IF('Tube Laser'!E9="One Side",'Tube Laser'!J9*0.2,IF('Tube Laser'!E9="Both Sides",'Tube Laser'!J9*0.4,"0")) -> 0 | AF9: =IF('Tube Laser'!F9="Yes",'Tube Laser'!J9*0.1,0) -> 0 | AG9: =IF('Tube Laser'!G9>0,'Tube Laser'!J9*0.2,0) -> 0 | AH9: =IF('Tube Laser'!H9="Yes",'Tube Laser'!J9*0.1,0) -> 0 | AJ9: =IFERROR(VLOOKUP('FB Laser'!N10,'FB Data'!A2:E150,3,FALSE)*'FB Laser'!M10,0) -> 0 | AK9: =IF(AJ9>75,"full-time",IF(AJ9>32.999,"partial","")) | AL9: =IF(AK9="partial",'FB Laser'!E10/60*35*0.5,IF(AK9="full-time",'FB Laser'!E10/60*35,0)) -> 0 | AM9: =ROUND(IFERROR(AL9/'FB Laser'!B10,0),2) -> 0 | AO9: =IFERROR(VLOOKUP('Tube Laser'!P9,'TL Data'!A2:E1227,3,FALSE)*'Tube Laser'!O9,0) -> 0 | AP9: =IF(AO9>75,"full-time",IF(AO9>32.999,"partial","")) | AQ9: =IF(AP9="partial",'Tube Laser'!D9/60/60*35*'Tube Laser'!B9*0.5,IF(AP9="full-time",'Tube Laser'!D9/60/60*35*'Tube Laser'!B9,0)) -> 0 | AR9: =ROUND(IFERROR(AQ9/'Tube Laser'!B9,0),2) -> 0 | AT9: =IFERROR('FB Laser'!J10*'FB Laser'!B10,"") | AU9: =IFERROR('Tube Laser'!L9*'Tube Laser'!B9,"")
A10: APL383003 | B10: AL PL 3/8" 3003 | C10: 5.346 | D10: LBS/SQFT | E10: 3 | K10: {=INDIRECT(TEXT(MIN(IF(($L$9:$M$100<>"")*(COUNTIF($K$8:K9,$L$9:$M$100)=0),ROW($9:$100)*100+COLUMN($L:$M),7^8)),"R0C00"),)&""} | L10: =IF('FB Laser'!A11=0,"",'FB Laser'!A11) | M10: =IF('Tube Laser'!A10=0,"",'Tube Laser'!A10) | O10: {=INDIRECT(TEXT(MIN(IF(($P$9:$Q$100<>"")*(COUNTIF($O$8:O9,$P$9:$Q$100)=0),ROW($9:$100)*100+COLUMN($P:$Q),7^8)),"R0C00"),)&""} | P10: =IF('FB Laser'!F11="Yes",'FB Laser'!A11,"") | Q10: =IF('Tube Laser'!I10="Yes",'Tube Laser'!A10,"") | R10: =IFERROR(('FB Laser'!G11*'FB Laser'!B11),"") | S10: =IFERROR('FB Laser'!H11*'FB Laser'!B11,"") -> 0 | U10: =IFERROR(((((('Tube Laser'!D10)*'Tube Laser'!B10)/60)/60)*188.17)+(AE10*'Tube Laser'!B10),"") -> 0 | V10: =IFERROR(('Tube Laser'!N10*'Tube Laser'!B10)+(AE10*'Tube Laser'!B10)+(AF10*'Tube Laser'!B10)+(AG10*'Tube Laser'!B10)+('FB Data'!AH10*'Tube Laser'!B10),"") -> 0 | X10: =IFERROR(('Tube Laser'!D10*'Tube Laser'!B10)/60/60,"") -> 0 | Z10: Both Sides | AB10: 2 | AE10: =IF('Tube Laser'!E10="One Side",'Tube Laser'!J10*0.2,IF('Tube Laser'!E10="Both Sides",'Tube Laser'!J10*0.4,"0")) -> 0 | AF10: =IF('Tube Laser'!F10="Yes",'Tube Laser'!J10*0.1,0) -> 0 | AG10: =IF('Tube Laser'!G10>0,'Tube Laser'!J10*0.2,0) -> 0 | AH10: =IF('Tube Laser'!H10="Yes",'Tube Laser'!J10*0.1,0) -> 0 | AJ10: =IFERROR(VLOOKUP('FB Laser'!N11,'FB Data'!A3:E151,3,FALSE)*'FB Laser'!M11,0) -> 0 | AK10: =IF(AJ10>75,"full-time",IF(AJ10>32.999,"partial","")) | AL10: =IF(AK10="partial",'FB Laser'!E11/60*35*0.5,IF(AK10="full-time",'FB Laser'!E11/60*35,0)) -> 0 | AM10: =ROUND(IFERROR(AL10/'FB Laser'!B11,0),2) -> 0 | AO10: =IFERROR(VLOOKUP('Tube Laser'!P10,'TL Data'!A3:E1228,3,FALSE)*'Tube Laser'!O10,0) -> 0 | AP10: =IF(AO10>75,"full-time",IF(AO10>32.999,"partial","")) | AQ10: =IF(AP10="partial",'Tube Laser'!D10/60/60*35*'Tube Laser'!B10*0.5,IF(AP10="full-time",'Tube Laser'!D10/60/60*35*'Tube Laser'!B10,0)) -> 0 | AR10: =ROUND(IFERROR(AQ10/'Tube Laser'!B10,0),2) -> 0 | AT10: =IFERROR('FB Laser'!J11*'FB Laser'!B11,"") | AU10: =IFERROR('Tube Laser'!L10*'Tube Laser'!B10,"")
A11: APL385052 | B11: AL PL 3/8" 5052 | C11: 5.238 | D11: LBS/SQFT | E11: 3 | K11: {=INDIRECT(TEXT(MIN(IF(($L$9:$M$100<>"")*(COUNTIF($K$8:K10,$L$9:$M$100)=0),ROW($9:$100)*100+COLUMN($L:$M),7^8)),"R0C00"),)&""} | L11: =IF('FB Laser'!A12=0,"",'FB Laser'!A12) | M11: =IF('Tube Laser'!A11=0,"",'Tube Laser'!A11) | O11: {=INDIRECT(TEXT(MIN(IF(($P$9:$Q$100<>"")*(COUNTIF($O$8:O10,$P$9:$Q$100)=0),ROW($9:$100)*100+COLUMN($P:$Q),7^8)),"R0C00"),)&""} | P11: =IF('FB Laser'!F12="Yes",'FB Laser'!A12,"") | Q11: =IF('Tube Laser'!I11="Yes",'Tube Laser'!A11,"") | R11: =IFERROR(('FB Laser'!G12*'FB Laser'!B12),"") | S11: =IFERROR('FB Laser'!H12*'FB Laser'!B12,"") -> 0 | U11: =IFERROR(((((('Tube Laser'!D11)*'Tube Laser'!B11)/60)/60)*188.17)+(AE11*'Tube Laser'!B11),"") -> 0 | V11: =IFERROR(('Tube Laser'!N11*'Tube Laser'!B11)+(AE11*'Tube Laser'!B11)+(AF11*'Tube Laser'!B11)+(AG11*'Tube Laser'!B11)+('FB Data'!AH11*'Tube Laser'!B11),"") -> 0 | X11: =IFERROR(('Tube Laser'!D11*'Tube Laser'!B11)/60/60,"") -> 0 | AB11: 3 | AE11: =IF('Tube Laser'!E11="One Side",'Tube Laser'!J11*0.2,IF('Tube Laser'!E11="Both Sides",'Tube Laser'!J11*0.4,"0")) -> 0 | AF11: =IF('Tube Laser'!F11="Yes",'Tube Laser'!J11*0.1,0) -> 0 | AG11: =IF('Tube Laser'!G11>0,'Tube Laser'!J11*0.2,0) -> 0 | AH11: =IF('Tube Laser'!H11="Yes",'Tube Laser'!J11*0.1,0) -> 0 | AJ11: =IFERROR(VLOOKUP('FB Laser'!N12,'FB Data'!A4:E152,3,FALSE)*'FB Laser'!M12,0) -> 0 | AK11: =IF(AJ11>75,"full-time",IF(AJ11>32.999,"partial","")) | AL11: =IF(AK11="partial",'FB Laser'!E12/60*35*0.5,IF(AK11="full-time",'FB Laser'!E12/60*35,0)) -> 0 | AM11: =ROUND(IFERROR(AL11/'FB Laser'!B12,0),2) -> 0 | AO11: =IFERROR(VLOOKUP('Tube Laser'!P11,'TL Data'!A4:E1229,3,FALSE)*'Tube Laser'!O11,0) -> 0 | AP11: =IF(AO11>75,"full-time",IF(AO11>32.999,"partial","")) | AQ11: =IF(AP11="partial",'Tube Laser'!D11/60/60*35*'Tube Laser'!B11*0.5,IF(AP11="full-time",'Tube Laser'!D11/60/60*35*'Tube Laser'!B11,0)) -> 0 | AR11: =ROUND(IFERROR(AQ11/'Tube Laser'!B11,0),2) -> 0 | AT11: =IFERROR('FB Laser'!J12*'FB Laser'!B12,"") | AU11: =IFERROR('Tube Laser'!L11*'Tube Laser'!B11,"")
A12: APL386061 | B12: AL PL 3/8" 6061 | C12: 5.44 | D12: LBS/SQFT | E12: 3 | K12: {=INDIRECT(TEXT(MIN(IF(($L$9:$M$100<>"")*(COUNTIF($K$8:K11,$L$9:$M$100)=0),ROW($9:$100)*100+COLUMN($L:$M),7^8)),"R0C00"),)&""} | L12: =IF('FB Laser'!A13=0,"",'FB Laser'!A13) | M12: =IF('Tube Laser'!A12=0,"",'Tube Laser'!A12) | O12: {=INDIRECT(TEXT(MIN(IF(($P$9:$Q$100<>"")*(COUNTIF($O$8:O11,$P$9:$Q$100)=0),ROW($9:$100)*100+COLUMN($P:$Q),7^8)),"R0C00"),)&""} | P12: =IF('FB Laser'!F13="Yes",'FB Laser'!A13,"") | Q12: =IF('Tube Laser'!I12="Yes",'Tube Laser'!A12,"") | R12: =IFERROR(('FB Laser'!G13*'FB Laser'!B13),"") | S12: =IFERROR('FB Laser'!H13*'FB Laser'!B13,"") -> 0 | U12: =IFERROR(((((('Tube Laser'!D12)*'Tube Laser'!B12)/60)/60)*188.17)+(AE12*'Tube Laser'!B12),"") -> 0 | V12: =IFERROR(('Tube Laser'!N12*'Tube Laser'!B12)+(AE12*'Tube Laser'!B12)+(AF12*'Tube Laser'!B12)+(AG12*'Tube Laser'!B12)+('FB Data'!AH12*'Tube Laser'!B12),"") -> 0 | X12: =IFERROR(('Tube Laser'!D12*'Tube Laser'!B12)/60/60,"") -> 0 | AB12: 4 | AE12: =IF('Tube Laser'!E12="One Side",'Tube Laser'!J12*0.2,IF('Tube Laser'!E12="Both Sides",'Tube Laser'!J12*0.4,"0")) -> 0 | AF12: =IF('Tube Laser'!F12="Yes",'Tube Laser'!J12*0.1,0) -> 0 | AG12: =IF('Tube Laser'!G12>0,'Tube Laser'!J12*0.2,0) -> 0 | AH12: =IF('Tube Laser'!H12="Yes",'Tube Laser'!J12*0.1,0) -> 0 | AJ12: =IFERROR(VLOOKUP('FB Laser'!N13,'FB Data'!A5:E153,3,FALSE)*'FB Laser'!M13,0) -> 0 | AK12: =IF(AJ12>75,"full-time",IF(AJ12>32.999,"partial","")) | AL12: =IF(AK12="partial",'FB Laser'!E13/60*35*0.5,IF(AK12="full-time",'FB Laser'!E13/60*35,0)) -> 0 | AM12: =ROUND(IFERROR(AL12/'FB Laser'!B13,0),2) -> 0 | AO12: =IFERROR(VLOOKUP('Tube Laser'!P12,'TL Data'!A5:E1230,3,FALSE)*'Tube Laser'!O12,0) -> 0 | AP12: =IF(AO12>75,"full-time",IF(AO12>32.999,"partial","")) | AQ12: =IF(AP12="partial",'Tube Laser'!D12/60/60*35*'Tube Laser'!B12*0.5,IF(AP12="full-time",'Tube Laser'!D12/60/60*35*'Tube Laser'!B12,0)) -> 0 | AR12: =ROUND(IFERROR(AQ12/'Tube Laser'!B12,0),2) -> 0 | AT12: =IFERROR('FB Laser'!J13*'FB Laser'!B13,"") | AU12: =IFERROR('Tube Laser'!L12*'Tube Laser'!B12,"")
A13: APL5166061 | B13: AL PL 5/16" 6061 | C13: 4.52 | D13: LBS/SQFT | E13: 3 | K13: {=INDIRECT(TEXT(MIN(IF(($L$9:$M$100<>"")*(COUNTIF($K$8:K12,$L$9:$M$100)=0),ROW($9:$100)*100+COLUMN($L:$M),7^8)),"R0C00"),)&""} | L13: =IF('FB Laser'!A14=0,"",'FB Laser'!A14) | M13: =IF('Tube Laser'!A13=0,"",'Tube Laser'!A13) | O13: {=INDIRECT(TEXT(MIN(IF(($P$9:$Q$100<>"")*(COUNTIF($O$8:O12,$P$9:$Q$100)=0),ROW($9:$100)*100+COLUMN($P:$Q),7^8)),"R0C00"),)&""} | P13: =IF('FB Laser'!F14="Yes",'FB Laser'!A14,"") | Q13: =IF('Tube Laser'!I13="Yes",'Tube Laser'!A13,"") | R13: =IFERROR(('FB Laser'!G14*'FB Laser'!B14),"") | S13: =IFERROR('FB Laser'!H14*'FB Laser'!B14,"") -> 0 | U13: =IFERROR(((((('Tube Laser'!D13)*'Tube Laser'!B13)/60)/60)*188.17)+(AE13*'Tube Laser'!B13),"") -> 0 | V13: =IFERROR(('Tube Laser'!N13*'Tube Laser'!B13)+(AE13*'Tube Laser'!B13)+(AF13*'Tube Laser'!B13)+(AG13*'Tube Laser'!B13)+('FB Data'!AH13*'Tube Laser'!B13),"") -> 0 | X13: =IFERROR(('Tube Laser'!D13*'Tube Laser'!B13)/60/60,"") -> 0 | AB13: 5 | AE13: =IF('Tube Laser'!E13="One Side",'Tube Laser'!J13*0.2,IF('Tube Laser'!E13="Both Sides",'Tube Laser'!J13*0.4,"0")) -> 0 | AF13: =IF('Tube Laser'!F13="Yes",'Tube Laser'!J13*0.1,0) -> 0 | AG13: =IF('Tube Laser'!G13>0,'Tube Laser'!J13*0.2,0) -> 0 | AH13: =IF('Tube Laser'!H13="Yes",'Tube Laser'!J13*0.1,0) -> 0 | AJ13: =IFERROR(VLOOKUP('FB Laser'!N14,'FB Data'!A6:E154,3,FALSE)*'FB Laser'!M14,0) -> 0 | AK13: =IF(AJ13>75,"full-time",IF(AJ13>32.999,"partial","")) | AL13: =IF(AK13="partial",'FB Laser'!E14/60*35*0.5,IF(AK13="full-time",'FB Laser'!E14/60*35,0)) -> 0 | AM13: =ROUND(IFERROR(AL13/'FB Laser'!B14,0),2) -> 0 | AO13: =IFERROR(VLOOKUP('Tube Laser'!P13,'TL Data'!A6:E1231,3,FALSE)*'Tube Laser'!O13,0) -> 0 | AP13: =IF(AO13>75,"full-time",IF(AO13>32.999,"partial","")) | AQ13: =IF(AP13="partial",'Tube Laser'!D13/60/60*35*'Tube Laser'!B13*0.5,IF(AP13="full-time",'Tube Laser'!D13/60/60*35*'Tube Laser'!B13,0)) -> 0 | AR13: =ROUND(IFERROR(AQ13/'Tube Laser'!B13,0),2) -> 0 | AT13: =IFERROR('FB Laser'!J14*'FB Laser'!B14,"") | AU13: =IFERROR('Tube Laser'!L13*'Tube Laser'!B13,"")
A14: APL586061 | B14: AL PL 5/8" 6061 | C14: 9.02 | D14: LBS/SQFT | E14: 3 | K14: {=INDIRECT(TEXT(MIN(IF(($L$9:$M$100<>"")*(COUNTIF($K$8:K13,$L$9:$M$100)=0),ROW($9:$100)*100+COLUMN($L:$M),7^8)),"R0C00"),)&""} | L14: =IF('FB Laser'!A15=0,"",'FB Laser'!A15) | M14: =IF('Tube Laser'!A14=0,"",'Tube Laser'!A14) | O14: {=INDIRECT(TEXT(MIN(IF(($P$9:$Q$100<>"")*(COUNTIF($O$8:O13,$P$9:$Q$100)=0),ROW($9:$100)*100+COLUMN($P:$Q),7^8)),"R0C00"),)&""} | P14: =IF('FB Laser'!F15="Yes",'FB Laser'!A15,"") | Q14: =IF('Tube Laser'!I14="Yes",'Tube Laser'!A14,"") | R14: =IFERROR(('FB Laser'!G15*'FB Laser'!B15),"") | S14: =IFERROR('FB Laser'!H15*'FB Laser'!B15,"") -> 0 | U14: =IFERROR(((((('Tube Laser'!D14)*'Tube Laser'!B14)/60)/60)*188.17)+(AE14*'Tube Laser'!B14),"") -> 0 | V14: =IFERROR(('Tube Laser'!N14*'Tube Laser'!B14)+(AE14*'Tube Laser'!B14)+(AF14*'Tube Laser'!B14)+(AG14*'Tube Laser'!B14)+('FB Data'!AH14*'Tube Laser'!B14),"") -> 0 | X14: =IFERROR(('Tube Laser'!D14*'Tube Laser'!B14)/60/60,"") -> 0 | AB14: 6 | AE14: =IF('Tube Laser'!E14="One Side",'Tube Laser'!J14*0.2,IF('Tube Laser'!E14="Both Sides",'Tube Laser'!J14*0.4,"0")) -> 0 | AF14: =IF('Tube Laser'!F14="Yes",'Tube Laser'!J14*0.1,0) -> 0 | AG14: =IF('Tube Laser'!G14>0,'Tube Laser'!J14*0.2,0) -> 0 | AH14: =IF('Tube Laser'!H14="Yes",'Tube Laser'!J14*0.1,0) -> 0 | AJ14: =IFERROR(VLOOKUP('FB Laser'!N15,'FB Data'!A7:E155,3,FALSE)*'FB Laser'!M15,0) -> 0 | AK14: =IF(AJ14>75,"full-time",IF(AJ14>32.999,"partial","")) | AL14: =IF(AK14="partial",'FB Laser'!E15/60*35*0.5,IF(AK14="full-time",'FB Laser'!E15/60*35,0)) -> 0 | AM14: =ROUND(IFERROR(AL14/'FB Laser'!B15,0),2) -> 0 | AO14: =IFERROR(VLOOKUP('Tube Laser'!P14,'TL Data'!A7:E1232,3,FALSE)*'Tube Laser'!O14,0) -> 0 | AP14: =IF(AO14>75,"full-time",IF(AO14>32.999,"partial","")) | AQ14: =IF(AP14="partial",'Tube Laser'!D14/60/60*35*'Tube Laser'!B14*0.5,IF(AP14="full-time",'Tube Laser'!D14/60/60*35*'Tube Laser'!B14,0)) -> 0 | AR14: =ROUND(IFERROR(AQ14/'Tube Laser'!B14,0),2) -> 0 | AT14: =IFERROR('FB Laser'!J15*'FB Laser'!B15,"") | AU14: =IFERROR('Tube Laser'!L14*'Tube Laser'!B14,"")
A15: APL786061 | B15: AL PL 7/8" 6061 | C15: 12.55 | D15: LBS/SQFT | E15: 3 | K15: {=INDIRECT(TEXT(MIN(IF(($L$9:$M$100<>"")*(COUNTIF($K$8:K14,$L$9:$M$100)=0),ROW($9:$100)*100+COLUMN($L:$M),7^8)),"R0C00"),)&""} | L15: =IF('FB Laser'!A16=0,"",'FB Laser'!A16) | M15: =IF('Tube Laser'!A15=0,"",'Tube Laser'!A15) | O15: {=INDIRECT(TEXT(MIN(IF(($P$9:$Q$100<>"")*(COUNTIF($O$8:O14,$P$9:$Q$100)=0),ROW($9:$100)*100+COLUMN($P:$Q),7^8)),"R0C00"),)&""} | P15: =IF('FB Laser'!F16="Yes",'FB Laser'!A16,"") | Q15: =IF('Tube Laser'!I15="Yes",'Tube Laser'!A15,"") | R15: =IFERROR(('FB Laser'!G16*'FB Laser'!B16),"") | S15: =IFERROR('FB Laser'!H16*'FB Laser'!B16,"") -> 0 | U15: =IFERROR(((((('Tube Laser'!D15)*'Tube Laser'!B15)/60)/60)*188.17)+(AE15*'Tube Laser'!B15),"") -> 0 | V15: =IFERROR(('Tube Laser'!N15*'Tube Laser'!B15)+(AE15*'Tube Laser'!B15)+(AF15*'Tube Laser'!B15)+(AG15*'Tube Laser'!B15)+('FB Data'!AH15*'Tube Laser'!B15),"") -> 0 | X15: =IFERROR(('Tube Laser'!D15*'Tube Laser'!B15)/60/60,"") -> 0 | AB15: 7 | AE15: =IF('Tube Laser'!E15="One Side",'Tube Laser'!J15*0.2,IF('Tube Laser'!E15="Both Sides",'Tube Laser'!J15*0.4,"0")) -> 0 | AF15: =IF('Tube Laser'!F15="Yes",'Tube Laser'!J15*0.1,0) -> 0 | AG15: =IF('Tube Laser'!G15>0,'Tube Laser'!J15*0.2,0) -> 0 | AH15: =IF('Tube Laser'!H15="Yes",'Tube Laser'!J15*0.1,0) -> 0 | AJ15: =IFERROR(VLOOKUP('FB Laser'!N16,'FB Data'!A8:E156,3,FALSE)*'FB Laser'!M16,0) -> 0 | AK15: =IF(AJ15>75,"full-time",IF(AJ15>32.999,"partial","")) | AL15: =IF(AK15="partial",'FB Laser'!E16/60*35*0.5,IF(AK15="full-time",'FB Laser'!E16/60*35,0)) -> 0 | AM15: =ROUND(IFERROR(AL15/'FB Laser'!B16,0),2) -> 0 | AO15: =IFERROR(VLOOKUP('Tube Laser'!P15,'TL Data'!A8:E1233,3,FALSE)*'Tube Laser'!O15,0) -> 0 | AP15: =IF(AO15>75,"full-time",IF(AO15>32.999,"partial","")) | AQ15: =IF(AP15="partial",'Tube Laser'!D15/60/60*35*'Tube Laser'!B15*0.5,IF(AP15="full-time",'Tube Laser'!D15/60/60*35*'Tube Laser'!B15,0)) -> 0 | AR15: =ROUND(IFERROR(AQ15/'Tube Laser'!B15,0),2) -> 0 | AT15: =IFERROR('FB Laser'!J16*'FB Laser'!B16,"") | AU15: =IFERROR('Tube Laser'!L15*'Tube Laser'!B15,"")
A16: ASH0503003 | B16: AL SHEET .050" 3003 | C16: 0.713 | D16: LBS/SQFT | E16: 4 | K16: {=INDIRECT(TEXT(MIN(IF(($L$9:$M$100<>"")*(COUNTIF($K$8:K15,$L$9:$M$100)=0),ROW($9:$100)*100+COLUMN($L:$M),7^8)),"R0C00"),)&""} | L16: =IF('FB Laser'!A17=0,"",'FB Laser'!A17) | M16: =IF('Tube Laser'!A16=0,"",'Tube Laser'!A16) | O16: {=INDIRECT(TEXT(MIN(IF(($P$9:$Q$100<>"")*(COUNTIF($O$8:O15,$P$9:$Q$100)=0),ROW($9:$100)*100+COLUMN($P:$Q),7^8)),"R0C00"),)&""} | P16: =IF('FB Laser'!F17="Yes",'FB Laser'!A17,"") | Q16: =IF('Tube Laser'!I16="Yes",'Tube Laser'!A16,"") | R16: =IFERROR(('FB Laser'!G17*'FB Laser'!B17),"") | S16: =IFERROR('FB Laser'!H17*'FB Laser'!B17,"") -> 0 | U16: =IFERROR(((((('Tube Laser'!D16)*'Tube Laser'!B16)/60)/60)*188.17)+(AE16*'Tube Laser'!B16),"") -> 0 | V16: =IFERROR(('Tube Laser'!N16*'Tube Laser'!B16)+(AE16*'Tube Laser'!B16)+(AF16*'Tube Laser'!B16)+(AG16*'Tube Laser'!B16)+('FB Data'!AH16*'Tube Laser'!B16),"") -> 0 | X16: =IFERROR(('Tube Laser'!D16*'Tube Laser'!B16)/60/60,"") -> 0 | AB16: 8 | AE16: =IF('Tube Laser'!E16="One Side",'Tube Laser'!J16*0.2,IF('Tube Laser'!E16="Both Sides",'Tube Laser'!J16*0.4,"0")) -> 0 | AF16: =IF('Tube Laser'!F16="Yes",'Tube Laser'!J16*0.1,0) -> 0 | AG16: =IF('Tube Laser'!G16>0,'Tube Laser'!J16*0.2,0) -> 0 | AH16: =IF('Tube Laser'!H16="Yes",'Tube Laser'!J16*0.1,0) -> 0 | AJ16: =IFERROR(VLOOKUP('FB Laser'!N17,'FB Data'!A9:E157,3,FALSE)*'FB Laser'!M17,0) -> 0 | AK16: =IF(AJ16>75,"full-time",IF(AJ16>32.999,"partial","")) | AL16: =IF(AK16="partial",'FB Laser'!E17/60*35*0.5,IF(AK16="full-time",'FB Laser'!E17/60*35,0)) -> 0 | AM16: =ROUND(IFERROR(AL16/'FB Laser'!B17,0),2) -> 0 | AO16: =IFERROR(VLOOKUP('Tube Laser'!P16,'TL Data'!A9:E1234,3,FALSE)*'Tube Laser'!O16,0) -> 0 | AP16: =IF(AO16>75,"full-time",IF(AO16>32.999,"partial","")) | AQ16: =IF(AP16="partial",'Tube Laser'!D16/60/60*35*'Tube Laser'!B16*0.5,IF(AP16="full-time",'Tube Laser'!D16/60/60*35*'Tube Laser'!B16,0)) -> 0 | AR16: =ROUND(IFERROR(AQ16/'Tube Laser'!B16,0),2) -> 0 | AT16: =IFERROR('FB Laser'!J17*'FB Laser'!B17,"") | AU16: =IFERROR('Tube Laser'!L16*'Tube Laser'!B16,"")
A17: ASH0505052 | B17: AL SHEET .050" 5052 | C17: 0.698 | D17: LBS/SQFT | E17: 4 | K17: {=INDIRECT(TEXT(MIN(IF(($L$9:$M$100<>"")*(COUNTIF($K$8:K16,$L$9:$M$100)=0),ROW($9:$100)*100+COLUMN($L:$M),7^8)),"R0C00"),)&""} | L17: =IF('FB Laser'!A18=0,"",'FB Laser'!A18) | M17: =IF('Tube Laser'!A17=0,"",'Tube Laser'!A17) | O17: {=INDIRECT(TEXT(MIN(IF(($P$9:$Q$100<>"")*(COUNTIF($O$8:O16,$P$9:$Q$100)=0),ROW($9:$100)*100+COLUMN($P:$Q),7^8)),"R0C00"),)&""} | P17: =IF('FB Laser'!F18="Yes",'FB Laser'!A18,"") | Q17: =IF('Tube Laser'!I17="Yes",'Tube Laser'!A17,"") | R17: =IFERROR(('FB Laser'!G18*'FB Laser'!B18),"") | S17: =IFERROR('FB Laser'!H18*'FB Laser'!B18,"") -> 0 | U17: =IFERROR(((((('Tube Laser'!D17)*'Tube Laser'!B17)/60)/60)*188.17)+(AE17*'Tube Laser'!B17),"") -> 0 | V17: =IFERROR(('Tube Laser'!N17*'Tube Laser'!B17)+(AE17*'Tube Laser'!B17)+(AF17*'Tube Laser'!B17)+(AG17*'Tube Laser'!B17)+('FB Data'!AH17*'Tube Laser'!B17),"") -> 0 | X17: =IFERROR(('Tube Laser'!D17*'Tube Laser'!B17)/60/60,"") -> 0 | AB17: 9 | AE17: =IF('Tube Laser'!E17="One Side",'Tube Laser'!J17*0.2,IF('Tube Laser'!E17="Both Sides",'Tube Laser'!J17*0.4,"0")) -> 0 | AF17: =IF('Tube Laser'!F17="Yes",'Tube Laser'!J17*0.1,0) -> 0 | AG17: =IF('Tube Laser'!G17>0,'Tube Laser'!J17*0.2,0) -> 0 | AH17: =IF('Tube Laser'!H17="Yes",'Tube Laser'!J17*0.1,0) -> 0 | AJ17: =IFERROR(VLOOKUP('FB Laser'!N18,'FB Data'!A10:E158,3,FALSE)*'FB Laser'!M18,0) -> 0 | AK17: =IF(AJ17>75,"full-time",IF(AJ17>32.999,"partial","")) | AL17: =IF(AK17="partial",'FB Laser'!E18/60*35*0.5,IF(AK17="full-time",'FB Laser'!E18/60*35,0)) -> 0 | AM17: =ROUND(IFERROR(AL17/'FB Laser'!B18,0),2) -> 0 | AO17: =IFERROR(VLOOKUP('Tube Laser'!P17,'TL Data'!A10:E1235,3,FALSE)*'Tube Laser'!O17,0) -> 0 | AP17: =IF(AO17>75,"full-time",IF(AO17>32.999,"partial","")) | AQ17: =IF(AP17="partial",'Tube Laser'!D17/60/60*35*'Tube Laser'!B17*0.5,IF(AP17="full-time",'Tube Laser'!D17/60/60*35*'Tube Laser'!B17,0)) -> 0 | AR17: =ROUND(IFERROR(AQ17/'Tube Laser'!B17,0),2) -> 0 | AT17: =IFERROR('FB Laser'!J18*'FB Laser'!B18,"") | AU17: =IFERROR('Tube Laser'!L17*'Tube Laser'!B17,"")
A18: ASH0506061 | B18: AL SHEET .050" 6061 | C18: 0.706 | D18: LBS/SQFT | E18: 4 | K18: {=INDIRECT(TEXT(MIN(IF(($L$9:$M$100<>"")*(COUNTIF($K$8:K17,$L$9:$M$100)=0),ROW($9:$100)*100+COLUMN($L:$M),7^8)),"R0C00"),)&""} | L18: =IF('FB Laser'!A19=0,"",'FB Laser'!A19) | M18: =IF('Tube Laser'!A18=0,"",'Tube Laser'!A18) | O18: {=INDIRECT(TEXT(MIN(IF(($P$9:$Q$100<>"")*(COUNTIF($O$8:O17,$P$9:$Q$100)=0),ROW($9:$100)*100+COLUMN($P:$Q),7^8)),"R0C00"),)&""} | P18: =IF('FB Laser'!F19="Yes",'FB Laser'!A19,"") | Q18: =IF('Tube Laser'!I18="Yes",'Tube Laser'!A18,"") | R18: =IFERROR(('FB Laser'!G19*'FB Laser'!B19),"") | S18: =IFERROR('FB Laser'!H19*'FB Laser'!B19,"") -> 0 | U18: =IFERROR(((((('Tube Laser'!D18)*'Tube Laser'!B18)/60)/60)*188.17)+(AE18*'Tube Laser'!B18),"") -> 0 | V18: =IFERROR(('Tube Laser'!N18*'Tube Laser'!B18)+(AE18*'Tube Laser'!B18)+(AF18*'Tube Laser'!B18)+(AG18*'Tube Laser'!B18)+('FB Data'!AH18*'Tube Laser'!B18),"") -> 0 | X18: =IFERROR(('Tube Laser'!D18*'Tube Laser'!B18)/60/60,"") -> 0 | AB18: 10 | AE18: =IF('Tube Laser'!E18="One Side",'Tube Laser'!J18*0.2,IF('Tube Laser'!E18="Both Sides",'Tube Laser'!J18*0.4,"0")) -> 0 | AF18: =IF('Tube Laser'!F18="Yes",'Tube Laser'!J18*0.1,0) -> 0 | AG18: =IF('Tube Laser'!G18>0,'Tube Laser'!J18*0.2,0) -> 0 | AH18: =IF('Tube Laser'!H18="Yes",'Tube Laser'!J18*0.1,0) -> 0 | AJ18: =IFERROR(VLOOKUP('FB Laser'!N19,'FB Data'!A11:E159,3,FALSE)*'FB Laser'!M19,0) -> 0 | AK18: =IF(AJ18>75,"full-time",IF(AJ18>32.999,"partial","")) | AL18: =IF(AK18="partial",'FB Laser'!E19/60*35*0.5,IF(AK18="full-time",'FB Laser'!E19/60*35,0)) -> 0 | AM18: =ROUND(IFERROR(AL18/'FB Laser'!B19,0),2) -> 0 | AO18: =IFERROR(VLOOKUP('Tube Laser'!P18,'TL Data'!A11:E1236,3,FALSE)*'Tube Laser'!O18,0) -> 0 | AP18: =IF(AO18>75,"full-time",IF(AO18>32.999,"partial","")) | AQ18: =IF(AP18="partial",'Tube Laser'!D18/60/60*35*'Tube Laser'!B18*0.5,IF(AP18="full-time",'Tube Laser'!D18/60/60*35*'Tube Laser'!B18,0)) -> 0 | AR18: =ROUND(IFERROR(AQ18/'Tube Laser'!B18,0),2) -> 0 | AT18: =IFERROR('FB Laser'!J19*'FB Laser'!B19,"") | AU18: =IFERROR('Tube Laser'!L18*'Tube Laser'!B18,"")
A19: ASH0633003 | B19: AL SHEET .063" 3003 | C19: 0.898 | D19: LBS/SQFT | E19: 4 | K19: {=INDIRECT(TEXT(MIN(IF(($L$9:$M$100<>"")*(COUNTIF($K$8:K18,$L$9:$M$100)=0),ROW($9:$100)*100+COLUMN($L:$M),7^8)),"R0C00"),)&""} | L19: =IF('FB Laser'!A20=0,"",'FB Laser'!A20) | M19: =IF('Tube Laser'!A19=0,"",'Tube Laser'!A19) | O19: {=INDIRECT(TEXT(MIN(IF(($P$9:$Q$100<>"")*(COUNTIF($O$8:O18,$P$9:$Q$100)=0),ROW($9:$100)*100+COLUMN($P:$Q),7^8)),"R0C00"),)&""} | P19: =IF('FB Laser'!F20="Yes",'FB Laser'!A20,"") | Q19: =IF('Tube Laser'!I19="Yes",'Tube Laser'!A19,"") | R19: =IFERROR(('FB Laser'!G20*'FB Laser'!B20),"") | S19: =IFERROR('FB Laser'!H20*'FB Laser'!B20,"") -> 0 | U19: =IFERROR(((((('Tube Laser'!D19)*'Tube Laser'!B19)/60)/60)*188.17)+(AE19*'Tube Laser'!B19),"") -> 0 | V19: =IFERROR(('Tube Laser'!N19*'Tube Laser'!B19)+(AE19*'Tube Laser'!B19)+(AF19*'Tube Laser'!B19)+(AG19*'Tube Laser'!B19)+('FB Data'!AH19*'Tube Laser'!B19),"") -> 0 | X19: =IFERROR(('Tube Laser'!D19*'Tube Laser'!B19)/60/60,"") -> 0 | AB19: 11 | AE19: =IF('Tube Laser'!E19="One Side",'Tube Laser'!J19*0.2,IF('Tube Laser'!E19="Both Sides",'Tube Laser'!J19*0.4,"0")) -> 0 | AF19: =IF('Tube Laser'!F19="Yes",'Tube Laser'!J19*0.1,0) -> 0 | AG19: =IF('Tube Laser'!G19>0,'Tube Laser'!J19*0.2,0) -> 0 | AH19: =IF('Tube Laser'!H19="Yes",'Tube Laser'!J19*0.1,0) -> 0 | AJ19: =IFERROR(VLOOKUP('FB Laser'!N20,'FB Data'!A12:E160,3,FALSE)*'FB Laser'!M20,0) -> 0 | AK19: =IF(AJ19>75,"full-time",IF(AJ19>32.999,"partial","")) | AL19: =IF(AK19="partial",'FB Laser'!E20/60*35*0.5,IF(AK19="full-time",'FB Laser'!E20/60*35,0)) -> 0 | AM19: =ROUND(IFERROR(AL19/'FB Laser'!B20,0),2) -> 0 | AO19: =IFERROR(VLOOKUP('Tube Laser'!P19,'TL Data'!A12:E1237,3,FALSE)*'Tube Laser'!O19,0) -> 0 | AP19: =IF(AO19>75,"full-time",IF(AO19>32.999,"partial","")) | AQ19: =IF(AP19="partial",'Tube Laser'!D19/60/60*35*'Tube Laser'!B19*0.5,IF(AP19="full-time",'Tube Laser'!D19/60/60*35*'Tube Laser'!B19,0)) -> 0 | AR19: =ROUND(IFERROR(AQ19/'Tube Laser'!B19,0),2) -> 0 | AT19: =IFERROR('FB Laser'!J20*'FB Laser'!B20,"") | AU19: =IFERROR('Tube Laser'!L19*'Tube Laser'!B19,"")
A20: ASH0635052 | B20: AL SHEET .063" 5052 | C20: 0.88 | D20: LBS/SQFT | E20: 4 | K20: {=INDIRECT(TEXT(MIN(IF(($L$9:$M$100<>"")*(COUNTIF($K$8:K19,$L$9:$M$100)=0),ROW($9:$100)*100+COLUMN($L:$M),7^8)),"R0C00"),)&""} | L20: =IF('FB Laser'!A21=0,"",'FB Laser'!A21) | M20: =IF('Tube Laser'!A20=0,"",'Tube Laser'!A20) | O20: {=INDIRECT(TEXT(MIN(IF(($P$9:$Q$100<>"")*(COUNTIF($O$8:O19,$P$9:$Q$100)=0),ROW($9:$100)*100+COLUMN($P:$Q),7^8)),"R0C00"),)&""} | P20: =IF('FB Laser'!F21="Yes",'FB Laser'!A21,"") | Q20: =IF('Tube Laser'!I20="Yes",'Tube Laser'!A20,"") | R20: =IFERROR(('FB Laser'!G21*'FB Laser'!B21),"") | S20: =IFERROR('FB Laser'!H21*'FB Laser'!B21,"") -> 0 | U20: =IFERROR(((((('Tube Laser'!D20)*'Tube Laser'!B20)/60)/60)*188.17)+(AE20*'Tube Laser'!B20),"") -> 0 | V20: =IFERROR(('Tube Laser'!N20*'Tube Laser'!B20)+(AE20*'Tube Laser'!B20)+(AF20*'Tube Laser'!B20)+(AG20*'Tube Laser'!B20)+('FB Data'!AH20*'Tube Laser'!B20),"") -> 0 | X20: =IFERROR(('Tube Laser'!D20*'Tube Laser'!B20)/60/60,"") -> 0 | AB20: 12 | AE20: =IF('Tube Laser'!E20="One Side",'Tube Laser'!J20*0.2,IF('Tube Laser'!E20="Both Sides",'Tube Laser'!J20*0.4,"0")) -> 0 | AF20: =IF('Tube Laser'!F20="Yes",'Tube Laser'!J20*0.1,0) -> 0 | AG20: =IF('Tube Laser'!G20>0,'Tube Laser'!J20*0.2,0) -> 0 | AH20: =IF('Tube Laser'!H20="Yes",'Tube Laser'!J20*0.1,0) -> 0 | AJ20: =IFERROR(VLOOKUP('FB Laser'!N21,'FB Data'!A13:E161,3,FALSE)*'FB Laser'!M21,0) -> 0 | AK20: =IF(AJ20>75,"full-time",IF(AJ20>32.999,"partial","")) | AL20: =IF(AK20="partial",'FB Laser'!E21/60*35*0.5,IF(AK20="full-time",'FB Laser'!E21/60*35,0)) -> 0 | AM20: =ROUND(IFERROR(AL20/'FB Laser'!B21,0),2) -> 0 | AO20: =IFERROR(VLOOKUP('Tube Laser'!P20,'TL Data'!A13:E1238,3,FALSE)*'Tube Laser'!O20,0) -> 0 | AP20: =IF(AO20>75,"full-time",IF(AO20>32.999,"partial","")) | AQ20: =IF(AP20="partial",'Tube Laser'!D20/60/60*35*'Tube Laser'!B20*0.5,IF(AP20="full-time",'Tube Laser'!D20/60/60*35*'Tube Laser'!B20,0)) -> 0 | AR20: =ROUND(IFERROR(AQ20/'Tube Laser'!B20,0),2) -> 0 | AT20: =IFERROR('FB Laser'!J21*'FB Laser'!B21,"") | AU20: =IFERROR('Tube Laser'!L20*'Tube Laser'!B20,"")
A21: ASH0636061 | B21: AL SHEET .063" 6061 | C21: 0.889 | D21: LBS/SQFT | E21: 4 | K21: {=INDIRECT(TEXT(MIN(IF(($L$9:$M$100<>"")*(COUNTIF($K$8:K20,$L$9:$M$100)=0),ROW($9:$100)*100+COLUMN($L:$M),7^8)),"R0C00"),)&""} | L21: =IF('FB Laser'!A22=0,"",'FB Laser'!A22) | M21: =IF('Tube Laser'!A21=0,"",'Tube Laser'!A21) | O21: {=INDIRECT(TEXT(MIN(IF(($P$9:$Q$100<>"")*(COUNTIF($O$8:O20,$P$9:$Q$100)=0),ROW($9:$100)*100+COLUMN($P:$Q),7^8)),"R0C00"),)&""} | P21: =IF('FB Laser'!F22="Yes",'FB Laser'!A22,"") | Q21: =IF('Tube Laser'!I21="Yes",'Tube Laser'!A21,"") | R21: =IFERROR(('FB Laser'!G22*'FB Laser'!B22),"") | S21: =IFERROR('FB Laser'!H22*'FB Laser'!B22,"") -> 0 | U21: =IFERROR(((((('Tube Laser'!D21)*'Tube Laser'!B21)/60)/60)*188.17)+(AE21*'Tube Laser'!B21),"") -> 0 | V21: =IFERROR(('Tube Laser'!N21*'Tube Laser'!B21)+(AE21*'Tube Laser'!B21)+(AF21*'Tube Laser'!B21)+(AG21*'Tube Laser'!B21)+('FB Data'!AH21*'Tube Laser'!B21),"") -> 0 | X21: =IFERROR(('Tube Laser'!D21*'Tube Laser'!B21)/60/60,"") -> 0 | AB21: 13 | AE21: =IF('Tube Laser'!E21="One Side",'Tube Laser'!J21*0.2,IF('Tube Laser'!E21="Both Sides",'Tube Laser'!J21*0.4,"0")) -> 0 | AF21: =IF('Tube Laser'!F21="Yes",'Tube Laser'!J21*0.1,0) -> 0 | AG21: =IF('Tube Laser'!G21>0,'Tube Laser'!J21*0.2,0) -> 0 | AH21: =IF('Tube Laser'!H21="Yes",'Tube Laser'!J21*0.1,0) -> 0 | AJ21: =IFERROR(VLOOKUP('FB Laser'!N22,'FB Data'!A14:E162,3,FALSE)*'FB Laser'!M22,0) -> 0 | AK21: =IF(AJ21>75,"full-time",IF(AJ21>32.999,"partial","")) | AL21: =IF(AK21="partial",'FB Laser'!E22/60*35*0.5,IF(AK21="full-time",'FB Laser'!E22/60*35,0)) -> 0 | AM21: =ROUND(IFERROR(AL21/'FB Laser'!B22,0),2) -> 0 | AO21: =IFERROR(VLOOKUP('Tube Laser'!P21,'TL Data'!A14:E1239,3,FALSE)*'Tube Laser'!O21,0) -> 0 | AP21: =IF(AO21>75,"full-time",IF(AO21>32.999,"partial","")) | AQ21: =IF(AP21="partial",'Tube Laser'!D21/60/60*35*'Tube Laser'!B21*0.5,IF(AP21="full-time",'Tube Laser'!D21/60/60*35*'Tube Laser'!B21,0)) -> 0 | AR21: =ROUND(IFERROR(AQ21/'Tube Laser'!B21,0),2) -> 0 | AT21: =IFERROR('FB Laser'!J22*'FB Laser'!B22,"") | AU21: =IFERROR('Tube Laser'!L21*'Tube Laser'!B21,"")
A22: ASH0803003 | B22: AL SHEET .080" 3003 | C22: 1.139 | D22: LBS/SQFT | E22: 4 | K22: {=INDIRECT(TEXT(MIN(IF(($L$9:$M$100<>"")*(COUNTIF($K$8:K21,$L$9:$M$100)=0),ROW($9:$100)*100+COLUMN($L:$M),7^8)),"R0C00"),)&""} | L22: =IF('FB Laser'!A23=0,"",'FB Laser'!A23) | M22: =IF('Tube Laser'!A22=0,"",'Tube Laser'!A22) | O22: {=INDIRECT(TEXT(MIN(IF(($P$9:$Q$100<>"")*(COUNTIF($O$8:O21,$P$9:$Q$100)=0),ROW($9:$100)*100+COLUMN($P:$Q),7^8)),"R0C00"),)&""} | P22: =IF('FB Laser'!F23="Yes",'FB Laser'!A23,"") | Q22: =IF('Tube Laser'!I22="Yes",'Tube Laser'!A22,"") | R22: =IFERROR(('FB Laser'!G23*'FB Laser'!B23),"") | S22: =IFERROR('FB Laser'!H23*'FB Laser'!B23,"") -> 0 | U22: =IFERROR(((((('Tube Laser'!D22)*'Tube Laser'!B22)/60)/60)*188.17)+(AE22*'Tube Laser'!B22),"") -> 0 | V22: =IFERROR(('Tube Laser'!N22*'Tube Laser'!B22)+(AE22*'Tube Laser'!B22)+(AF22*'Tube Laser'!B22)+(AG22*'Tube Laser'!B22)+('FB Data'!AH22*'Tube Laser'!B22),"") -> 0 | X22: =IFERROR(('Tube Laser'!D22*'Tube Laser'!B22)/60/60,"") -> 0 | AB22: 14 | AE22: =IF('Tube Laser'!E22="One Side",'Tube Laser'!J22*0.2,IF('Tube Laser'!E22="Both Sides",'Tube Laser'!J22*0.4,"0")) -> 0 | AF22: =IF('Tube Laser'!F22="Yes",'Tube Laser'!J22*0.1,0) -> 0 | AG22: =IF('Tube Laser'!G22>0,'Tube Laser'!J22*0.2,0) -> 0 | AH22: =IF('Tube Laser'!H22="Yes",'Tube Laser'!J22*0.1,0) -> 0 | AJ22: =IFERROR(VLOOKUP('FB Laser'!N23,'FB Data'!A15:E163,3,FALSE)*'FB Laser'!M23,0) -> 0 | AK22: =IF(AJ22>75,"full-time",IF(AJ22>32.999,"partial","")) | AL22: =IF(AK22="partial",'FB Laser'!E23/60*35*0.5,IF(AK22="full-time",'FB Laser'!E23/60*35,0)) -> 0 | AM22: =ROUND(IFERROR(AL22/'FB Laser'!B23,0),2) -> 0 | AO22: =IFERROR(VLOOKUP('Tube Laser'!P22,'TL Data'!A15:E1240,3,FALSE)*'Tube Laser'!O22,0) -> 0 | AP22: =IF(AO22>75,"full-time",IF(AO22>32.999,"partial","")) | AQ22: =IF(AP22="partial",'Tube Laser'!D22/60/60*35*'Tube Laser'!B22*0.5,IF(AP22="full-time",'Tube Laser'!D22/60/60*35*'Tube Laser'!B22,0)) -> 0 | AR22: =ROUND(IFERROR(AQ22/'Tube Laser'!B22,0),2) -> 0 | AT22: =IFERROR('FB Laser'!J23*'FB Laser'!B23,"") | AU22: =IFERROR('Tube Laser'!L22*'Tube Laser'!B22,"")
... A38: CPL12 | B38: CAST AL PL 1/2" | C38: 7.272 | D38: LBS/SQFT | E38: 5 | K38: {=INDIRECT(TEXT(MIN(IF(($L$9:$M$100<>"")*(COUNTIF($K$8:K37,$L$9:$M$100)=0),ROW($9:$100)*100+COLUMN($L:$M),7^8)),"R0C00"),)&""} | L38: =IF('FB Laser'!A39=0,"",'FB Laser'!A39) | M38: =IF('Tube Laser'!A38=0,"",'Tube Laser'!A38) | O38: {=INDIRECT(TEXT(MIN(IF(($P$9:$Q$100<>"")*(COUNTIF($O$8:O37,$P$9:$Q$100)=0),ROW($9:$100)*100+COLUMN($P:$Q),7^8)),"R0C00"),)&""} | P38: =IF('FB Laser'!F39="Yes",'FB Laser'!A39,"") | Q38: =IF('Tube Laser'!I38="Yes",'Tube Laser'!A38,"") | R38: =IFERROR(('FB Laser'!G39*'FB Laser'!B39),"") | S38: =IFERROR('FB Laser'!H39*'FB Laser'!B39,"") -> 0 | U38: =IFERROR(((((('Tube Laser'!D38)*'Tube Laser'!B38)/60)/60)*188.17)+(AE38*'Tube Laser'!B38),"") -> 0 | V38: =IFERROR(('Tube Laser'!N38*'Tube Laser'!B38)+(AE38*'Tube Laser'!B38)+(AF38*'Tube Laser'!B38)+(AG38*'Tube Laser'!B38)+('FB Data'!AH38*'Tube Laser'!B38),"") -> 0 | X38: =IFERROR(('Tube Laser'!D38*'Tube Laser'!B38)/60/60,"") -> 0 | AB38: 30 | AE38: =IF('Tube Laser'!E38="One Side",'Tube Laser'!J38*0.2,IF('Tube Laser'!E38="Both Sides",'Tube Laser'!J38*0.4,"0")) -> 0 | AF38: =IF('Tube Laser'!F38="Yes",'Tube Laser'!J38*0.1,0) -> 0 | AG38: =IF('Tube Laser'!G38>0,'Tube Laser'!J38*0.2,0) -> 0 | AH38: =IF('Tube Laser'!H38="Yes",'Tube Laser'!J38*0.1,0) -> 0 | AJ38: =IFERROR(VLOOKUP('FB Laser'!N39,'FB Data'!A31:E179,3,FALSE)*'FB Laser'!M39,0) -> 0 | AK38: =IF(AJ38>75,"full-time",IF(AJ38>32.999,"partial","")) | AL38: =IF(AK38="partial",'FB Laser'!E39/60*35*0.5,IF(AK38="full-time",'FB Laser'!E39/60*35,0)) -> 0 | AM38: =ROUND(IFERROR(AL38/'FB Laser'!B39,0),2) -> 0 | AO38: =IFERROR(VLOOKUP('Tube Laser'!P38,'TL Data'!A31:E1256,3,FALSE)*'Tube Laser'!O38,0) -> 0 | AP38: =IF(AO38>75,"full-time",IF(AO38>32.999,"partial","")) | AQ38: =IF(AP38="partial",'Tube Laser'!D38/60/60*35*'Tube Laser'!B38*0.5,IF(AP38="full-time",'Tube Laser'!D38/60/60*35*'Tube Laser'!B38,0)) -> 0 | AR38: =ROUND(IFERROR(AQ38/'Tube Laser'!B38,0),2) -> 0 | AT38: =IFERROR('FB Laser'!J39*'FB Laser'!B39,"") | AU38: =IFERROR('Tube Laser'!L38*'Tube Laser'!B38,"")
A39: CPL14 | B39: CAST AL PL 1/4" | C39: 3.636 | D39: LBS/SQFT | E39: 5 | K39: {=INDIRECT(TEXT(MIN(IF(($L$9:$M$100<>"")*(COUNTIF($K$8:K38,$L$9:$M$100)=0),ROW($9:$100)*100+COLUMN($L:$M),7^8)),"R0C00"),)&""} | L39: =IF('FB Laser'!A40=0,"",'FB Laser'!A40) | M39: =IF('Tube Laser'!A39=0,"",'Tube Laser'!A39) | O39: {=INDIRECT(TEXT(MIN(IF(($P$9:$Q$100<>"")*(COUNTIF($O$8:O38,$P$9:$Q$100)=0),ROW($9:$100)*100+COLUMN($P:$Q),7^8)),"R0C00"),)&""} | P39: =IF('FB Laser'!F40="Yes",'FB Laser'!A40,"") | Q39: =IF('Tube Laser'!I39="Yes",'Tube Laser'!A39,"") | R39: =IFERROR(('FB Laser'!G40*'FB Laser'!B40),"") | S39: =IFERROR('FB Laser'!H40*'FB Laser'!B40,"") -> 0 | U39: =IFERROR(((((('Tube Laser'!D39)*'Tube Laser'!B39)/60)/60)*188.17)+(AE39*'Tube Laser'!B39),"") -> 0 | V39: =IFERROR(('Tube Laser'!N39*'Tube Laser'!B39)+(AE39*'Tube Laser'!B39)+(AF39*'Tube Laser'!B39)+(AG39*'Tube Laser'!B39)+('FB Data'!AH39*'Tube Laser'!B39),"") -> 0 | X39: =IFERROR(('Tube Laser'!D39*'Tube Laser'!B39)/60/60,"") -> 0 | AE39: =IF('Tube Laser'!E39="One Side",'Tube Laser'!J39*0.2,IF('Tube Laser'!E39="Both Sides",'Tube Laser'!J39*0.4,"0")) -> 0 | AF39: =IF('Tube Laser'!F39="Yes",'Tube Laser'!J39*0.1,0) -> 0 | AG39: =IF('Tube Laser'!G39>0,'Tube Laser'!J39*0.2,0) -> 0 | AH39: =IF('Tube Laser'!H39="Yes",'Tube Laser'!J39*0.1,0) -> 0 | AJ39: =IFERROR(VLOOKUP('FB Laser'!N40,'FB Data'!A32:E180,3,FALSE)*'FB Laser'!M40,0) -> 0 | AK39: =IF(AJ39>75,"full-time",IF(AJ39>32.999,"partial","")) | AL39: =IF(AK39="partial",'FB Laser'!E40/60*35*0.5,IF(AK39="full-time",'FB Laser'!E40/60*35,0)) -> 0 | AM39: =ROUND(IFERROR(AL39/'FB Laser'!B40,0),2) -> 0 | AO39: =IFERROR(VLOOKUP('Tube Laser'!P39,'TL Data'!A32:E1257,3,FALSE)*'Tube Laser'!O39,0) -> 0 | AP39: =IF(AO39>75,"full-time",IF(AO39>32.999,"partial","")) | AQ39: =IF(AP39="partial",'Tube Laser'!D39/60/60*35*'Tube Laser'!B39*0.5,IF(AP39="full-time",'Tube Laser'!D39/60/60*35*'Tube Laser'!B39,0)) -> 0 | AR39: =ROUND(IFERROR(AQ39/'Tube Laser'!B39,0),2) -> 0 | AT39: =IFERROR('FB Laser'!J40*'FB Laser'!B40,"") | AU39: =IFERROR('Tube Laser'!L39*'Tube Laser'!B39,"")
A40: CPL34 | B40: CAST AL PL 3/4" | C40: 10.91 | D40: LBS/SQFT | E40: 5 | K40: {=INDIRECT(TEXT(MIN(IF(($L$9:$M$100<>"")*(COUNTIF($K$8:K39,$L$9:$M$100)=0),ROW($9:$100)*100+COLUMN($L:$M),7^8)),"R0C00"),)&""} | L40: =IF('FB Laser'!A41=0,"",'FB Laser'!A41) | M40: =IF('Tube Laser'!A40=0,"",'Tube Laser'!A40) | O40: {=INDIRECT(TEXT(MIN(IF(($P$9:$Q$100<>"")*(COUNTIF($O$8:O39,$P$9:$Q$100)=0),ROW($9:$100)*100+COLUMN($P:$Q),7^8)),"R0C00"),)&""} | P40: =IF('FB Laser'!F41="Yes",'FB Laser'!A41,"") | Q40: =IF('Tube Laser'!I40="Yes",'Tube Laser'!A40,"") | R40: =IFERROR(('FB Laser'!G41*'FB Laser'!B41),"") | S40: =IFERROR('FB Laser'!H41*'FB Laser'!B41,"") -> 0 | U40: =IFERROR(((((('Tube Laser'!D40)*'Tube Laser'!B40)/60)/60)*188.17)+(AE40*'Tube Laser'!B40),"") -> 0 | V40: =IFERROR(('Tube Laser'!N40*'Tube Laser'!B40)+(AE40*'Tube Laser'!B40)+(AF40*'Tube Laser'!B40)+(AG40*'Tube Laser'!B40)+('FB Data'!AH40*'Tube Laser'!B40),"") -> 0 | X40: =IFERROR(('Tube Laser'!D40*'Tube Laser'!B40)/60/60,"") -> 0 | AE40: =IF('Tube Laser'!E40="One Side",'Tube Laser'!J40*0.2,IF('Tube Laser'!E40="Both Sides",'Tube Laser'!J40*0.4,"0")) -> 0 | AF40: =IF('Tube Laser'!F40="Yes",'Tube Laser'!J40*0.1,0) -> 0 | AG40: =IF('Tube Laser'!G40>0,'Tube Laser'!J40*0.2,0) -> 0 | AH40: =IF('Tube Laser'!H40="Yes",'Tube Laser'!J40*0.1,0) -> 0 | AJ40: =IFERROR(VLOOKUP('FB Laser'!N41,'FB Data'!A33:E181,3,FALSE)*'FB Laser'!M41,0) -> 0 | AK40: =IF(AJ40>75,"full-time",IF(AJ40>32.999,"partial","")) | AL40: =IF(AK40="partial",'FB Laser'!E41/60*35*0.5,IF(AK40="full-time",'FB Laser'!E41/60*35,0)) -> 0 | AM40: =ROUND(IFERROR(AL40/'FB Laser'!B41,0),2) -> 0 | AO40: =IFERROR(VLOOKUP('Tube Laser'!P40,'TL Data'!A33:E1258,3,FALSE)*'Tube Laser'!O40,0) -> 0 | AP40: =IF(AO40>75,"full-time",IF(AO40>32.999,"partial","")) | AQ40: =IF(AP40="partial",'Tube Laser'!D40/60/60*35*'Tube Laser'!B40*0.5,IF(AP40="full-time",'Tube Laser'!D40/60/60*35*'Tube Laser'!B40,0)) -> 0 | AR40: =ROUND(IFERROR(AQ40/'Tube Laser'!B40,0),2) -> 0 | AT40: =IFERROR('FB Laser'!J41*'FB Laser'!B41,"") | AU40: =IFERROR('Tube Laser'!L40*'Tube Laser'!B40,"")
A41: CPL38 | B41: CAST AL PL 3/8" | C41: 5.454 | D41: LBS/SQFT | E41: 5 | K41: {=INDIRECT(TEXT(MIN(IF(($L$9:$M$100<>"")*(COUNTIF($K$8:K40,$L$9:$M$100)=0),ROW($9:$100)*100+COLUMN($L:$M),7^8)),"R0C00"),)&""} | L41: =IF('FB Laser'!A42=0,"",'FB Laser'!A42) | M41: =IF('Tube Laser'!A41=0,"",'Tube Laser'!A41) | O41: {=INDIRECT(TEXT(MIN(IF(($P$9:$Q$100<>"")*(COUNTIF($O$8:O40,$P$9:$Q$100)=0),ROW($9:$100)*100+COLUMN($P:$Q),7^8)),"R0C00"),)&""} | P41: =IF('FB Laser'!F42="Yes",'FB Laser'!A42,"") | Q41: =IF('Tube Laser'!I41="Yes",'Tube Laser'!A41,"") | R41: =IFERROR(('FB Laser'!G42*'FB Laser'!B42),"") | S41: =IFERROR('FB Laser'!H42*'FB Laser'!B42,"") -> 0 | U41: =IFERROR(((((('Tube Laser'!D41)*'Tube Laser'!B41)/60)/60)*188.17)+(AE41*'Tube Laser'!B41),"") -> 0 | V41: =IFERROR(('Tube Laser'!N41*'Tube Laser'!B41)+(AE41*'Tube Laser'!B41)+(AF41*'Tube Laser'!B41)+(AG41*'Tube Laser'!B41)+('FB Data'!AH41*'Tube Laser'!B41),"") -> 0 | X41: =IFERROR(('Tube Laser'!D41*'Tube Laser'!B41)/60/60,"") -> 0 | AE41: =IF('Tube Laser'!E41="One Side",'Tube Laser'!J41*0.2,IF('Tube Laser'!E41="Both Sides",'Tube Laser'!J41*0.4,"0")) -> 0 | AF41: =IF('Tube Laser'!F41="Yes",'Tube Laser'!J41*0.1,0) -> 0 | AG41: =IF('Tube Laser'!G41>0,'Tube Laser'!J41*0.2,0) -> 0 | AH41: =IF('Tube Laser'!H41="Yes",'Tube Laser'!J41*0.1,0) -> 0 | AJ41: =IFERROR(VLOOKUP('FB Laser'!N42,'FB Data'!A34:E182,3,FALSE)*'FB Laser'!M42,0) -> 0 | AK41: =IF(AJ41>75,"full-time",IF(AJ41>32.999,"partial","")) | AL41: =IF(AK41="partial",'FB Laser'!E42/60*35*0.5,IF(AK41="full-time",'FB Laser'!E42/60*35,0)) -> 0 | AM41: =ROUND(IFERROR(AL41/'FB Laser'!B42,0),2) -> 0 | AO41: =IFERROR(VLOOKUP('Tube Laser'!P41,'TL Data'!A34:E1259,3,FALSE)*'Tube Laser'!O41,0) -> 0 | AP41: =IF(AO41>75,"full-time",IF(AO41>32.999,"partial","")) | AQ41: =IF(AP41="partial",'Tube Laser'!D41/60/60*35*'Tube Laser'!B41*0.5,IF(AP41="full-time",'Tube Laser'!D41/60/60*35*'Tube Laser'!B41,0)) -> 0 | AR41: =ROUND(IFERROR(AQ41/'Tube Laser'!B41,0),2) -> 0 | AT41: =IFERROR('FB Laser'!J42*'FB Laser'!B42,"") | AU41: =IFERROR('Tube Laser'!L41*'Tube Laser'!B41,"")
A42: CPL58 | B42: CAST AL PL 5/8" | C42: 9.09 | D42: LBS/SQFT | E42: 5 | K42: {=INDIRECT(TEXT(MIN(IF(($L$9:$M$100<>"")*(COUNTIF($K$8:K41,$L$9:$M$100)=0),ROW($9:$100)*100+COLUMN($L:$M),7^8)),"R0C00"),)&""} | L42: =IF('FB Laser'!A43=0,"",'FB Laser'!A43) | M42: =IF('Tube Laser'!A42=0,"",'Tube Laser'!A42) | O42: {=INDIRECT(TEXT(MIN(IF(($P$9:$Q$100<>"")*(COUNTIF($O$8:O41,$P$9:$Q$100)=0),ROW($9:$100)*100+COLUMN($P:$Q),7^8)),"R0C00"),)&""} | P42: =IF('FB Laser'!F43="Yes",'FB Laser'!A43,"") | Q42: =IF('Tube Laser'!I42="Yes",'Tube Laser'!A42,"") | R42: =IFERROR(('FB Laser'!G43*'FB Laser'!B43),"") | S42: =IFERROR('FB Laser'!H43*'FB Laser'!B43,"") -> 0 | U42: =IFERROR(((((('Tube Laser'!D42)*'Tube Laser'!B42)/60)/60)*188.17)+(AE42*'Tube Laser'!B42),"") -> 0 | V42: =IFERROR(('Tube Laser'!N42*'Tube Laser'!B42)+(AE42*'Tube Laser'!B42)+(AF42*'Tube Laser'!B42)+(AG42*'Tube Laser'!B42)+('FB Data'!AH42*'Tube Laser'!B42),"") -> 0 | X42: =IFERROR(('Tube Laser'!D42*'Tube Laser'!B42)/60/60,"") -> 0 | AE42: =IF('Tube Laser'!E42="One Side",'Tube Laser'!J42*0.2,IF('Tube Laser'!E42="Both Sides",'Tube Laser'!J42*0.4,"0")) -> 0 | AF42: =IF('Tube Laser'!F42="Yes",'Tube Laser'!J42*0.1,0) -> 0 | AG42: =IF('Tube Laser'!G42>0,'Tube Laser'!J42*0.2,0) -> 0 | AH42: =IF('Tube Laser'!H42="Yes",'Tube Laser'!J42*0.1,0) -> 0 | AJ42: =IFERROR(VLOOKUP('FB Laser'!N43,'FB Data'!A35:E183,3,FALSE)*'FB Laser'!M43,0) -> 0 | AK42: =IF(AJ42>75,"full-time",IF(AJ42>32.999,"partial","")) | AL42: =IF(AK42="partial",'FB Laser'!E43/60*35*0.5,IF(AK42="full-time",'FB Laser'!E43/60*35,0)) -> 0 | AM42: =ROUND(IFERROR(AL42/'FB Laser'!B43,0),2) -> 0 | AO42: =IFERROR(VLOOKUP('Tube Laser'!P42,'TL Data'!A35:E1260,3,FALSE)*'Tube Laser'!O42,0) -> 0 | AP42: =IF(AO42>75,"full-time",IF(AO42>32.999,"partial","")) | AQ42: =IF(AP42="partial",'Tube Laser'!D42/60/60*35*'Tube Laser'!B42*0.5,IF(AP42="full-time",'Tube Laser'!D42/60/60*35*'Tube Laser'!B42,0)) -> 0 | AR42: =ROUND(IFERROR(AQ42/'Tube Laser'!B42,0),2) -> 0 | AT42: =IFERROR('FB Laser'!J43*'FB Laser'!B43,"") | AU42: =IFERROR('Tube Laser'!L42*'Tube Laser'!B42,"")
A43: CPL78 | B43: CAST AL PL 7/8" | C43: 12.73 | D43: LBS/SQFT | E43: 5 | K43: {=INDIRECT(TEXT(MIN(IF(($L$9:$M$100<>"")*(COUNTIF($K$8:K42,$L$9:$M$100)=0),ROW($9:$100)*100+COLUMN($L:$M),7^8)),"R0C00"),)&""} | L43: =IF('FB Laser'!A44=0,"",'FB Laser'!A44) | M43: =IF('Tube Laser'!A43=0,"",'Tube Laser'!A43) | O43: {=INDIRECT(TEXT(MIN(IF(($P$9:$Q$100<>"")*(COUNTIF($O$8:O42,$P$9:$Q$100)=0),ROW($9:$100)*100+COLUMN($P:$Q),7^8)),"R0C00"),)&""} | P43: =IF('FB Laser'!F44="Yes",'FB Laser'!A44,"") | Q43: =IF('Tube Laser'!I43="Yes",'Tube Laser'!A43,"") | R43: =IFERROR(('FB Laser'!G44*'FB Laser'!B44),"") | S43: =IFERROR('FB Laser'!H44*'FB Laser'!B44,"") -> 0 | U43: =IFERROR(((((('Tube Laser'!D43)*'Tube Laser'!B43)/60)/60)*188.17)+(AE43*'Tube Laser'!B43),"") -> 0 | V43: =IFERROR(('Tube Laser'!N43*'Tube Laser'!B43)+(AE43*'Tube Laser'!B43)+(AF43*'Tube Laser'!B43)+(AG43*'Tube Laser'!B43)+('FB Data'!AH43*'Tube Laser'!B43),"") -> 0 | X43: =IFERROR(('Tube Laser'!D43*'Tube Laser'!B43)/60/60,"") -> 0 | AE43: =IF('Tube Laser'!E43="One Side",'Tube Laser'!J43*0.2,IF('Tube Laser'!E43="Both Sides",'Tube Laser'!J43*0.4,"0")) -> 0 | AF43: =IF('Tube Laser'!F43="Yes",'Tube Laser'!J43*0.1,0) -> 0 | AG43: =IF('Tube Laser'!G43>0,'Tube Laser'!J43*0.2,0) -> 0 | AH43: =IF('Tube Laser'!H43="Yes",'Tube Laser'!J43*0.1,0) -> 0 | AJ43: =IFERROR(VLOOKUP('FB Laser'!N44,'FB Data'!A36:E184,3,FALSE)*'FB Laser'!M44,0) -> 0 | AK43: =IF(AJ43>75,"full-time",IF(AJ43>32.999,"partial","")) | AL43: =IF(AK43="partial",'FB Laser'!E44/60*35*0.5,IF(AK43="full-time",'FB Laser'!E44/60*35,0)) -> 0 | AM43: =ROUND(IFERROR(AL43/'FB Laser'!B44,0),2) -> 0 | AO43: =IFERROR(VLOOKUP('Tube Laser'!P43,'TL Data'!A36:E1261,3,FALSE)*'Tube Laser'!O43,0) -> 0 | AP43: =IF(AO43>75,"full-time",IF(AO43>32.999,"partial","")) | AQ43: =IF(AP43="partial",'Tube Laser'!D43/60/60*35*'Tube Laser'!B43*0.5,IF(AP43="full-time",'Tube Laser'!D43/60/60*35*'Tube Laser'!B43,0)) -> 0 | AR43: =ROUND(IFERROR(AQ43/'Tube Laser'!B43,0),2) -> 0 | AT43: =IFERROR('FB Laser'!J44*'FB Laser'!B44,"") | AU43: =IFERROR('Tube Laser'!L43*'Tube Laser'!B43,"")
A44: CRSH10GA | B44: CR SHEET 10GA | C44: 5.625 | D44: LBS/SQFT | E44: 1.75 | K44: {=INDIRECT(TEXT(MIN(IF(($L$9:$M$100<>"")*(COUNTIF($K$8:K43,$L$9:$M$100)=0),ROW($9:$100)*100+COLUMN($L:$M),7^8)),"R0C00"),)&""} | L44: =IF('FB Laser'!A45=0,"",'FB Laser'!A45) | M44: =IF('Tube Laser'!A44=0,"",'Tube Laser'!A44) | O44: {=INDIRECT(TEXT(MIN(IF(($P$9:$Q$100<>"")*(COUNTIF($O$8:O43,$P$9:$Q$100)=0),ROW($9:$100)*100+COLUMN($P:$Q),7^8)),"R0C00"),)&""} | P44: =IF('FB Laser'!F45="Yes",'FB Laser'!A45,"") | Q44: =IF('Tube Laser'!I44="Yes",'Tube Laser'!A44,"") | R44: =IFERROR(('FB Laser'!G45*'FB Laser'!B45),"") | S44: =IFERROR('FB Laser'!H45*'FB Laser'!B45,"") -> 0 | U44: =IFERROR(((((('Tube Laser'!D44)*'Tube Laser'!B44)/60)/60)*188.17)+(AE44*'Tube Laser'!B44),"") -> 0 | V44: =IFERROR(('Tube Laser'!N44*'Tube Laser'!B44)+(AE44*'Tube Laser'!B44)+(AF44*'Tube Laser'!B44)+(AG44*'Tube Laser'!B44)+('FB Data'!AH44*'Tube Laser'!B44),"") -> 0 | X44: =IFERROR(('Tube Laser'!D44*'Tube Laser'!B44)/60/60,"") -> 0 | AE44: =IF('Tube Laser'!E44="One Side",'Tube Laser'!J44*0.2,IF('Tube Laser'!E44="Both Sides",'Tube Laser'!J44*0.4,"0")) -> 0 | AF44: =IF('Tube Laser'!F44="Yes",'Tube Laser'!J44*0.1,0) -> 0 | AG44: =IF('Tube Laser'!G44>0,'Tube Laser'!J44*0.2,0) -> 0 | AH44: =IF('Tube Laser'!H44="Yes",'Tube Laser'!J44*0.1,0) -> 0 | AJ44: =IFERROR(VLOOKUP('FB Laser'!N45,'FB Data'!A37:E185,3,FALSE)*'FB Laser'!M45,0) -> 0 | AK44: =IF(AJ44>75,"full-time",IF(AJ44>32.999,"partial","")) | AL44: =IF(AK44="partial",'FB Laser'!E45/60*35*0.5,IF(AK44="full-time",'FB Laser'!E45/60*35,0)) -> 0 | AM44: =ROUND(IFERROR(AL44/'FB Laser'!B45,0),2) -> 0 | AO44: =IFERROR(VLOOKUP('Tube Laser'!P44,'TL Data'!A37:E1262,3,FALSE)*'Tube Laser'!O44,0) -> 0 | AP44: =IF(AO44>75,"full-time",IF(AO44>32.999,"partial","")) | AQ44: =IF(AP44="partial",'Tube Laser'!D44/60/60*35*'Tube Laser'!B44*0.5,IF(AP44="full-time",'Tube Laser'!D44/60/60*35*'Tube Laser'!B44,0)) -> 0 | AR44: =ROUND(IFERROR(AQ44/'Tube Laser'!B44,0),2) -> 0 | AT44: =IFERROR('FB Laser'!J45*'FB Laser'!B45,"") | AU44: =IFERROR('Tube Laser'!L44*'Tube Laser'!B44,"")
A45: CRSH11GA | B45: CR SHEET 11GA | C45: 5 | D45: LBS/SQFT | E45: 1.75 | K45: {=INDIRECT(TEXT(MIN(IF(($L$9:$M$100<>"")*(COUNTIF($K$8:K44,$L$9:$M$100)=0),ROW($9:$100)*100+COLUMN($L:$M),7^8)),"R0C00"),)&""} | L45: =IF('FB Laser'!A46=0,"",'FB Laser'!A46) | M45: =IF('Tube Laser'!A45=0,"",'Tube Laser'!A45) | O45: {=INDIRECT(TEXT(MIN(IF(($P$9:$Q$100<>"")*(COUNTIF($O$8:O44,$P$9:$Q$100)=0),ROW($9:$100)*100+COLUMN($P:$Q),7^8)),"R0C00"),)&""} | P45: =IF('FB Laser'!F46="Yes",'FB Laser'!A46,"") | Q45: =IF('Tube Laser'!I45="Yes",'Tube Laser'!A45,"") | R45: =IFERROR(('FB Laser'!G46*'FB Laser'!B46),"") | S45: =IFERROR('FB Laser'!H46*'FB Laser'!B46,"") -> 0 | U45: =IFERROR(((((('Tube Laser'!D45)*'Tube Laser'!B45)/60)/60)*188.17)+(AE45*'Tube Laser'!B45),"") -> 0 | V45: =IFERROR(('Tube Laser'!N45*'Tube Laser'!B45)+(AE45*'Tube Laser'!B45)+(AF45*'Tube Laser'!B45)+(AG45*'Tube Laser'!B45)+('FB Data'!AH45*'Tube Laser'!B45),"") -> 0 | X45: =IFERROR(('Tube Laser'!D45*'Tube Laser'!B45)/60/60,"") -> 0 | AE45: =IF('Tube Laser'!E45="One Side",'Tube Laser'!J45*0.2,IF('Tube Laser'!E45="Both Sides",'Tube Laser'!J45*0.4,"0")) -> 0 | AF45: =IF('Tube Laser'!F45="Yes",'Tube Laser'!J45*0.1,0) -> 0 | AG45: =IF('Tube Laser'!G45>0,'Tube Laser'!J45*0.2,0) -> 0 | AH45: =IF('Tube Laser'!H45="Yes",'Tube Laser'!J45*0.1,0) -> 0 | AJ45: =IFERROR(VLOOKUP('FB Laser'!N46,'FB Data'!A38:E186,3,FALSE)*'FB Laser'!M46,0) -> 0 | AK45: =IF(AJ45>75,"full-time",IF(AJ45>32.999,"partial","")) | AL45: =IF(AK45="partial",'FB Laser'!E46/60*35*0.5,IF(AK45="full-time",'FB Laser'!E46/60*35,0)) -> 0 | AM45: =ROUND(IFERROR(AL45/'FB Laser'!B46,0),2) -> 0 | AO45: =IFERROR(VLOOKUP('Tube Laser'!P45,'TL Data'!A38:E1263,3,FALSE)*'Tube Laser'!O45,0) -> 0 | AP45: =IF(AO45>75,"full-time",IF(AO45>32.999,"partial","")) | AQ45: =IF(AP45="partial",'Tube Laser'!D45/60/60*35*'Tube Laser'!B45*0.5,IF(AP45="full-time",'Tube Laser'!D45/60/60*35*'Tube Laser'!B45,0)) -> 0 | AR45: =ROUND(IFERROR(AQ45/'Tube Laser'!B45,0),2) -> 0 | AT45: =IFERROR('FB Laser'!J46*'FB Laser'!B46,"") | AU45: =IFERROR('Tube Laser'!L45*'Tube Laser'!B45,"")
A46: CRSH12GA | B46: CR SHEET 12GA | C46: 4.375 | D46: LBS/SQFT | E46: 1.75 | K46: {=INDIRECT(TEXT(MIN(IF(($L$9:$M$100<>"")*(COUNTIF($K$8:K45,$L$9:$M$100)=0),ROW($9:$100)*100+COLUMN($L:$M),7^8)),"R0C00"),)&""} | L46: =IF('FB Laser'!A47=0,"",'FB Laser'!A47) | M46: =IF('Tube Laser'!A46=0,"",'Tube Laser'!A46) | O46: {=INDIRECT(TEXT(MIN(IF(($P$9:$Q$100<>"")*(COUNTIF($O$8:O45,$P$9:$Q$100)=0),ROW($9:$100)*100+COLUMN($P:$Q),7^8)),"R0C00"),)&""} | P46: =IF('FB Laser'!F47="Yes",'FB Laser'!A47,"") | Q46: =IF('Tube Laser'!I46="Yes",'Tube Laser'!A46,"") | R46: =IFERROR(('FB Laser'!G47*'FB Laser'!B47),"") | S46: =IFERROR('FB Laser'!H47*'FB Laser'!B47,"") -> 0 | U46: =IFERROR(((((('Tube Laser'!D46)*'Tube Laser'!B46)/60)/60)*188.17)+(AE46*'Tube Laser'!B46),"") -> 0 | V46: =IFERROR(('Tube Laser'!N46*'Tube Laser'!B46)+(AE46*'Tube Laser'!B46)+(AF46*'Tube Laser'!B46)+(AG46*'Tube Laser'!B46)+('FB Data'!AH46*'Tube Laser'!B46),"") -> 0 | X46: =IFERROR(('Tube Laser'!D46*'Tube Laser'!B46)/60/60,"") -> 0 | AE46: =IF('Tube Laser'!E46="One Side",'Tube Laser'!J46*0.2,IF('Tube Laser'!E46="Both Sides",'Tube Laser'!J46*0.4,"0")) -> 0 | AF46: =IF('Tube Laser'!F46="Yes",'Tube Laser'!J46*0.1,0) -> 0 | AG46: =IF('Tube Laser'!G46>0,'Tube Laser'!J46*0.2,0) -> 0 | AH46: =IF('Tube Laser'!H46="Yes",'Tube Laser'!J46*0.1,0) -> 0 | AJ46: =IFERROR(VLOOKUP('FB Laser'!N47,'FB Data'!A39:E187,3,FALSE)*'FB Laser'!M47,0) -> 0 | AK46: =IF(AJ46>75,"full-time",IF(AJ46>32.999,"partial","")) | AL46: =IF(AK46="partial",'FB Laser'!E47/60*35*0.5,IF(AK46="full-time",'FB Laser'!E47/60*35,0)) -> 0 | AM46: =ROUND(IFERROR(AL46/'FB Laser'!B47,0),2) -> 0 | AO46: =IFERROR(VLOOKUP('Tube Laser'!P46,'TL Data'!A39:E1264,3,FALSE)*'Tube Laser'!O46,0) -> 0 | AP46: =IF(AO46>75,"full-time",IF(AO46>32.999,"partial","")) | AQ46: =IF(AP46="partial",'Tube Laser'!D46/60/60*35*'Tube Laser'!B46*0.5,IF(AP46="full-time",'Tube Laser'!D46/60/60*35*'Tube Laser'!B46,0)) -> 0 | AR46: =ROUND(IFERROR(AQ46/'Tube Laser'!B46,0),2) -> 0 | AT46: =IFERROR('FB Laser'!J47*'FB Laser'!B47,"") | AU46: =IFERROR('Tube Laser'!L46*'Tube Laser'!B46,"")
A47: CRSH14GA | B47: CR SHEET 14GA | C47: 3.125 | D47: LBS/SQFT | E47: 1.75 | K47: {=INDIRECT(TEXT(MIN(IF(($L$9:$M$100<>"")*(COUNTIF($K$8:K46,$L$9:$M$100)=0),ROW($9:$100)*100+COLUMN($L:$M),7^8)),"R0C00"),)&""} | L47: =IF('FB Laser'!A48=0,"",'FB Laser'!A48) | M47: =IF('Tube Laser'!A47=0,"",'Tube Laser'!A47) | O47: {=INDIRECT(TEXT(MIN(IF(($P$9:$Q$100<>"")*(COUNTIF($O$8:O46,$P$9:$Q$100)=0),ROW($9:$100)*100+COLUMN($P:$Q),7^8)),"R0C00"),)&""} | P47: =IF('FB Laser'!F48="Yes",'FB Laser'!A48,"") | Q47: =IF('Tube Laser'!I47="Yes",'Tube Laser'!A47,"") | R47: =IFERROR(('FB Laser'!G48*'FB Laser'!B48),"") | S47: =IFERROR('FB Laser'!H48*'FB Laser'!B48,"") -> 0 | U47: =IFERROR(((((('Tube Laser'!D47)*'Tube Laser'!B47)/60)/60)*188.17)+(AE47*'Tube Laser'!B47),"") -> 0 | V47: =IFERROR(('Tube Laser'!N47*'Tube Laser'!B47)+(AE47*'Tube Laser'!B47)+(AF47*'Tube Laser'!B47)+(AG47*'Tube Laser'!B47)+('FB Data'!AH47*'Tube Laser'!B47),"") -> 0 | X47: =IFERROR(('Tube Laser'!D47*'Tube Laser'!B47)/60/60,"") -> 0 | AE47: =IF('Tube Laser'!E47="One Side",'Tube Laser'!J47*0.2,IF('Tube Laser'!E47="Both Sides",'Tube Laser'!J47*0.4,"0")) -> 0 | AF47: =IF('Tube Laser'!F47="Yes",'Tube Laser'!J47*0.1,0) -> 0 | AG47: =IF('Tube Laser'!G47>0,'Tube Laser'!J47*0.2,0) -> 0 | AH47: =IF('Tube Laser'!H47="Yes",'Tube Laser'!J47*0.1,0) -> 0 | AJ47: =IFERROR(VLOOKUP('FB Laser'!N48,'FB Data'!A40:E188,3,FALSE)*'FB Laser'!M48,0) -> 0 | AK47: =IF(AJ47>75,"full-time",IF(AJ47>32.999,"partial","")) | AL47: =IF(AK47="partial",'FB Laser'!E48/60*35*0.5,IF(AK47="full-time",'FB Laser'!E48/60*35,0)) -> 0 | AM47: =ROUND(IFERROR(AL47/'FB Laser'!B48,0),2) -> 0 | AO47: =IFERROR(VLOOKUP('Tube Laser'!P47,'TL Data'!A40:E1265,3,FALSE)*'Tube Laser'!O47,0) -> 0 | AP47: =IF(AO47>75,"full-time",IF(AO47>32.999,"partial","")) | AQ47: =IF(AP47="partial",'Tube Laser'!D47/60/60*35*'Tube Laser'!B47*0.5,IF(AP47="full-time",'Tube Laser'!D47/60/60*35*'Tube Laser'!B47,0)) -> 0 | AR47: =ROUND(IFERROR(AQ47/'Tube Laser'!B47,0),2) -> 0 | AT47: =IFERROR('FB Laser'!J48*'FB Laser'!B48,"") | AU47: =IFERROR('Tube Laser'!L47*'Tube Laser'!B47,"")
A48: CRSH16GA | B48: CR SHEET 16GA | C48: 2.5 | D48: LBS/SQFT | E48: 1.75 | K48: {=INDIRECT(TEXT(MIN(IF(($L$9:$M$100<>"")*(COUNTIF($K$8:K47,$L$9:$M$100)=0),ROW($9:$100)*100+COLUMN($L:$M),7^8)),"R0C00"),)&""} | L48: =IF('FB Laser'!A49=0,"",'FB Laser'!A49) | M48: =IF('Tube Laser'!A48=0,"",'Tube Laser'!A48) | O48: {=INDIRECT(TEXT(MIN(IF(($P$9:$Q$100<>"")*(COUNTIF($O$8:O47,$P$9:$Q$100)=0),ROW($9:$100)*100+COLUMN($P:$Q),7^8)),"R0C00"),)&""} | P48: =IF('FB Laser'!F49="Yes",'FB Laser'!A49,"") | Q48: =IF('Tube Laser'!I48="Yes",'Tube Laser'!A48,"") | R48: =IFERROR(('FB Laser'!G49*'FB Laser'!B49),"") | S48: =IFERROR('FB Laser'!H49*'FB Laser'!B49,"") -> 0 | U48: =IFERROR(((((('Tube Laser'!D48)*'Tube Laser'!B48)/60)/60)*188.17)+(AE48*'Tube Laser'!B48),"") -> 0 | V48: =IFERROR(('Tube Laser'!N48*'Tube Laser'!B48)+(AE48*'Tube Laser'!B48)+(AF48*'Tube Laser'!B48)+(AG48*'Tube Laser'!B48)+('FB Data'!AH48*'Tube Laser'!B48),"") -> 0 | X48: =IFERROR(('Tube Laser'!D48*'Tube Laser'!B48)/60/60,"") -> 0 | AE48: =IF('Tube Laser'!E48="One Side",'Tube Laser'!J48*0.2,IF('Tube Laser'!E48="Both Sides",'Tube Laser'!J48*0.4,"0")) -> 0 | AF48: =IF('Tube Laser'!F48="Yes",'Tube Laser'!J48*0.1,0) -> 0 | AG48: =IF('Tube Laser'!G48>0,'Tube Laser'!J48*0.2,0) -> 0 | AH48: =IF('Tube Laser'!H48="Yes",'Tube Laser'!J48*0.1,0) -> 0 | AJ48: =IFERROR(VLOOKUP('FB Laser'!N49,'FB Data'!A41:E189,3,FALSE)*'FB Laser'!M49,0) -> 0 | AK48: =IF(AJ48>75,"full-time",IF(AJ48>32.999,"partial","")) | AL48: =IF(AK48="partial",'FB Laser'!E49/60*35*0.5,IF(AK48="full-time",'FB Laser'!E49/60*35,0)) -> 0 | AM48: =ROUND(IFERROR(AL48/'FB Laser'!B49,0),2) -> 0 | AO48: =IFERROR(VLOOKUP('Tube Laser'!P48,'TL Data'!A41:E1266,3,FALSE)*'Tube Laser'!O48,0) -> 0 | AP48: =IF(AO48>75,"full-time",IF(AO48>32.999,"partial","")) | AQ48: =IF(AP48="partial",'Tube Laser'!D48/60/60*35*'Tube Laser'!B48*0.5,IF(AP48="full-time",'Tube Laser'!D48/60/60*35*'Tube Laser'!B48,0)) -> 0 | AR48: =ROUND(IFERROR(AQ48/'Tube Laser'!B48,0),2) -> 0 | AT48: =IFERROR('FB Laser'!J49*'FB Laser'!B49,"") | AU48: =IFERROR('Tube Laser'!L48*'Tube Laser'!B48,"")
A49: CRSH18GA | B49: CR SHEET 18GA | C49: 2 | D49: LBS/SQFT | E49: 1.75 | K49: {=INDIRECT(TEXT(MIN(IF(($L$9:$M$100<>"")*(COUNTIF($K$8:K48,$L$9:$M$100)=0),ROW($9:$100)*100+COLUMN($L:$M),7^8)),"R0C00"),)&""} | L49: =IF('FB Laser'!A50=0,"",'FB Laser'!A50) | M49: =IF('Tube Laser'!A49=0,"",'Tube Laser'!A49) | O49: {=INDIRECT(TEXT(MIN(IF(($P$9:$Q$100<>"")*(COUNTIF($O$8:O48,$P$9:$Q$100)=0),ROW($9:$100)*100+COLUMN($P:$Q),7^8)),"R0C00"),)&""} | P49: =IF('FB Laser'!F50="Yes",'FB Laser'!A50,"") | Q49: =IF('Tube Laser'!I49="Yes",'Tube Laser'!A49,"") | R49: =IFERROR(('FB Laser'!G50*'FB Laser'!B50),"") | S49: =IFERROR('FB Laser'!H50*'FB Laser'!B50,"") -> 0 | U49: =IFERROR(((((('Tube Laser'!D49)*'Tube Laser'!B49)/60)/60)*188.17)+(AE49*'Tube Laser'!B49),"") -> 0 | V49: =IFERROR(('Tube Laser'!N49*'Tube Laser'!B49)+(AE49*'Tube Laser'!B49)+(AF49*'Tube Laser'!B49)+(AG49*'Tube Laser'!B49)+('FB Data'!AH49*'Tube Laser'!B49),"") -> 0 | X49: =IFERROR(('Tube Laser'!D49*'Tube Laser'!B49)/60/60,"") -> 0 | AE49: =IF('Tube Laser'!E49="One Side",'Tube Laser'!J49*0.2,IF('Tube Laser'!E49="Both Sides",'Tube Laser'!J49*0.4,"0")) -> 0 | AF49: =IF('Tube Laser'!F49="Yes",'Tube Laser'!J49*0.1,0) -> 0 | AG49: =IF('Tube Laser'!G49>0,'Tube Laser'!J49*0.2,0) -> 0 | AH49: =IF('Tube Laser'!H49="Yes",'Tube Laser'!J49*0.1,0) -> 0 | AJ49: =IFERROR(VLOOKUP('FB Laser'!N50,'FB Data'!A42:E190,3,FALSE)*'FB Laser'!M50,0) -> 0 | AK49: =IF(AJ49>75,"full-time",IF(AJ49>32.999,"partial","")) | AL49: =IF(AK49="partial",'FB Laser'!E50/60*35*0.5,IF(AK49="full-time",'FB Laser'!E50/60*35,0)) -> 0 | AM49: =ROUND(IFERROR(AL49/'FB Laser'!B50,0),2) -> 0 | AO49: =IFERROR(VLOOKUP('Tube Laser'!P49,'TL Data'!A42:E1267,3,FALSE)*'Tube Laser'!O49,0) -> 0 | AP49: =IF(AO49>75,"full-time",IF(AO49>32.999,"partial","")) | AQ49: =IF(AP49="partial",'Tube Laser'!D49/60/60*35*'Tube Laser'!B49*0.5,IF(AP49="full-time",'Tube Laser'!D49/60/60*35*'Tube Laser'!B49,0)) -> 0 | AR49: =ROUND(IFERROR(AQ49/'Tube Laser'!B49,0),2) -> 0 | AT49: =IFERROR('FB Laser'!J50*'FB Laser'!B50,"") | AU49: =IFERROR('Tube Laser'!L49*'Tube Laser'!B49,"")
A50: CRSH20GA | B50: CR SHEET 20GA | C50: 1.5 | D50: LBS/SQFT | E50: 1.75 | K50: {=INDIRECT(TEXT(MIN(IF(($L$9:$M$100<>"")*(COUNTIF($K$8:K49,$L$9:$M$100)=0),ROW($9:$100)*100+COLUMN($L:$M),7^8)),"R0C00"),)&""} | L50: =IF('FB Laser'!A51=0,"",'FB Laser'!A51) | M50: =IF('Tube Laser'!A50=0,"",'Tube Laser'!A50) | O50: {=INDIRECT(TEXT(MIN(IF(($P$9:$Q$100<>"")*(COUNTIF($O$8:O49,$P$9:$Q$100)=0),ROW($9:$100)*100+COLUMN($P:$Q),7^8)),"R0C00"),)&""} | P50: =IF('FB Laser'!F51="Yes",'FB Laser'!A51,"") | Q50: =IF('Tube Laser'!I50="Yes",'Tube Laser'!A50,"") | R50: =IFERROR(('FB Laser'!G51*'FB Laser'!B51),"") | S50: =IFERROR('FB Laser'!H51*'FB Laser'!B51,"") -> 0 | U50: =IFERROR(((((('Tube Laser'!D50)*'Tube Laser'!B50)/60)/60)*188.17)+(AE50*'Tube Laser'!B50),"") -> 0 | V50: =IFERROR(('Tube Laser'!N50*'Tube Laser'!B50)+(AE50*'Tube Laser'!B50)+(AF50*'Tube Laser'!B50)+(AG50*'Tube Laser'!B50)+('FB Data'!AH50*'Tube Laser'!B50),"") -> 0 | X50: =IFERROR(('Tube Laser'!D50*'Tube Laser'!B50)/60/60,"") -> 0 | AE50: =IF('Tube Laser'!E50="One Side",'Tube Laser'!J50*0.2,IF('Tube Laser'!E50="Both Sides",'Tube Laser'!J50*0.4,"0")) -> 0 | AF50: =IF('Tube Laser'!F50="Yes",'Tube Laser'!J50*0.1,0) -> 0 | AG50: =IF('Tube Laser'!G50>0,'Tube Laser'!J50*0.2,0) -> 0 | AH50: =IF('Tube Laser'!H50="Yes",'Tube Laser'!J50*0.1,0) -> 0 | AJ50: =IFERROR(VLOOKUP('FB Laser'!N51,'FB Data'!A43:E191,3,FALSE)*'FB Laser'!M51,0) -> 0 | AK50: =IF(AJ50>75,"full-time",IF(AJ50>32.999,"partial","")) | AL50: =IF(AK50="partial",'FB Laser'!E51/60*35*0.5,IF(AK50="full-time",'FB Laser'!E51/60*35,0)) -> 0 | AM50: =ROUND(IFERROR(AL50/'FB Laser'!B51,0),2) -> 0 | AO50: =IFERROR(VLOOKUP('Tube Laser'!P50,'TL Data'!A43:E1268,3,FALSE)*'Tube Laser'!O50,0) -> 0 | AP50: =IF(AO50>75,"full-time",IF(AO50>32.999,"partial","")) | AQ50: =IF(AP50="partial",'Tube Laser'!D50/60/60*35*'Tube Laser'!B50*0.5,IF(AP50="full-time",'Tube Laser'!D50/60/60*35*'Tube Laser'!B50,0)) -> 0 | AR50: =ROUND(IFERROR(AQ50/'Tube Laser'!B50,0),2) -> 0 | AT50: =IFERROR('FB Laser'!J51*'FB Laser'!B51,"") | AU50: =IFERROR('Tube Laser'!L50*'Tube Laser'!B50,"")
... A98: PL316A36 | B98: PL 3/16" A36 | C98: 7.66 | D98: LBS/SQFT | E98: 1.25 | K98: {=INDIRECT(TEXT(MIN(IF(($L$9:$M$100<>"")*(COUNTIF($K$8:K97,$L$9:$M$100)=0),ROW($9:$100)*100+COLUMN($L:$M),7^8)),"R0C00"),)&""} | L98: =IF('FB Laser'!A99=0,"",'FB Laser'!A99) | M98: =IF('Tube Laser'!A98=0,"",'Tube Laser'!A98) | O98: {=INDIRECT(TEXT(MIN(IF(($P$9:$Q$100<>"")*(COUNTIF($O$8:O97,$P$9:$Q$100)=0),ROW($9:$100)*100+COLUMN($P:$Q),7^8)),"R0C00"),)&""} | P98: =IF('FB Laser'!F99="Yes",'FB Laser'!A99,"") | Q98: =IF('Tube Laser'!I98="Yes",'Tube Laser'!A98,"") | R98: =IFERROR(('FB Laser'!G99*'FB Laser'!B99),"") | S98: =IFERROR('FB Laser'!H99*'FB Laser'!B99,"") -> 0 | U98: =IFERROR(((((('Tube Laser'!D98)*'Tube Laser'!B98)/60)/60)*188.17)+(AE98*'Tube Laser'!B98),"") -> 0 | V98: =IFERROR(('Tube Laser'!N98*'Tube Laser'!B98)+(AE98*'Tube Laser'!B98)+(AF98*'Tube Laser'!B98)+(AG98*'Tube Laser'!B98)+('FB Data'!AH98*'Tube Laser'!B98),"") -> 0 | X98: =IFERROR(('Tube Laser'!D98*'Tube Laser'!B98)/60/60,"") -> 0 | AE98: =IF('Tube Laser'!E98="One Side",'Tube Laser'!J98*0.2,IF('Tube Laser'!E98="Both Sides",'Tube Laser'!J98*0.4,"0")) -> 0 | AF98: =IF('Tube Laser'!F98="Yes",'Tube Laser'!J98*0.1,0) -> 0 | AG98: =IF('Tube Laser'!G98>0,'Tube Laser'!J98*0.2,0) -> 0 | AH98: =IF('Tube Laser'!H98="Yes",'Tube Laser'!J98*0.1,0) -> 0 | AJ98: =IFERROR(VLOOKUP('FB Laser'!N99,'FB Data'!A91:E239,3,FALSE)*'FB Laser'!M99,0) -> 0 | AK98: =IF(AJ98>75,"full-time",IF(AJ98>32.999,"partial","")) | AL98: =IF(AK98="partial",'FB Laser'!E99/60*35*0.5,IF(AK98="full-time",'FB Laser'!E99/60*35,0)) -> 0 | AM98: =ROUND(IFERROR(AL98/'FB Laser'!B99,0),2) -> 0 | AO98: =IFERROR(VLOOKUP('Tube Laser'!P98,'TL Data'!A91:E1316,3,FALSE)*'Tube Laser'!O98,0) -> 0 | AP98: =IF(AO98>75,"full-time",IF(AO98>32.999,"partial","")) | AQ98: =IF(AP98="partial",'Tube Laser'!D98/60/60*35*'Tube Laser'!B98*0.5,IF(AP98="full-time",'Tube Laser'!D98/60/60*35*'Tube Laser'!B98,0)) -> 0 | AR98: =ROUND(IFERROR(AQ98/'Tube Laser'!B98,0),2) -> 0 | AT98: =IFERROR('FB Laser'!J99*'FB Laser'!B99,"") | AU98: =IFERROR('Tube Laser'!L98*'Tube Laser'!B98,"")
A99: PL316A57250 | B99: PL 3/16" A572-50 | C99: 7.66 | D99: LBS/SQFT | E99: 1.25 | K99: {=INDIRECT(TEXT(MIN(IF(($L$9:$M$100<>"")*(COUNTIF($K$8:K98,$L$9:$M$100)=0),ROW($9:$100)*100+COLUMN($L:$M),7^8)),"R0C00"),)&""} | O99: {=INDIRECT(TEXT(MIN(IF(($P$9:$Q$100<>"")*(COUNTIF($O$8:O98,$P$9:$Q$100)=0),ROW($9:$100)*100+COLUMN($P:$Q),7^8)),"R0C00"),)&""} | P99: =IF('FB Laser'!F100="Yes",'FB Laser'!A100,"") | Q99: =IF('Tube Laser'!I99="Yes",'Tube Laser'!A99,"") | R99: =IFERROR(('FB Laser'!G100*'FB Laser'!B100),"") -> 0 | S99: =IFERROR('FB Laser'!H100*'FB Laser'!B100,"") -> 0 | U99: =IFERROR(((((('Tube Laser'!D99)*'Tube Laser'!B99)/60)/60)*188.17)+(AE99*'Tube Laser'!B99),"") -> 0 | V99: =IFERROR(('Tube Laser'!N99*'Tube Laser'!B99)+(AE99*'Tube Laser'!B99)+(AF99*'Tube Laser'!B99)+(AG99*'Tube Laser'!B99)+('FB Data'!AH99*'Tube Laser'!B99),"") -> 0 | X99: =IFERROR(('Tube Laser'!D99*'Tube Laser'!B99)/60/60,"") -> 0 | AE99: =IF('Tube Laser'!E99="One Side",'Tube Laser'!J99*0.2,IF('Tube Laser'!E99="Both Sides",'Tube Laser'!J99*0.4,"0")) -> 0 | AF99: =IF('Tube Laser'!F99="Yes",'Tube Laser'!J99*0.1,0) -> 0 | AG99: =IF('Tube Laser'!G99>0,'Tube Laser'!J99*0.2,0) -> 0 | AH99: =IF('Tube Laser'!H99="Yes",'Tube Laser'!J99*0.1,0) -> 0 | AJ99: =IFERROR(VLOOKUP('FB Laser'!N100,'FB Data'!A92:E240,3,FALSE)*'FB Laser'!M100,0) -> 0 | AK99: =IF(AJ99>75,"full-time",IF(AJ99>32.999,"partial","")) | AL99: =IF(AK99="partial",'FB Laser'!E100/60*35*0.5,IF(AK99="full-time",'FB Laser'!E100/60*35,0)) -> 0 | AM99: =ROUND(IFERROR(AL99/'FB Laser'!B100,0),2) -> 0 | AO99: =IFERROR(VLOOKUP('Tube Laser'!P99,'TL Data'!A92:E1317,3,FALSE)*'Tube Laser'!O99,0) -> 0 | AP99: =IF(AO99>75,"full-time",IF(AO99>32.999,"partial","")) | AQ99: =IF(AP99="partial",'Tube Laser'!D99/60/60*35*'Tube Laser'!B99*0.5,IF(AP99="full-time",'Tube Laser'!D99/60/60*35*'Tube Laser'!B99,0)) -> 0 | AR99: =ROUND(IFERROR(AQ99/'Tube Laser'!B99,0),2) -> 0 | AT99: =IFERROR('FB Laser'!J100*'FB Laser'!B100,"") -> 0 | AU99: =IFERROR('Tube Laser'!L99*'Tube Laser'!B99,"") -> 0
A100: PL34A36 | B100: PL 3/4" A36 | C100: 30.63 | D100: LBS/SQFT | E100: 1.25 | K100: {=INDIRECT(TEXT(MIN(IF(($L$9:$M$100<>"")*(COUNTIF($K$8:K99,$L$9:$M$100)=0),ROW($9:$100)*100+COLUMN($L:$M),7^8)),"R0C00"),)&""} | O100: {=INDIRECT(TEXT(MIN(IF(($P$9:$Q$100<>"")*(COUNTIF($O$8:O99,$P$9:$Q$100)=0),ROW($9:$100)*100+COLUMN($P:$Q),7^8)),"R0C00"),)&""} | P100: =IF('FB Laser'!F101="Yes",'FB Laser'!A101,"") | Q100: =IF('Tube Laser'!I100="Yes",'Tube Laser'!A100,"") | R100: =IFERROR(('FB Laser'!G101*'FB Laser'!B101),"") -> 0 | S100: =IFERROR('FB Laser'!H101*'FB Laser'!B101,"") -> 0 | U100: =IFERROR(((((('Tube Laser'!D100)*'Tube Laser'!B100)/60)/60)*188.17)+(AE100*'Tube Laser'!B100),"") -> 0 | V100: =IFERROR(('Tube Laser'!N100*'Tube Laser'!B100)+(AE100*'Tube Laser'!B100)+(AF100*'Tube Laser'!B100)+(AG100*'Tube Laser'!B100)+('FB Data'!AH100*'Tube Laser'!B100),"") -> 0 | X100: =IFERROR(('Tube Laser'!D100*'Tube Laser'!B100)/60/60,"") -> 0 | AE100: =IF('Tube Laser'!E100="One Side",'Tube Laser'!J100*0.2,IF('Tube Laser'!E100="Both Sides",'Tube Laser'!J100*0.4,"0")) -> 0 | AF100: =IF('Tube Laser'!F100="Yes",'Tube Laser'!J100*0.1,0) -> 0 | AG100: =IF('Tube Laser'!G100>0,'Tube Laser'!J100*0.2,0) -> 0 | AH100: =IF('Tube Laser'!H100="Yes",'Tube Laser'!J100*0.1,0) -> 0 | AJ100: =IFERROR(VLOOKUP('FB Laser'!N101,'FB Data'!A93:E241,3,FALSE)*'FB Laser'!M101,0) -> 0 | AK100: =IF(AJ100>75,"full-time",IF(AJ100>32.999,"partial","")) | AL100: =IF(AK100="partial",'FB Laser'!E101/60*35*0.5,IF(AK100="full-time",'FB Laser'!E101/60*35,0)) -> 0 | AM100: =ROUND(IFERROR(AL100/'FB Laser'!B101,0),2) -> 0 | AO100: =IFERROR(VLOOKUP('Tube Laser'!P100,'TL Data'!A93:E1318,3,FALSE)*'Tube Laser'!O100,0) -> 0 | AP100: =IF(AO100>75,"full-time",IF(AO100>32.999,"partial","")) | AQ100: =IF(AP100="partial",'Tube Laser'!D100/60/60*35*'Tube Laser'!B100*0.5,IF(AP100="full-time",'Tube Laser'!D100/60/60*35*'Tube Laser'!B100,0)) -> 0 | AR100: =ROUND(IFERROR(AQ100/'Tube Laser'!B100,0),2) -> 0 | AT100: =IFERROR('FB Laser'!J101*'FB Laser'!B101,"") -> 0 | AU100: =IFERROR('Tube Laser'!L100*'Tube Laser'!B100,"") -> 0
